Workbook

Sheet План оплат
B2: 46121 | D2: Копилка б/н | E2: Б/н | F2: Нал | G2: Копилка нал | H2: факт нал | M2: Таблица заполняется до 10:00 Бухгалетерия/ Фин.служба
B3: Остатки на расчетных счетах | C3: 4778685 | D3: 200000 | E3: =C3+D3 | F3: 4358000 | H3: =F3+G3 | M3: Утверждается Управляющим Диреткором до 12:00
A4: =C3+H3+E4 | B4: План поступлений | E4: ='ДДС МЕСЯЦ'!V7+'ДДС МЕСЯЦ'!V8+'ДДС МЕСЯЦ'!V9+'ДДС МЕСЯЦ'!V12+'ДДС МЕСЯЦ'!V14+'ДДС МЕСЯЦ'!V18+'ДДС МЕСЯЦ'!V19 | F4: 0
A5: =E1131+E1132+E1133+E1134+E1135+E1136+E1137+F1131+F1132+F1133+F1134+F1135+F1136+F1137 | E5: план поступлений
B8: Дата | C8: Контрагент | D8: Назначение платежа | E8: Сумма Безнал. | F8: Сумма Нал. | G8: Сумма | H8: Статус | I8: Согласовано с Е.Е.
B9: 45813 | D9: Гугл диск | E9: 0 | F9: 30000 | G9: 30000 | H9: Отложено
B10: 45817 | C10: ИП Intellpack | D10: Ящики транспортировочные 100шт | E10: 419000 | F10: 0 | G10: 419000 | H10: Выплачено | M10: ЦЕНА ИЗМЕНИЛАСЬ
B11: 45818 | C11: Василий | D11: Ноутбук д/этикеровщика | E11: 0 | F11: 65000 | G11: 65000 | H11: Выплачено
B12: 45813 | D12: Закуп фруктов | E12: 0 | F12: 5465 | G12: 5465 | H12: Выплачено
B13: 45813 | D13: Форма силиконовая | E13: 0 | F13: 6400 | G13: 6400 | H13: Выплачено
B14: 45819 | D14: Миксер планетарный | E14: 270000 | G14: 270000 | H14: Отложено
B15: 45818 | C15: Расчет | D15: Уволенные сотрудники | E15: 0 | F15: 724000 | G15: 724000 | H15: Выплачено
B16: 45814 | D16: Вызывным катломойщицам | E16: 0 | F16: 24000 | G16: 24000 | H16: Выплачено
B17: 45814 | D17: ЗП Олеся | E17: 0 | F17: 2725000 | G17: 2725000 | H17: Выплачено
B18: 45783 | D18: Вызывные сотрудники | E18: 0 | F18: 120000 | G18: 120000 | H18: Выплачено
B19: 45817 | D19: Вернуть на кредитный счет | E19: 8000000 | F19: 0 | G19: 8000000 | H19: Выплачено
B20: 45817 | C20: Подотчет | D20: Бижанов Асылбек | E20: 0 | F20: 150000 | G20: 150000 | H20: Выплачено
B21: 45817 | C21: Отдел кадров | D21: Конц.товары и реклама | E21: 0 | F21: 25000 | G21: 25000 | H21: Отложено
B22: 45817 | D22: Принтер д/диспетчеров | E22: 272992 | F22: 0 | G22: 272992 | H22: Отложено
B23: 45817 | C23: Подотчет Есжановой Г | D23: Новый дизайн наклейки СЕГОДНЯ | E23: 0 | F23: 80000 | G23: 80000 | H23: Выплачено
B24: 45817 | D24: Гигрометр | E24: 150000 | F24: 0 | G24: 150000 | H24: Отложено
B25: 45817 | D25: Вызывные повара (пекарня,котломойка) | E25: 0 | F25: 87000 | G25: 87000 | H25: Выплачено
B26: 45817 | D26: Инвентарь | E26: 0 | F26: 740200 | G26: 740200 | H26: Отложено
B27: 45817 | C27: отложить | D27: на подключение ТП (шкаф, кабеля и тд) | E27: 2000000 | F27: 0 | G27: 2000000 | H27: Отложено
B28: 45818 | D28: ЗП Ковешниковой Зои | E28: 0 | F28: 1533571 | G28: 1533571 | H28: Выплачено
B29: 45818 | C29: на карточку сотрудникам | D29: Офицальное зп | E29: 13933776 | F29: 0 | G29: 13933776 | H29: Выплачено
B30: 45818 | C30: Подотчет | D30: Ли Станислав | E30: 0 | F30: 300000 | G30: 300000 | H30: Выплачено
B31: 45820 | C31: Вон С | D31: Инвентарь | E31: 0 | F31: 200000 | G31: 200000 | H31: Отложено
B32: 45818 | C32: Сон Сергей | D32: Штрих коды по курсу 6,45*8000 рубль | E32: 0 | F32: 51600 | G32: 51600 | H32: Выплачено
B33: 45818 | C33: Сырье | D33: Оплата по поставщикам | E33: 10434810 | F33: 0 | G33: 10434810 | H33: Выплачено
B34: 45819 | C34: Исполнительные листы | D34: ЧСИ по сотрудникам | E34: 573335 | F34: 0 | G34: 589785 | H34: Выплачено
B35: 45819 | C35: снимаем со счета | D35: на копилку 2 млн, на зп 2 млн | E35: 0 | F35: 4000000 | G35: 4000000 | H35: Выплачено
B36: 45819 | C36: Сырье | D36: Оплата по поставщикам (вторая часть) | E36: 8000000 | F36: 0 | G36: 9102655 | H36: Выплачено
B37: 45819 | D37: Стерилезатор | E37: 84800 | F37: 0 | G37: 84800 | H37: Выплачено
B38: 45819 | C38: Рынок | D38: Инвентарь д/кондитерки | E38: 0 | F38: 150000 | G38: 150000 | H38: Выплачено
B39: 45819 | D39: Светлана | F39: 140000 | G39: 140000 | H39: Выплачено
B40: 45819 | C40: Подотчет | D40: Ли Станислав | F40: 300000 | G40: 300000 | H40: Выплачено
B41: 45819 | C41: ч-з Арнур (на каспий ФЛ) | D41: Установка счетчика | F41: 220000 | G41: 220000 | H41: Выплачено
B42: 45819 | D42: Уволенные сотрудники | F42: 573014 | G42: 573014 | H42: Выплачено
B43: 45819 | C43: Подотчет | D43: Сон С | F43: 100000 | G43: 100000 | H43: Выплачено
B44: 45820 | C44: ЗП | D44: Лагманщики и сушист/Зкльфия и Муратбек | F44: 1643000 | G44: 1643000 | H44: Выплачено
B45: 45820 | C45: Подотчет | D45: Ли Станислав | F45: 600000 | G45: 600000 | H45: Выплачено
B46: 45821 | C46: Аванс по служебке | D46: Абдраманова Айгуль | F46: 150000 | G46: 150000 | H46: Выплачено
B47: 45821 | D47: Уволенные сотрудники | F47: 1000000 | G47: 1270482 | H47: Выплачено
B48: 45821 | D48: Оплата по поставщикам | E48: 15000000 | G48: 8032663 | H48: Выплачено
B49: 45821 | C49: Сон С | D49: Аренда квартир | F49: 350000 | H49: Выплачено
B50: 45821 | C50: Тараз | D50: Мед | F50: 322700 | G50: 322700 | H50: Выплачено
B51: 45821 | C51: Рынок | D51: Инвентарь д/пекарни | F51: 150000 | G51: 150000 | H51: Выплачено
B52: 45824 | D52: Гигрометр | E52: 150000 | G52: 150000 | H52: Отложено | K52: запрашивала Перизат,Василий,Асылбек,Сергей
B53: 45824 | D53: Установка счетчика | F53: 500000 | G53: 500000 | H53: Выплачено
B54: 45824 | C54: Дядь Эрик | D54: Салаты | F54: 517000 | G54: 600000 | H54: Выплачено
B55: 45824 | D55: Битрикс | E55: 147360 | G55: 147360 | H55: Выплачено
B56: 45824 | C56: Отдел кадров | D56: Шкаф д/папок | G56: 50000 | H56: Выплачено
B57: 45824 | C57: Узбеков | D57: Аренда квартир | F57: 350000 | G57: 350000 | H57: Выплачено
B58: 45824 | D58: Зп сотрудникам | F58: 4275124 | G58: 4275124 | H58: Выплачено
B59: 45793 | D59: Оплата по поставщикам | E59: 3292436 | G59: 3292436 | H59: Выплачено
B60: 45825 | C60: ОС | D60: Мармит | E60: 70000 | G60: 70000 | H60: Отложено
B61: 45825 | C61: Подотчет | D61: Ли Станислав | F61: 300000 | G61: 300000 | H61: Выплачено
B62: 45825 | C62: Технолог | D62: Инвентарь и рамки | F62: 100000 | G62: 100000 | H62: Отложено
B63: 45825 | C63: ИП Алексеевское | D63: Пищевые отходы | E63: 100000 | G63: 100000 | H63: Выплачено
B64: 45825 | C64: Отдел кадров | D64: Размещение рекламы | F64: 20000 | G64: 20000 | H64: Выплачено
B65: 45826 | D65: Зп сотрудникам | F65: 10755546 | G65: 10755546 | H65: Выплачено
B66: 45826 | D66: Оплата по поставщикам | E66: 12000000 | G66: 12283607 | H66: Выплачено
B67: 45826 | C67: Экспрес-сервис | D67: Аренда | E67: 6050000 | G67: 6050000 | H67: Выплачено
B68: 45826 | C68: Стас | F68: 300000 | G68: 300000 | H68: Выплачено
B69: 45827 | D69: Зп сотрудникам | F69: 4612250 | G69: 4612250 | H69: Выплачено
B70: 45827 | D70: Оплата по поставщикам | E70: 4428595 | G70: 4443666.5 | H70: Выплачено
B71: 45827 | C71: Вызывные | D71: Тех персонал | F71: 36000 | G71: 108000 | H71: Выплачено
B72: 45827 | C72: Возврат | D72: По служебке | F72: 2966 | G72: 2966 | H72: Выплачено
B73: 45827 | C73: Асылбек | D73: Ремонт и настройки морозильников | E73: 120000 | G73: 120000 | H73: Выплачено
B74: 45827 | C74: Ли Станислав | D74: Рынок | F74: 600000 | G74: 600000 | H74: Выплачено
B75: 45827 | C75: Богомол | D75: Охрана | E75: 600240 | G75: 600240 | H75: Выплачено
B76: 45827 | C76: Подотчет | D76: Асылбек | F76: 100000 | G76: 100000 | H76: Выплачено
B77: 45828 | C77: APF service | D77: Вывоз мусора | E77: 508200 | G77: 508200 | H77: Выплачено
B78: 45828 | D78: Оплата по поставщикам | E78: 14281800 | G78: 14281800 | H78: Выплачено
B79: 45828 | D79: Уволенные сотрудники | F79: 1603912 | G79: 1603912 | H79: Выплачено
B80: 45828 | C80: Торговый дизайн | D80: Миксер планетарный | E80: 343492 | G80: 343492 | H80: Выплачено
B81: 45828 | C81: Craft | D81: Форма д/сотрудников | E81: 270000 | G81: 270000 | H81: Выплачено
B82: 45463 | C82: Ремонт бытовой техники | D82: Ремонт микросхемы | E82: 8000 | G82: 8000 | H82: Выплачено
B83: 45828 | C83: Mega service | D83: Ремонт весов | E83: 35000 | G83: 35000 | H83: Выплачено
B84: 45828 | C84: CRIND | D84: Заточка ножей | E84: 9000 | G84: 9000 | H84: Выплачено
B85: 45828 | C85: ИП Ни Н.Г. | D85: Ремонт агрегата Фасовка | E85: 25000 | G85: 25000 | H85: Выплачено
B86: 45828 | C86: Россия | D86: Контейнер от Бластора | E86: 1227717 | G86: 1227717 | H86: Выплачено
B87: 45828 | C87: Счет предоставят завтра | D87: Агрегатор на новую морозильную камеру | E87: 4000000 | G87: 4000000 | H87: Отложено
B88: 45831 | C88: Ибрайханов Муратбек | D88: Квартира с 20 по 30 июня | F88: 25000 | G88: 25000 | H88: Выплачено
B89: 45831 | C89: ANT S | D89: Принтер д/диспетчеров | E89: 251630 | G89: 251630 | H89: Выплачено
B90: 45831 | D90: Налог за май | E90: 8144089 | H90: Выплачено
B91: 45831 | D91: Дезинфекция | E91: 145000 | H91: Выплачено
B92: 45831 | C92: Тех персонал | D92: Вызывные | F92: 36000 | G92: 36000 | H92: Выплачено
B93: 45831 | D93: Зп сотрудникам | F93: 2911238 | G93: 2911238 | H93: Выплачено
B94: 45831 | C94: Кафе софт | D94: Выгрузка | E94: 79200 | G94: 79200 | H94: Выплачено
B95: 45832 | D95: Оплата по поставщикам | E95: 10201856 | G95: 10201856 | H95: Выплачено
B96: 45832 | D96: Зп сотрудникам | F96: 353000 | G96: 353000 | H96: Выплачено
B97: 45832 | C97: Стас | D97: Рынок | F97: 300000 | G97: 300000 | H97: Выплачено
B98: 45832 | C98: Elevator Servise ремонт лифта | E98: 75000 | G98: 75000 | H98: Выплачено
B99: 45832 | C99: Очистка жироуловителя | F99: 40000 | G99: 40000 | H99: Выплачено
B100: 45833 | C100: Гузя | D100: Закуп д/тортов | F100: 15200 | G100: 15200 | H100: Выплачено
B101: 45833 | C101: Стас | D101: Рынок | F101: 300000 | G101: 300000 | H101: Выплачено
B102: 45833 | C102: Квартира | D102: аренда | F102: 350000 | G102: 350000 | H102: Выплачено
B103: 45833 | C103: Асылбек | D103: На приобретение необходимых | F103: 250000 | G103: 250000 | H103: Выплачено
...

Sheet Банки всех ТОО и ИП
A1: Контакт ведущего менеджера по банку (ИМЯ, телефон) | B1: Наименование ТОО/ИП | C1: Банк | D1: Подписант | E1: Механика подписания | F1: Владелец счёта | G1: Директор | H1: На кого есть доверенность | I1: Доступ Бух просмотра и выставления счетов | J1: Комментарии
A2: 2323 | B2: ТОО "Фуд завод" | C2: Каспи | D2: Ольга и Олеся | E2: on-line, приложение | F2: Эрик Цой | G2: Эрик Цой | H2: Олеся | I2: Бухгалтерия предприятия, открывает доступ Ольга | J2: снятие Акерке, создание платежей Я и Акерке
A3: Эльвира, 8-705-182-05-05 | B3: ТОО "Фуд завод" | C3: Жусан | D3: Ольга и Олеся | E3: on-line | F3: Эрик Цой | G3: Эрик Цой | H3: Олеся | I3: Бухгалтерия предприятия, открывает доступ Ольга | J3: создает платежки зарплатный бухгалтер через этот счет оплачивает исполнительный лист
A4: Лия, 8-775-133-21-96 | B4: ТОО "Фуд завод" | C4: РБК | D4: Ольга и Олеся | E4: on-line, через ОТП ключ, ключ у Акерке. Вход чепрез логин и пароль на сайт банка. эцп? | F4: Эрик Цой | G4: Эрик Цой | H4: Олеся | I4: Бухгалтерия предприятия, открывает доступ Ольга | J4: Акерке на создание и снятие через пароль и ключ ОТП
A5: риск | B5: ИП Айдана (ТОО "Фуд завод") | C5: Каспи | D5: Ольга и Олеся | E5: on-line | F5: Айдана | G5: Айдана | H5: Айдана и Акерке | I5: Бухгалтерия предприятия, открывает доступ Ольга | J5: создает Акерке
A6: риск | B6: ИП Сапакова (КБ) | C6: Каспи | D6: Айдана | E6: on-line | F6: Айгерим | H6: Айдана | J6: создает Акерке
A7: риск | B7: ИП Сапакова (КБ) | C7: Нур Банк | D7: Айдана | E7: on-line | F7: Айгерим | H7: Айдана | J7: ключи достпупа есть у нас в бухгалтерии вместе в ключом от подписи, может просматривать Юрий
A8: риск | B8: ТОО Армидейл | C8: Каспи | D8: Айдана+Акерке (до 01.06.26) | E8: on-line | F8: Армен | H8: Акерке, Айдана | J8: Акерке создает платежи и снимает деньги
A9: риск | B9: ТОО На районе Crave (Жетысу) | C9: Каспи | D9: Айдана | E9: on-line | F9: Артём | H9: Айдана, Акерке | J9: Акерке создает платежи и снимает деньги
B10: ТОО Кристалфрайз | C10: Каспи | D10: Ольга и Олеся | E10: on-line | F10: Малышев С | G10: Малышев С | H10: Ольга и Олеся | I10: Бухгалтерия предприятия, открывает доступ Ольга | J10: создает и подписывает Айгерим Сапакова
B11: ТОО "Фуд завод Астана" | C11: Каспий | D11: Олеся | E11: on-line | F11: Олеся Сергеевна | G11: Олеся Сергеевна | H11: -
B12: ТОО "Фуд завод Астана" | C12: БЦК | D12: Олеся | E12: on-line | F12: Олеся Сергеевна | G12: Олеся Сергеевна | H12: -
B13: ТОО "Фуд завод Астана" | C13: Форте | D13: Олеся | E13: on-line | F13: Олеся Сергеевна | G13: Олеся Сергеевна | H13: - | J13: надо организовтаь доступ к форте онлайн
B14: ТОО "Фуд завод Астана" | C14: Фридом | D14: Олеся

Sheet ДЕНЬ ОПЛАТ
B1: ПРОСТАВЬТЕ ДАТУ
B2: 46202 | C2: Остаток на начало | D2: Поступление | E2: Выбытие | F2: Остаток на конец | H2: Оплата поставщикам | N2: ОПИУ на 25.06.2026
B3: Расчётный счёт | C3: =12786388-C4-C5 | D3: =SUMIF(B11:B260,B2,E11:E260) | E3: =SUMIF(B265:B722,B2,E265:E722) | F3: =C3+D3-E3 | H3: 01.06-07.06.2026 | I3: 08.06-14.06.2026 | J3: 15.06-21.06.2026 | K3: 22.06-28.06.2026 | L3: 29.06-30.06.2027 | M3: сумма, средний %
B4: Касса | C4: 2008321 | D4: =SUMIF(B11:B262,B2,D10:D262) | E4: =SUMIF(B266:B723,B2,D266:D723) | F4: =C4+D4-E4 | G4: гашение КЗ | H4: =34458818+964000 | I4: =25257596+4303979+241995 | J4: =24398148+4556056 | K4: =27832950+2576580+718145 | L4: 1 | M4: =I4+J4+K4+L4+H4 | N4: 114121764
B5: Копилка | C5: 9800000 | G5: выручка | H5: 49606340 | I5: 72681513 | J5: 60988297 | K5: =45642381 | L5: 1 | M5: =I5+J5+K5+L5+H5 | N5: 231572946
B6: ИТОГО | C6: =C5+C4+C3 | D6: =D3+D4+D5 | E6: =E3+E4+E5 | F6: =F3+F4+F5 | G6: % от выручки | H6: =H4/H5 | I6: =I4/I5 | J6: =J4/J5 | K6: =K4/K5 | L6: =L4/L5 | M6: =AVERAGE(I6:L6) | N6: =N4/N5
K8: -28825915
B9: Поступления | K9: -2876580
B10: Дата | C10: Наименование контрагента | D10: Наличный | E10: Безналичный | F10: Комментарий | K10: -718145
B11: 46128 | C11: ДФЗ | E11: 2000000
B12: 46128 | C12: Яндекс | E12: 3964105
B13: 46128 | C13: Даркстор | E13: 1000000
B14: 46128 | C14: Фуд Вендинг | D14: 1500000
B15: 46128 | C15: RP | E15: 5000000
B16: 46128 | C16: Wolf | E16: =18644+27718
B17: 46128 | C17: Базилик | E17: 675750
B18: 46129 | C18: Crave | E18: 800000
B19: 46129 | C19: DQ | E19: 672552
B20: 46129 | C20: ДФЗ | E20: 5000000
B21: 46129 | C21: KASPI | E21: 1500000
B22: 46132 | C22: ДФЗ | E22: 11327800
B23: 46133 | C23: KASPI | E23: 900000
B24: 46133 | C24: ДФЗ | E24: 5305000
B25: 46133 | C25: Яндекс | E25: 7664529
B26: 46133 | C26: Базилик | E26: 979348
B27: 46134 | C27: Wolf | E27: 143759
B28: 46134 | C28: KASPI | E28: 1400000
... B31: 46135 | C31: ДФЗ | E31: 2530000
B32: 46135 | C32: Фуд Вендинг
B33: 46135 | C33: Wolf | E33: 29839
B34: 46135 | C34: Базилик | E34: 588058
B35: 46135 | C35: Бобух | E35: =337625+75706
B36: 46135 | C36: KASPI | E36: 1400000
B37: 46136 | C37: Алга | E37: 1000000
B38: 46136 | C38: ДФЗ | E38: 4880000
B39: 46136 | C39: KASPI | E39: 1500000
B40: 46136 | C40: Фуд Вендинг | D40: 1500000
B41: 46136 | C41: Бобух | E41: 84839
B42: 46136 | C42: Базилик | E42: 869592
B43: 46136 | C43: DSF | E43: 2000000
B44: 46139 | C44: ДФЗ | E44: 11900000 | I44: Пикассо (актуализировать долг, брали продукт)
B45: 46139 | C45: KASPI | E45: 1500000 | I45: Элипс (логистическая компания)
B46: 46140 | C46: ДФЗ | E46: 5540000 | I46: АЛИШЕР (AL-Group) | J46: 1,2 млн.тенге
B47: 46140 | C47: Базилик | E47: 676067 | I47: ЛУКОЙЛ (ТОО АЛГА) | J47: 3,3 млн.тенге
B48: 46140 | C48: Яндекс | E48: 8092147 | I48: всех мелких-прошерстить
B49: 46140 | C49: МайМарт | E49: 2000000 | I49: ДФЗ (остаток)
B50: 46140 | C50: DSF | E50: 2000000
B51: 46140 | C51: ЧЛ | E51: =38200+7000
B52: 46140 | C52: Глово | E52: 762501
B53: 46141 | C53: ДФЗ | E53: 1302000
B54: 46141 | C54: Wolf | E54: 106776
B55: 46141 | C55: KASPI | E55: 300000
B56: 46141 | C56: Crave | E56: 400000
B57: 46141 | C57: ЧЛ | E57: =3000+7500
B58: 46142 | C58: Яндекс | E58: 8000000
B59: 46142 | C59: ДФЗ | E59: 2000000
B60: 46142 | C60: RP | E60: 5000000
B61: 46142 | C61: Даркстор | E61: 1000000
B62: 46146 | C62: ДФЗ | E62: 16295000
B63: 46146 | C63: Базилик 2, Базилик 5 | E63: 2218910
B64: 46146 | C64: KASPI | E64: 1500000
B65: 46146 | C65: CRAVE | E65: =600000+27107
B66: 46146 | C66: ЧЛ | E66: =10800+91846
B67: 46147 | C67: 85-ТОО Д.Ф.З. | E67: 4500000
B68: 46147 | C68: 110 АЗС "Sinooil" | E68: 185519
B69: 46147 | C69: 111 ТОО ГЛОВО ОСНОВНОЙ | E69: 641457
B70: 46147 | C70: 113-Wolt Services Kazakhstan | E70: 385362
B71: 46147 | C71: 556-Romantic (торты) Махамбетов Акзер | E71: 333200
B72: 46147 | C72: 102-Яндекс лавка ОСНОВНОЙ | E72: 7293368
B73: 46147 | C73: 110 АЗС "Sinooil" | E73: 1242000
B74: 46147 | C74: KASPI | E74: 1600000
B75: 46147 | C75: 1-Базилик 1 (Шевченко) | E75: 809110
B76: 46147 | C76: ЧЛ | E76: =28809+9000
B77: 46148 | C77: 85-ТОО Д.Ф.З. | E77: =1170000+500000
B78: 46148 | C78: 108-GO Market KRG ИП | E78: 340088
B79: 46148 | C79: 7-Kaspi Банк | E79: 1200000
B80: 46148 | C80: 103-Бобух ИП | E80: 89394
B81: 46148 | C81: 558- ТРИО Romantic (торты) | E81: 84000
B82: 46148 | C82: ЧЛ | E82: 14000
B83: 46149 | C83: Олив | E83: 1500000
B84: 46149 | C84: Ник и Ко | E84: 1647000
B85: 46150 | C85: 112 PRO OIL SERVICE ИП г. Талгар, с. Кендала, ул. Смыкова д.118 (LUKOIL) | E85: 81893
B86: 46150 | C86: 85-ТОО Д.Ф.З. (дистрибьютор) | E86: 5600000
B87: 46150 | C87: 85-ТОО Д.Ф.З. (дистрибьютор) | E87: 4900000
B88: 46150 | C88: 558- ТРИО Romantic (торты) Нурлыбаев Алибек | E88: 86800
B89: 46150 | C89: 85-ТОО Д.Ф.З. (дистрибьютор) | E89: 1500000
... B102: 46155 | C102: Crave | E102: 1500000
B103: 46155 | C103: 0Частное | D103: =25000
B104: 46156 | C104: 102-Яндекс лавка ОСНОВНОЙ | E104: 4779295
B105: 46156 | C105: 85-ТОО Д.Ф.З. (дистрибьютор) | E105: 2800000
B106: 46156 | C106: 99-RP АЗС основной | E106: 7000000
B107: 46157 | C107: 1-Базилик 1 (Шевченко) | E107: 909 275
B108: 46157 | C108: 7-Kaspi Банк (Склад ГП) | E108: 500 000
B109: 46157 | C109: 113-Wolt Services Kazakhstan ОСНОВНОЙ | E109: 110776
B110: 46157 | C110: 105-Алга экспресс ОСНОВНОЙ | E110: 500000
B111: 46157 | C111: 85-ТОО Д.Ф.З. (дистрибьютор) | E111: 4950000
B112: 46157 | C112: 90-Маймарт | E112: 2 000 000
B113: 46160 | C113: 556-Romantic (торты) Махамбетов Акзер | E113: 294000
B114: 46160 | C114: 85-ТОО Д.Ф.З. (дистрибьютор) | E114: 10522000
B115: 46161 | C115: 102-Яндекс лавка ОСНОВНОЙ | E115: 8461065
...

Sheet Неделя ОПЛАТ 
B1: ПРОСТАВЬТЕ неделю
B2: 1 | C2: Остаток на начало | D2: Поступление | E2: Выбытие | F2: Остаток на конец | H2: Оплата поставщикам | N2: ОПИУ на 25.06.2026
A3: 01.07.2026 (1нед, вкл. 29,30.26) | B3: Расчётный счёт | C3: 0 | D3: =SUMIF(B11:B121,B2,E11:E121) | E3: =SUMIF(B126:B447,B2,E126:E447) | F3: =C3+D3-E3 | H3: 01.06-07.06.2026 | I3: 08.06-14.06.2026 | J3: 15.06-21.06.2026 | K3: 22.06-28.06.2026 | L3: 29.06-30.06.2027 | M3: сумма, средний %
A4: 06.07.2026 (2нед) | B4: Касса | C4: 0 | D4: =SUMIF(B11:B123,B2,D10:D123) | E4: =SUMIF(B127:B448,B2,D127:D448) | F4: =C4+D4-E4 | G4: гашение КЗ | H4: =34458818+964000 | I4: =25257596+4303979+241995 | J4: =24398148+4556056 | K4: =27832950+2576580+718145 | L4: 1 | M4: =I4+J4+K4+L4+H4 | N4: 114121764
A5: 13.07.2026 (3нед) | B5: Копилка | C5: 0 | G5: выручка | H5: 49606340 | I5: 72681513 | J5: 60988297 | K5: =45642381 | L5: 1 | M5: =I5+J5+K5+L5+H5 | N5: 231572946
A6: 20.07.2026 (4 нед) | B6: ИТОГО | C6: =C5+C4+C3 | D6: =D3+D4+D5 | E6: =E3+E4+E5 | F6: =F3+F4+F5 | G6: % от выручки | H6: =H4/H5 | I6: =I4/I5 | J6: =J4/J5 | K6: =K4/K5 | L6: =L4/L5 | M6: =AVERAGE(I6:L6) | N6: =N4/N5
A7: 27.07.2026 (5 нед)
K8: -28825915
B9: Поступления | K9: -2876580
B10: Дата | C10: Наименование контрагента | D10: Наличный | E10: Безналичный | F10: Комментарий | K10: -718145
B11: 1 | C11: 85-ДФЗ (дистрибьютор) | E11: 22250000
B12: 1 | C12: 102-Яндекс лавка ОСНОВНОЙ | E12: 14000000
B13: 1 | C13: 7-Kaspi Банк (Склад ГП) | E13: 5000000
B14: 1 | C14: 99-RP АЗС основной | E14: 8000000
B15: 1 | C15: 96-ТОО DSF (дистрибьютор) | E15: 8000000
B16: 1 | C16: 2-Базилик 2 (Желтоксан) | E16: 1500000
B17: 1 | C17: 1-Базилик 1 (Шевченко) | E17: 1300000
B18: 1 | C18: 111 ТОО ГЛОВО ОСНОВНОЙ | E18: 1000000
B19: 1 | C19: 90-Маймарт | E19: 1000000
B20: 1 | C20: 0Частное лицо Покупатель | E20: 1000000
B21: 1 | C21: 110 АЗС "Sinooil" ШЫМКЕНТ | E21: 500000
B22: 1 | C22: 108-GO Market KRG ИП ОСНОВНОЙ | E22: 500000
... B82: 5 | C82: 558- ТРИО Romantic (торты) Нурлыбаев Алибек | E82: 260000
B124: Выбытие
B125: Дата | C125: Основание | D125: Наличный | E125: Безналичный | F125: Комментарий
B126: 46121 | C126: Бригадиру Болатбек Даулету | D126: 50000 | F126: Выплачено
B127: 46121 | C127: ЗП | E127: 15223109 | F127: Выплачено
B128: 46121 | C128: закуп сырьё | E128: 1776000 | F128: Выплачено
B129: 46121 | C129: ЗП лагманщикам | D129: 306000 | F129: Выплачено
B130: 46121 | C130: Ли Станислав | D130: 600000 | F130: Выплачено
B131: 46121 | C131: Дорожные | D131: 9000 | F131: Выплачено
B132: 46122 | C132: ОСТАТОК КПН | E132: 1104937 | F132: Выплачено
B133: 46122 | C133: ЗП Уволеных | D133: 2393824 | F133: Выплачено
B134: 46122 | C134: На размещение платных объявлений | D134: 20000 | F134: Выплачено
B135: 46122 | C135: Дизайнер РП (2 тейбл тента) | D135: 14000 | F135: Выплачено
B136: 46122 | C136: ЗП 5 сотрудникам они получает до 12 число | D136: 1251000 | F136: К оплате
B137: 46122 | C137: вызов ассенизаторской 2 машины | D137: 50000 | F137: Выплачено
B138: 46122 | C138: за оплату почты | D138: 107000 | F138: Выплачено
B139: 46122 | C139: Оплата за логистику Демьянов | D139: 300000 | F139: Выплачено
B140: 46122 | C140: Даулет, нач. производства ЗП | D140: 1281165 | F140: Выплачено
B141: 46122 | C141: Астана | D141: 120000 | F141: К оплате
B142: 46122 | C142: закуп сырьё | E142: 3778100 | F142: Выплачено
B143: 46122 | C143: Веб касса | D143: 8200 | F143: Выплачено
B144: 46125 | C144: Герасименко (аренда+депозит за кв) | D144: =390000+150000 | F144: Выплачено
B145: 46125 | C145: Тоймарт | D145: 390 344 | F145: Выплачено
B146: 46125 | C146: ЗАКУП СЫРЬЁ (безнал) | E146: 6263921 | F146: Выплачено
B147: 46125 | C147: Ayala Trade ТОО творг | E147: 416500 | F147: Выплачено
B148: 46125 | C148: квартира Узбеков | D148: 300000 | F148: Выплачено
B149: 46125 | C149: Сергей Сон ЗП март (часть) | D149: 54600 | F149: Выплачено
B150: 46125 | D150: 1000000 | F150: Выплачено
B151: 46125 | C151: Ахмерова | E151: 110160 | F151: Выплачено
B152: 46125 | C152: Эрик Капуста | D152: 138400 | F152: Выплачено | G152: повтор
B153: 46125 | C153: ИП Демьянов | E153: 1870000 | F153: Выплачено
B154: 46126 | C154: Ли Станислав | D154: 1000000 | F154: Выплачено
B155: 46126 | C155: аванс по СЗ | D155: 150000 | F155: Выплачено
B156: 46126 | C156: за Нотариуса | D156: 10813 | F156: Выплачено
B157: 46126 | C157: Закуп сырьё | E157: 9125564 | F157: Выплачено
B158: 46126 | C158: Силиконовые шторы | E158: 31000 | F158: Выплачено
B159: 46126 | C159: Лампы | F159: К оплате
B160: 46126 | C160: Масло подсолнечное | E160: 120000 | F160: К оплате
B161: 46127 | C161: Компенсация бензина (РОП) вчера не была деньги | D161: 35000 | F161: Выплачено | G161: создать приказ
B162: 46127 | C162: Аренда помещения | E162: 6655000 | F162: Выплачено
B163: 46127 | C163: аванс по СЗ | D163: 100000 | F163: Выплачено
B164: 46127 | C164: Заиров Расулжан ЗП по Сз | D164: 369 000 | F164: Выплачено
B165: 46127 | C165: Исполнителный лист | E165: 800 000 | F165: Выплачено | G165: что входит
B166: 46127 | C166: Public Health Inspection | E166: 144 800 | F166: Выплачено
B167: 46127 | C167: ТОО Horeca Guardian | E167: 340 000 | F167: Выплачено
B168: 46127 | C168: Ли Станислав | D168: 500 000 | F168: Выплачено
B169: 46127 | C169: Дашида | D169: 437200 | F169: Выплачено
B170: 46127 | C170: Закуп сырьё | E170: 5000000 | F170: К оплате
B171: 46128 | C171: аванс по СЗ | D171: 150000 | F171: Выплачено
B172: 46128 | C172: ЗП лагманщикам | D172: 316000 | F172: Выплачено
B173: 46128 | C173: Ли Станислав | D173: 700 000 | F173: Выплачено
B174: 46128 | C174: Закуп сырьё | E174: 5526012 | F174: Выплачено
B175: 46128 | C175: Логистика АСТАНА (выдать Александру) | D175: 54000 | F175: Выплачено
B176: 46128 | C176: Оплата дизайнеру | D176: 50000 | F176: Выплачено
B177: 46128 | C177: Аванс Барататова | D177: 150000 | F177: Выплачено
B178: 46128 | C178: Аванс Худобаева | D178: 100000 | F178: Выплачено
B179: 46128 | C179: Каталоги | E179: 15 760 | F179: Выплачено
B180: 46129 | C180: Ли Станислав | D180: 500 000 | F180: Выплачено
B181: 46129 | C181: Шашубаева | D181: 50 000 | F181: Выплачено
B182: 46129 | C182: удержание с логистической компании | D182: 56 939 | F182: Выплачено
B183: 46129 | C183: установка окна для курьера | D183: 80 000 | F183: Выплачено
B184: 46129 | C184: Аванс Имашев Улан | D184: 300 000 | F184: Выплачено
B185: 46129 | C185: Аванс Шишериной М.С | D185: 110 000 | F185: Выплачено
B186: 46129 | C186: Отложить на ЗП | E186: 10000000 | F186: К оплате
B187: 46129 | C187: Закуп сырьё утро | D187: 126000 | E187: 3680180 | F187: Выплачено
B188: 46129 | C188: Аренда квартиры ф.дир (19.04-19.05) | D188: 390000 | F188: Выплачено
B189: 46129 | C189: Закуп сырьё вечер | E189: =2000000+300000+263625 | F189: Выплачено
B190: 46129 | C190: ЗП уволенных | D190: 2600000 | F190: Выплачено
B191: 46132 | C191: Айран и Газ балон | D191: 48600 | F191: Выплачено
B192: 46132 | C192: Оплата за разработку логотипа | E192: 1000000 | F192: Выплачено
B193: 46132 | C193: Ноутбук | D193: 173446 | F193: Выплачено
B194: 46132 | C194: ЗП | D194: =17826000+369000 | F194: Выплачено
B195: 46132 | C195: Закуп сырьё вечер | D195: 427620 | E195: 1886893 | F195: Выплачено
B196: 46133 | C196: Закуп сырьё | E196: 4040634 | F196: Выплачено
B197: 46133 | C197: Зарплата не весь остаток (производство) | D197: 5961267 | F197: Выплачено
B198: 46133 | C198: Оплата грузчикам | D198: 24000 | F198: Выплачено
B199: 46133 | C199: Ли Станислав | D199: 500000 | F199: Выплачено
B200: 46134 | C200: Култаева Жадыра За лекарства по СЗ | D200: 60329 | F200: Выплачено
...

Sheet ДДС НЕДЕЛЬН.
C1: 46202 | D1: 46203 | E1: 46204 | F1: 46205 | G1: 46206 | H1: 1неделя | I1: 46209 | J1: 46210 | K1: 46211 | L1: 46212 | M1: 46213 | N1: 46216 | O1: 46217 | P1: 46218 | Q1: 46219 | R1: 46220 | S1: 46223 | T1: 46224 | U1: 46225 | V1: 46226 | W1: 46227 | X1: 46230 | Y1: 46231 | Z1: 46232 | AA1: 46233 | AB1: 46234
C2: понедельник | D2: вторник | E2: среда | F2: четверг | G2: пятница | I2: понедельник | J2: вторник | K2: среда | L2: четверг | M2: пятница | N2: понедельник | O2: вторник | P2: среда | Q2: четверг | R2: пятница | S2: понедельник | T2: вторник | U2: среда | V2: четверг | W2: пятница | X2: понедельник | Y2: вторник | Z2: среда | AA2: четверг | AB2: пятница | AC2: прирост 18% к факту апреля
C3: 46202 | D3: 46203 | E3: =E1 | F3: =F1 | G3: =G1 | I3: =I1 | J3: =J1 | K3: =K1 | L3: =L1 | M3: =M1 | N3: =N1 | O3: =O1 | P3: =P1 | ... AB3: =AB1 | AC3: Итого план | AD3: Итого факт | AE3: Отклонение
C4: План | D4: План | E4: План | F4: План | G4: План | I4: План | J4: План | K4: План | L4: План | M4: План | N4: План | O4: План | P4: План | Q4: План | R4: План | AA4: =Z80 | AB4: =AA80
A5: Остаток на начало по Банку | C5: 5000000 | D5: =C81 | E5: =D81 | F5: =E81 | G5: =F81 | H5: =G5 | I5: =G81 | J5: =I81 | K5: =J81 | L5: =K81 | M5: =L81 | N5: =M81 | O5: =N81 | P5: =O81 | Q5: =P81 | ... AB5: =AA81 | AC5: =#REF! | AD5: =AC5 | AE5: =AD5-AC5
A6: Остаток на начало по Кассе | C6: 5000000 | D6: =C82 | E6: =D82 | F6: =E82 | G6: =F82 | H6: =G6 | I6: =G82 | J6: =I82 | K6: =J82 | L6: =K82 | M6: =L82 | N6: =M82 | O6: =N82 | P6: =O82 | Q6: =P82 | ... AB6: =AA82 | AC6: =#REF! | AD6: =AC6 | AE6: =AD6-AC6
A7: Прочие | B7: Приход | C7: 1000000 | E7: 1000000 | G7: 1000000 | H7: =C7+D7+E7+F7+G7 | I7: 1000000 | K7: 1000000 | M7: 1000000 | N7: 1000000 | P7: 1000000 | R7: 1000000 | S7: 1000000 | U7: 1000000 | W7: 1000000 | X7: 1000000 | Z7: 1000000 | AA7: 1000000 | AC7: =C7+D7+E7+F7+G7+I7+J7+K7+L7+M7+N7+O7+P7+Q7+R7+S7+T7+U7+V7+W7+X7+Y7+Z7 | AD7: =#REF!+#REF!+#REF!+#REF!+#REF!+#REF!+#REF!+#REF!+#REF!+#REF!+#REF!+#REF!+#REF!+#REF!+#REF!+#REF!+#REF!+#REF!+#REF!+#REF!+#REF! | AE7: =AC7-AD7
A8: Б1, Б2, Б5 | B8: Приход | D8: 1000000 | E8: 1000000 | F8: 1000000 | G8: 1000000 | H8: =C8+D8+E8+F8+G8 | J8: 1000000 | L8: 1000000 | M8: 1000000 | O8: 1000000 | Q8: 1000000 | R8: 1000000 | T8: 1000000 | U8: 1000000 | V8: 1000000 | Y8: 1000000 | Z8: 1000000 | AA8: 10000000 | AC8: =C8+D8+E8+F8+G8+I8+J8+K8+L8+M8+N8+O8+P8+Q8+R8+S8+T8+U8+V8+W8+X8+Y8+Z8 | AD8: =#REF!+#REF!+#REF!+#REF!+#REF!+#REF!+#REF!+#REF!+#REF!+#REF!+#REF!+#REF!+#REF!+#REF!+#REF!+#REF!+#REF!+#REF!+#REF!+#REF!+#REF! | AE8: =AC8-AD8
A9: Яндекс | B9: Приход | D9: 6000000 | F9: 8000000 | H9: =C9+D9+E9+F9+G9 | J9: 6000000 | L9: 10000000 | O9: 6000000 | Q9: 10000000 | T9: 9000000 | V9: 10000000 | Y9: 9000000 | AA9: 2000000 | AC9: =C9+D9+E9+F9+G9+I9+J9+K9+L9+M9+N9+O9+P9+Q9+R9+S9+T9+U9+V9+W9+X9+Y9+Z9 | AD9: =#REF!+#REF!+#REF!+#REF!+#REF!+#REF!+#REF!+#REF!+#REF!+#REF!+#REF!+#REF!+#REF!+#REF!+#REF!+#REF!+#REF!+#REF!+#REF!+#REF!+#REF! | AE9: =AC9-AD9
A10: Май Март | B10: Приход | D10: 2000000 | F10: 2000000 | H10: =C10+D10+E10+F10+G10 | L10: 2000000 | Q10: 2000000 | T10: 2000000 | V10: 2000000 | Y10: 2000000 | AB10: 1000000 | AC10: =C10+D10+E10+F10+G10+I10+J10+K10+L10+M10+N10+O10+P10+Q10+R10+S10+T10+U10+V10+W10+X10+Y10+Z10 | AD10: =#REF!+#REF!+#REF!+#REF!+#REF!+#REF!+#REF!+#REF!+#REF!+#REF!+#REF!+#REF!+#REF!+#REF!+#REF!+#REF!+#REF!+#REF!+#REF!+#REF!+#REF! | AE10: =AC10-AD10
A11: 7-Kaspi Банк | B11: Приход | C11: 614000 | D11: 500000 | E11: 1000000 | F11: 1000000 | G11: 1000000 | H11: =C11+D11+E11+F11+G11 | I11: 1000000 | J11: 1000000 | K11: 1000000 | L11: 1000000 | M11: 1000000 | N11: 1000000 | O11: 1000000 | P11: 1000000 | Q11: 1000000 | R11: 1000000 | S11: 1000000 | U11: 1000000 | W11: 1000000 | X11: 1000000 | Z11: 1000000 | AB11: 3000000 | AC11: =C11+D11+E11+F11+G11+I11+J11+K11+L11+M11+N11+O11+P11+Q11+R11+S11+T11+U11+V11+W11+X11+Y11+Z11 | AD11: =#REF!+#REF!+#REF!+#REF!+#REF!+#REF!+#REF!+#REF!+#REF!+#REF!+#REF!+#REF!+#REF!+#REF!+#REF!+#REF!+#REF!+#REF!+#REF!+#REF!+#REF! | AE11: =AC11-AD11
A12: Crave | B12: Приход | D12: 200000 | H12: =C12+D12+E12+F12+G12 | I12: 3000000 | K12: 3000000 | M12: 3000000 | N12: 3000000 | P12: 3000000 | R12: 3000000 | S12: 3000000 | U12: 3000000 | W12: 3000000 | X12: 3000000 | Z12: 3000000 | AA12: 6000000 | AC12: =C12+D12+E12+F12+G12+I12+J12+K12+L12+M12+N12+O12+P12+Q12+R12+S12+T12+U12+V12+W12+X12+Y12+Z12 | AD12: =#REF!+#REF!+#REF!+#REF!+#REF!+#REF!+#REF!+#REF!+#REF!+#REF!+#REF!+#REF!+#REF!+#REF!+#REF!+#REF!+#REF!+#REF!+#REF!+#REF!+#REF! | AE12: =AC12-AD12
A13: 99-RP АЗС | B13: Приход | F13: 6000000 | H13: =C13+D13+E13+F13+G13 | L13: 6000000 | Q13: 6000000 | V13: 6000000 | AC13: =C13+D13+E13+F13+G13+I13+J13+K13+L13+M13+N13+O13+P13+Q13+R13+S13+T13+U13+V13+W13+X13+Y13+Z13 | AD13: =#REF!+#REF!+#REF!+#REF!+#REF!+#REF!+#REF!+#REF!+#REF!+#REF!+#REF!+#REF!+#REF!+#REF!+#REF!+#REF!+#REF!+#REF!+#REF!+#REF!+#REF! | AE13: =AC13-AD13
A14: 96- DSF покупатель | B14: Приход | D14: 4000000 | H14: =C14+D14+E14+F14+G14 | M14: 2000000 | Q14: 2000000 | U14: 1000000 | Z14: 1000000 | AA14: 4000000 | AB14: 4000000 | AC14: =C14+D14+E14+F14+G14+I14+J14+K14+L14+M14+N14+O14+P14+Q14+R14+S14+T14+U14+V14+W14+X14+Y14+Z14 | AD14: =#REF!+#REF!+#REF!+#REF!+#REF!+#REF!+#REF!+#REF!+#REF!+#REF!+#REF!+#REF!+#REF!+#REF!+#REF!+#REF!+#REF!+#REF!+#REF!+#REF!+#REF! | AE14: =AC14-AD14
A15: 85-ДФЗ дистрибьютер ФЗ | B15: Приход | C15: 11900000 | D15: 4000000 | F15: 4000000 | G15: 6000000 | H15: =C15+D15+E15+F15+G15 | I15: 2000000 | J15: 2000000 | K15: 10000000 | L15: 4000000 | M15: 2000000 | N15: 4000000 | O15: 1000000 | P15: 10000000 | Q15: 4000000 | R15: 2000000 | S15: 2000000 | T15: 5000000 | U15: 10000000 | V15: 4000000 | W15: 4000000 | X15: 2000000 | Y15: 5000000 | Z15: 10000000 | AC15: =C15+D15+E15+F15+G15+I15+J15+K15+L15+M15+N15+O15+P15+Q15+R15+S15+T15+U15+V15+W15+X15+Y15+Z15 | AD15: =#REF!+#REF!+#REF!+#REF!+#REF!+#REF!+#REF!+#REF!+#REF!+#REF!+#REF!+#REF!+#REF!+#REF!+#REF!+#REF!+#REF!+#REF!+#REF!+#REF!+#REF! | AE15: =AC15-AD15
A16: 110 АЗС №67 "Sinooil" | B16: Приход | D16: 200000 | F16: 150000 | H16: =C16+D16+E16+F16+G16 | J16: 1500000 | N16: 1000000 | U16: 2000000 | Z16: 2000000 | AC16: =C16+D16+E16+F16+G16+I16+J16+K16+L16+M16+N16+O16+P16+Q16+R16+S16+T16+U16+V16+W16+X16+Y16+Z16 | AD16: =#REF!+#REF!+#REF!+#REF!+#REF!+#REF!+#REF!+#REF!+#REF!+#REF!+#REF!+#REF!+#REF!+#REF!+#REF!+#REF!+#REF!+#REF!+#REF!+#REF!+#REF! | AE16: =AC16-AD16
A17: 100 ТУАР (шинлайн) | B17: Приход | H17: =C17+D17+E17+F17+G17 | AC17: =C17+D17+E17+F17+G17+I17+J17+K17+L17+M17+N17+O17+P17+Q17+R17+S17+T17+U17+V17+W17+X17+Y17+Z17 | AD17: =#REF!+#REF!+#REF!+#REF!+#REF!+#REF!+#REF!+#REF!+#REF!+#REF!+#REF!+#REF!+#REF!+#REF!+#REF!+#REF!+#REF!+#REF!+#REF!+#REF!+#REF! | AE17: =AC17-AD17
A18: Даркстор Чоко | B18: Приход | E18: 400000 | F18: 160000 | G18: 200000 | H18: =C18+D18+E18+F18+G18 | I18: 500000 | K18: 500000 | Q18: 650000 | S18: 150000 | U18: 150000 | X18: 150000 | Z18: 150000 | AA18: 200000 | AB18: 200000 | AC18: =C18+D18+E18+F18+G18+I18+J18+K18+L18+M18+N18+O18+P18+Q18+R18+S18+T18+U18+V18+W18+X18+Y18+Z18 | AD18: =#REF!+#REF!+#REF!+#REF!+#REF!+#REF!+#REF!+#REF!+#REF!+#REF!+#REF!+#REF!+#REF!+#REF!+#REF!+#REF!+#REF!+#REF!+#REF!+#REF!+#REF! | AE18: =AC18-AD18
A19: Глово, Вольт | B19: Приход | D19: 658000 | H19: =C19+D19+E19+F19+G19 | J19: 100000 | M19: 100000 | N19: 100000 | O19: 100000 | P19: 100000 | Q19: 100000 | R19: 100000 | S19: 200000 | T19: 100000 | U19: 200000 | V19: 200000 | W19: 200000 | X19: 200000 | Y19: 100000 | Z19: 200000 | AA19: 300000 | AC19: =C19+D19+E19+F19+G19+I19+J19+K19+L19+M19+N19+O19+P19+Q19+R19+S19+T19+U19+V19+W19+X19+Y19+Z19 | AD19: =#REF!+#REF!+#REF!+#REF!+#REF!+#REF!+#REF!+#REF!+#REF!+#REF!+#REF!+#REF!+#REF!+#REF!+#REF!+#REF!+#REF!+#REF!+#REF!+#REF!+#REF! | AE19: =AC19-AD19
A20: Торты | B20: Приход | C20: 65000 | D20: 20000 | F20: 109000 | H20: =C20+D20+E20+F20+G20 | Q20: 300000 | V20: 300000 | AA20: =SUM(AA6:AA19) | AB20: =SUM(AB6:AB19) | AC20: =C20+D20+E20+F20+G20+I20+J20+K20+L20+M20+N20+O20+P20+Q20+R20+S20+T20+U20+V20+W20+X20+Y20+Z20 | AD20: =#REF!+#REF!+#REF!+#REF!+#REF!+#REF!+#REF!+#REF!+#REF!+#REF!+#REF!+#REF!+#REF!+#REF!+#REF!+#REF!+#REF!+#REF!+#REF!+#REF!+#REF! | AE20: =AC20-AD20
A21: Итого по банку | B21: Приход | C21: =SUM(C7:C20) | D21: =SUM(D7:D20) | E21: =SUM(E7:E20) | F21: =SUM(F7:F20) | G21: =SUM(G7:G20) | H21: =SUM(H7:H20) | I21: =SUM(I7:I20) | J21: =SUM(J7:J20) | ... Z21: =SUM(Z7:Z20) | AC21: =C21+D21+E21+F21+G21+I21+J21+K21+L21+M21+N21+O21+P21+Q21+R21+S21+T21+U21+V21+W21+X21+Y21+Z21 | AD21: =#REF!+#REF!+#REF!+#REF!+#REF!+#REF!+#REF!+#REF!+#REF!+#REF!+#REF!+#REF!+#REF!+#REF!+#REF!+#REF!+#REF!+#REF!+#REF!+#REF!+#REF! | AE21: =AC21-AD21
A22: 97- Кейтеринг гость | B22: Приход | F22: 450000 | H22: =C22+D22+E22+F22+G22 | L22: 250000 | O22: 300000 | T22: 500000 | Y22: 500000 | AC22: =C22+D22+E22+F22+G22+I22+J22+K22+L22+M22+N22+O22+P22+Q22+R22+S22+T22+U22+V22+W22+X22+Y22+Z22 | AD22: =#REF!+#REF!+#REF!+#REF!+#REF!+#REF!+#REF!+#REF!+#REF!+#REF!+#REF!+#REF!+#REF!+#REF!+#REF!+#REF!+#REF!+#REF!+#REF!+#REF!+#REF! | AE22: =AC22-AD22
A23: Возврат с подотчета, Кредит | B23: Приход | H23: =C23+D23+E23+F23+G23 | AA23: 600000 | AC23: =C23+D23+E23+F23+G23+I23+J23+K23+L23+M23+N23+O23+P23+Q23+R23+S23+T23+U23+V23+W23+X23+Y23+Z23 | AD23: =#REF!+#REF!+#REF!+#REF!+#REF!+#REF!+#REF!+#REF!+#REF!+#REF!+#REF!+#REF!+#REF!+#REF!+#REF!+#REF!+#REF!+#REF!+#REF!+#REF!+#REF! | AE23: =AC23-AD23
A24: Crave | B24: Приход | C24: 600000 | F24: 600000 | H24: =C24+D24+E24+F24+G24 | I24: 600000 | L24: 600000 | N24: 600000 | Q24: 600000 | S24: 600000 | V24: 600000 | X24: 600000 | AA24: 1000000 | AC24: =C24+D24+E24+F24+G24+I24+J24+K24+L24+M24+N24+O24+P24+Q24+R24+S24+T24+U24+V24+W24+X24+Y24+Z24 | AD24: =#REF!+#REF!+#REF!+#REF!+#REF!+#REF!+#REF!+#REF!+#REF!+#REF!+#REF!+#REF!+#REF!+#REF!+#REF!+#REF!+#REF!+#REF!+#REF!+#REF!+#REF! | AE24: =AC24-AD24
A25: 7-Kaspi Банк (нал) | B25: Приход | F25: 1000000 | H25: =C25+D25+E25+F25+G25 | L25: 1000000 | Q25: 1000000 | V25: 1000000 | AC25: =C25+D25+E25+F25+G25+I25+J25+K25+L25+M25+N25+O25+P25+Q25+R25+S25+T25+U25+V25+W25+X25+Y25+Z25 | AD25: =#REF!+#REF!+#REF!+#REF!+#REF!+#REF!+#REF!+#REF!+#REF!+#REF!+#REF!+#REF!+#REF!+#REF!+#REF!+#REF!+#REF!+#REF!+#REF!+#REF!+#REF! | AE25: =AC25-AD25
A26: Частное лицо (Покупатель) | B26: Приход | F26: 200000 | H26: =C26+D26+E26+F26+G26 | L26: 400000 | Q26: 200000 | T26: 200000 | Y26: 200000 | AA26: 1500000 | AC26: =C26+D26+E26+F26+G26+I26+J26+K26+L26+M26+N26+O26+P26+Q26+R26+S26+T26+U26+V26+W26+X26+Y26+Z26 | AD26: =#REF!+#REF!+#REF!+#REF!+#REF!+#REF!+#REF!+#REF!+#REF!+#REF!+#REF!+#REF!+#REF!+#REF!+#REF!+#REF!+#REF!+#REF!+#REF!+#REF!+#REF! | AE26: =AC26-AD26
A27: 98-FOOD vending : СКЛАД АППАРАТ №1 (ФЗ Ермагамбет) | B27: Приход | F27: 1500000 | H27: =C27+D27+E27+F27+G27 | L27: 1500000 | Q27: 1500000 | V27: 1500000 | AA27: =SUM(AA21:AA26) | AB27: =SUM(AB21:AB26) | AC27: =C27+D27+E27+F27+G27+I27+J27+K27+L27+M27+N27+O27+P27+Q27+R27+S27+T27+U27+V27+W27+X27+Y27+Z27 | AD27: =#REF!+#REF!+#REF!+#REF!+#REF!+#REF!+#REF!+#REF!+#REF!+#REF!+#REF!+#REF!+#REF!+#REF!+#REF!+#REF!+#REF!+#REF!+#REF!+#REF!+#REF! | AE27: =AC27-AD27
A28: Итого по кассе | B28: Приход | C28: =SUM(C22:C27) | D28: =SUM(D22:D27) | E28: =SUM(E22:E27) | F28: =SUM(F22:F27) | G28: =SUM(G22:G27) | H28: =C28+D28+E28+F28+G28 | I28: =SUM(I22:I27) | J28: =SUM(J22:J27) | K28: =SUM(K22:K27) | L28: =SUM(L22:L27) | M28: =SUM(M22:M27) | N28: =SUM(N22:N27) | O28: =SUM(O22:O27) | P28: =SUM(P22:P27) | ... Z28: =SUM(Z22:Z27) | AA28: =AA20+AA27 | AB28: =AB20+AB27 | AC28: =C28+D28+E28+F28+G28+I28+J28+K28+L28+M28+N28+O28+P28+Q28+R28+S28+T28+U28+V28+W28+X28+Y28+Z28 | AD28: =#REF!+#REF!+#REF!+#REF!+#REF!+#REF!+#REF!+#REF!+#REF!+#REF!+#REF!+#REF!+#REF!+#REF!+#REF!+#REF!+#REF!+#REF!+#REF!+#REF!+#REF! | AE28: =AC28-AD28
A29: 1.Выручка | B29: Приход | C29: =C21+C28 | D29: =D21+D28 | E29: =E21+E28 | F29: =F21+F28 | G29: =G21+G28 | H29: =H21+H28 | I29: =I21+I28 | J29: =J21+J28 | ... Z29: =Z21+Z28 | AC29: =C29+D29+E29+F29+G29+I29+J29+K29+L29+M29+N29+O29+P29+Q29+R29+S29+T29+U29+V29+W29+X29+Y29+Z29 | AD29: =#REF!+#REF!+#REF!+#REF!+#REF!+#REF!+#REF!+#REF!+#REF!+#REF!+#REF!+#REF!+#REF!+#REF!+#REF!+#REF!+#REF!+#REF!+#REF!+#REF!+#REF! | AE29: =AC29-AD29
A30: IT-обслуживание,телефония,интернет | B30: Расход | D30: -90000 | F30: -220400 | H30: =C30+D30+E30+F30+G30 | S30: -90000 | T30: -90000 | X30: -90000 | Y30: -90000 | AC30: =C30+D30+E30+F30+G30+I30+J30+K30+L30+M30+N30+O30+P30+Q30+R30+S30+T30+U30+V30+W30+X30+Y30+Z30 | AD30: =#REF!+#REF!+#REF!+#REF!+#REF!+#REF!+#REF!+#REF!+#REF!+#REF!+#REF!+#REF!+#REF!+#REF!+#REF!+#REF!+#REF!+#REF!+#REF!+#REF!+#REF! | AE30: =AC30-AD30
A31: Авансы поставщикам | B31: Расход | H31: =C31+D31+E31+F31+G31 | AA31: -55000 | AB31: -55000 | AC31: =C31+D31+E31+F31+G31+I31+J31+K31+L31+M31+N31+O31+P31+Q31+R31+S31+T31+U31+V31+W31+X31+Y31+Z31 | AD31: =#REF!+#REF!+#REF!+#REF!+#REF!+#REF!+#REF!+#REF!+#REF!+#REF!+#REF!+#REF!+#REF!+#REF!+#REF!+#REF!+#REF!+#REF!+#REF!+#REF!+#REF! | AE31: =AC31-AD31
A32: Административные расходы | B32: Расход | C32: -55000 | D32: =-400000 | E32: -55000 | F32: -55000 | G32: -55000 | H32: =C32+D32+E32+F32+G32 | I32: -55000 | J32: -30000 | K32: -55000 | L32: -55000 | M32: -55000 | N32: -55000 | O32: -55000 | P32: -55000 | Q32: -55000 | R32: -55000 | S32: -55000 | T32: -55000 | U32: -55000 | V32: -55000 | W32: -55000 | X32: -55000 | Y32: -55000 | Z32: -55000 | AC32: =C32+D32+E32+F32+G32+I32+J32+K32+L32+M32+N32+O32+P32+Q32+R32+S32+T32+U32+V32+W32+X32+Y32+Z32 | AD32: =#REF!+#REF!+#REF!+#REF!+#REF!+#REF!+#REF!+#REF!+#REF!+#REF!+#REF!+#REF!+#REF!+#REF!+#REF!+#REF!+#REF!+#REF!+#REF!+#REF!+#REF! | AE32: =AC32-AD32
A33: Возврат ВФП | B33: Расход | H33: =C33+D33+E33+F33+G33 | AC33: =C33+D33+E33+F33+G33+I33+J33+K33+L33+M33+N33+O33+P33+Q33+R33+S33+T33+U33+V33+W33+X33+Y33+Z33 | AD33: =#REF!+#REF!+#REF!+#REF!+#REF!+#REF!+#REF!+#REF!+#REF!+#REF!+#REF!+#REF!+#REF!+#REF!+#REF!+#REF!+#REF!+#REF!+#REF!+#REF!+#REF! | AE33: =AC33-AD33
A34: Представительские расходы | B34: Расход | H34: =C34+D34+E34+F34+G34 | AC34: =C34+D34+E34+F34+G34+I34+J34+K34+L34+M34+N34+O34+P34+Q34+R34+S34+T34+U34+V34+W34+X34+Y34+Z34 | AD34: =#REF!+#REF!+#REF!+#REF!+#REF!+#REF!+#REF!+#REF!+#REF!+#REF!+#REF!+#REF!+#REF!+#REF!+#REF!+#REF!+#REF!+#REF!+#REF!+#REF!+#REF! | AE34: =AC34-AD34
A35: Аренда помещений | B35: Расход | H35: =C35+D35+E35+F35+G35 | J35: -6655000 | AC35: =C35+D35+E35+F35+G35+I35+J35+K35+L35+M35+N35+O35+P35+Q35+R35+S35+T35+U35+V35+W35+X35+Y35+Z35 | AD35: =#REF!+#REF!+#REF!+#REF!+#REF!+#REF!+#REF!+#REF!+#REF!+#REF!+#REF!+#REF!+#REF!+#REF!+#REF!+#REF!+#REF!+#REF!+#REF!+#REF!+#REF! | AE35: =AC35-AD35
A36: Газ | B36: Расход | H36: =C36+D36+E36+F36+G36 | S36: -630000 | X36: -630000 | AC36: =C36+D36+E36+F36+G36+I36+J36+K36+L36+M36+N36+O36+P36+Q36+R36+S36+T36+U36+V36+W36+X36+Y36+Z36 | AD36: =#REF!+#REF!+#REF!+#REF!+#REF!+#REF!+#REF!+#REF!+#REF!+#REF!+#REF!+#REF!+#REF!+#REF!+#REF!+#REF!+#REF!+#REF!+#REF!+#REF!+#REF! | AE36: =AC36-AD36
A37: Маркетинг | B37: Расход | H37: =C37+D37+E37+F37+G37 | AC37: =C37+D37+E37+F37+G37+I37+J37+K37+L37+M37+N37+O37+P37+Q37+R37+S37+T37+U37+V37+W37+X37+Y37+Z37 | AD37: =#REF!+#REF!+#REF!+#REF!+#REF!+#REF!+#REF!+#REF!+#REF!+#REF!+#REF!+#REF!+#REF!+#REF!+#REF!+#REF!+#REF!+#REF!+#REF!+#REF!+#REF! | AE37: =AC37-AD37
A38: Мусор | B38: Расход | H38: =C38+D38+E38+F38+G38 | M38: -100000 | Q38: -642920 | AC38: =C38+D38+E38+F38+G38+I38+J38+K38+L38+M38+N38+O38+P38+Q38+R38+S38+T38+U38+V38+W38+X38+Y38+Z38 | AD38: =#REF!+#REF!+#REF!+#REF!+#REF!+#REF!+#REF!+#REF!+#REF!+#REF!+#REF!+#REF!+#REF!+#REF!+#REF!+#REF!+#REF!+#REF!+#REF!+#REF!+#REF! | AE38: =AC38-AD38
A39: Налоги и другие платежи в бюджет | B39: Расход | H39: =C39+D39+E39+F39+G39 | M39: -8000000 | N39: -6000000 | T39: -12000000 | Y39: -12000000 | AC39: =C39+D39+E39+F39+G39+I39+J39+K39+L39+M39+N39+O39+P39+Q39+R39+S39+T39+U39+V39+W39+X39+Y39+Z39 | AD39: =#REF!+#REF!+#REF!+#REF!+#REF!+#REF!+#REF!+#REF!+#REF!+#REF!+#REF!+#REF!+#REF!+#REF!+#REF!+#REF!+#REF!+#REF!+#REF!+#REF!+#REF! | AE39: =AC39-AD39
A40: Оплата труда | B40: Расход | F40: -18500000 | H40: =C40+D40+E40+F40+G40 | Q40: -2030000 | AC40: =C40+D40+E40+F40+G40+I40+J40+K40+L40+M40+N40+O40+P40+Q40+R40+S40+T40+U40+V40+W40+X40+Y40+Z40 | AD40: =#REF!+#REF!+#REF!+#REF!+#REF!+#REF!+#REF!+#REF!+#REF!+#REF!+#REF!+#REF!+#REF!+#REF!+#REF!+#REF!+#REF!+#REF!+#REF!+#REF!+#REF! | AE40: =AC40-AD40
A41: Охрана | B41: Расход | H41: =C41+D41+E41+F41+G41 | J41: -1000000 | AC41: =C41+D41+E41+F41+G41+I41+J41+K41+L41+M41+N41+O41+P41+Q41+R41+S41+T41+U41+V41+W41+X41+Y41+Z41 | AD41: =#REF!+#REF!+#REF!+#REF!+#REF!+#REF!+#REF!+#REF!+#REF!+#REF!+#REF!+#REF!+#REF!+#REF!+#REF!+#REF!+#REF!+#REF!+#REF!+#REF!+#REF! | AE41: =AC41-AD41
A42: Платежи поставщикам Прочее | B42: Расход | H42: =C42+D42+E42+F42+G42 | AA42: -3000000 | AC42: =C42+D42+E42+F42+G42+I42+J42+K42+L42+M42+N42+O42+P42+Q42+R42+S42+T42+U42+V42+W42+X42+Y42+Z42 | AD42: =#REF!+#REF!+#REF!+#REF!+#REF!+#REF!+#REF!+#REF!+#REF!+#REF!+#REF!+#REF!+#REF!+#REF!+#REF!+#REF!+#REF!+#REF!+#REF!+#REF!+#REF! | AE42: =AC42-AD42
A43: Производственные расходы | B43: Расход | D43: -3000000 | H43: =C43+D43+E43+F43+G43 | J43: -3000000 | K43: -3000000 | L43: -3000000 | Q43: -3000000 | S43: -3000000 | V43: -3000000 | X43: -3000000 | AC43: =C43+D43+E43+F43+G43+I43+J43+K43+L43+M43+N43+O43+P43+Q43+R43+S43+T43+U43+V43+W43+X43+Y43+Z43 | AD43: =#REF!+#REF!+#REF!+#REF!+#REF!+#REF!+#REF!+#REF!+#REF!+#REF!+#REF!+#REF!+#REF!+#REF!+#REF!+#REF!+#REF!+#REF!+#REF!+#REF!+#REF! | AE43: =AC43-AD43
A44: Инвентарь | B44: Расход | H44: =C44+D44+E44+F44+G44 | AC44: =C44+D44+E44+F44+G44+I44+J44+K44+L44+M44+N44+O44+P44+Q44+R44+S44+T44+U44+V44+W44+X44+Y44+Z44 | AD44: =#REF!+#REF!+#REF!+#REF!+#REF!+#REF!+#REF!+#REF!+#REF!+#REF!+#REF!+#REF!+#REF!+#REF!+#REF!+#REF!+#REF!+#REF!+#REF!+#REF!+#REF! | AE44: =AC44-AD44
A45: Униформа | B45: Расход | H45: =C45+D45+E45+F45+G45 | AC45: =C45+D45+E45+F45+G45+I45+J45+K45+L45+M45+N45+O45+P45+Q45+R45+S45+T45+U45+V45+W45+X45+Y45+Z45 | AD45: =#REF!+#REF!+#REF!+#REF!+#REF!+#REF!+#REF!+#REF!+#REF!+#REF!+#REF!+#REF!+#REF!+#REF!+#REF!+#REF!+#REF!+#REF!+#REF!+#REF!+#REF! | AE45: =AC45-AD45
A46: Упаковка | B46: Расход | D46: -3000000 | F46: -1000000 | H46: =C46+D46+E46+F46+G46 | K46: -1500000 | L46: -900000 | M46: -600000 | O46: -1000000 | Q46: -1000000 | R46: -2000000 | AC46: =C46+D46+E46+F46+G46+I46+J46+K46+L46+M46+N46+O46+P46+Q46+R46+S46+T46+U46+V46+W46+X46+Y46+Z46 | AD46: =#REF!+#REF!+#REF!+#REF!+#REF!+#REF!+#REF!+#REF!+#REF!+#REF!+#REF!+#REF!+#REF!+#REF!+#REF!+#REF!+#REF!+#REF!+#REF!+#REF!+#REF! | AE46: =AC46-AD46
A47: Хоз.товара | B47: Расход | H47: =C47+D47+E47+F47+G47 | M47: -300000 | AA47: =-915358-1770150 | AB47: =-915358-1770150 | AC47: =C47+D47+E47+F47+G47+I47+J47+K47+L47+M47+N47+O47+P47+Q47+R47+S47+T47+U47+V47+W47+X47+Y47+Z47 | AD47: =#REF!+#REF!+#REF!+#REF!+#REF!+#REF!+#REF!+#REF!+#REF!+#REF!+#REF!+#REF!+#REF!+#REF!+#REF!+#REF!+#REF!+#REF!+#REF!+#REF!+#REF! | AE47: =AC47-AD47
A48: Погашение кредита и %% | B48: Расход | H48: =C48+D48+E48+F48+G48 | S48: -1198352 | V48: =-915358-1770150 | W48: =-915358-1770150 | X48: -1198352 | AB48: -2725000 | AC48: =C48+D48+E48+F48+G48+I48+J48+K48+L48+M48+N48+O48+P48+Q48+R48+S48+T48+U48+V48+W48+X48+Y48+Z48 | AD48: =#REF!+#REF!+#REF!+#REF!+#REF!+#REF!+#REF!+#REF!+#REF!+#REF!+#REF!+#REF!+#REF!+#REF!+#REF!+#REF!+#REF!+#REF!+#REF!+#REF!+#REF! | AE48: =AC48-AD48
A49: Расходы по реализации Разные(Логистика) | B49: Расход | D49: -800000 | G49: -2525000 | H49: =C49+D49+E49+F49+G49 | J49: -800000 | M49: -2725000 | O49: -800000 | R49: -2725000 | T49: -800000 | W49: -2725000 | Y49: -800000 | AC49: =C49+D49+E49+F49+G49+I49+J49+K49+L49+M49+N49+O49+P49+Q49+R49+S49+T49+U49+V49+W49+X49+Y49+Z49 | AD49: =#REF!+#REF!+#REF!+#REF!+#REF!+#REF!+#REF!+#REF!+#REF!+#REF!+#REF!+#REF!+#REF!+#REF!+#REF!+#REF!+#REF!+#REF!+#REF!+#REF!+#REF! | AE49: =AC49-AD49
A50: Ремонт помещений | B50: Расход | H50: =C50+D50+E50+F50+G50 | AC50: =C50+D50+E50+F50+G50+I50+J50+K50+L50+M50+N50+O50+P50+Q50+R50+S50+T50+U50+V50+W50+X50+Y50+Z50 | AD50: =#REF!+#REF!+#REF!+#REF!+#REF!+#REF!+#REF!+#REF!+#REF!+#REF!+#REF!+#REF!+#REF!+#REF!+#REF!+#REF!+#REF!+#REF!+#REF!+#REF!+#REF! | AE50: =AC50-AD50
A51: Ремонт оборудования | B51: Расход | H51: =C51+D51+E51+F51+G51 | AC51: =C51+D51+E51+F51+G51+I51+J51+K51+L51+M51+N51+O51+P51+Q51+R51+S51+T51+U51+V51+W51+X51+Y51+Z51 | AD51: =#REF!+#REF!+#REF!+#REF!+#REF!+#REF!+#REF!+#REF!+#REF!+#REF!+#REF!+#REF!+#REF!+#REF!+#REF!+#REF!+#REF!+#REF!+#REF!+#REF!+#REF! | AE51: =AC51-AD51
A52: Приобретение основных средств | B52: Расход | H52: =C52+D52+E52+F52+G52 | AA52: -5000000 | AB52: -5000000 | AC52: =C52+D52+E52+F52+G52+I52+J52+K52+L52+M52+N52+O52+P52+Q52+R52+S52+T52+U52+V52+W52+X52+Y52+Z52 | AD52: =#REF!+#REF!+#REF!+#REF!+#REF!+#REF!+#REF!+#REF!+#REF!+#REF!+#REF!+#REF!+#REF!+#REF!+#REF!+#REF!+#REF!+#REF!+#REF!+#REF!+#REF! | AE52: =AC52-AD52
A53: Сырье Платежи поставщикам | B53: Расход | C53: -9000000 | D53: -6000000 | F53: -9000000 | G53: -5000000 | H53: =C53+D53+E53+F53+G53 | I53: -5000000 | J53: -8000000 | K53: -5000000 | L53: -6000000 | M53: -5000000 | N53: -5000000 | O53: -5000000 | P53: -5000000 | Q53: -5000000 | R53: -5000000 | S53: -5000000 | T53: -5000000 | U53: -5000000 | V53: -5000000 | W53: -5000000 | X53: -5000000 | Y53: -5000000 | Z53: -5000000 | AC53: =C53+D53+E53+F53+G53+I53+J53+K53+L53+M53+N53+O53+P53+Q53+R53+S53+T53+U53+V53+W53+X53+Y53+Z53 | AD53: =#REF!+#REF!+#REF!+#REF!+#REF!+#REF!+#REF!+#REF!+#REF!+#REF!+#REF!+#REF!+#REF!+#REF!+#REF!+#REF!+#REF!+#REF!+#REF!+#REF!+#REF! | AE53: =AC53-AD53
A54: Электроэнергия | B54: Расход | H54: =C54+D54+E54+F54+G54 | S54: -6900000 | X54: -6900000 | AA54: =SUM(AA29:AA53) | AB54: =SUM(AB29:AB53) | AC54: =C54+D54+E54+F54+G54+I54+J54+K54+L54+M54+N54+O54+P54+Q54+R54+S54+T54+U54+V54+W54+X54+Y54+Z54 | AD54: =#REF!+#REF!+#REF!+#REF!+#REF!+#REF!+#REF!+#REF!+#REF!+#REF!+#REF!+#REF!+#REF!+#REF!+#REF!+#REF!+#REF!+#REF!+#REF!+#REF!+#REF! | AE54: =AC54-AD54
A55: Итого по банку | B55: Расход | C55: =SUM(C30:C54) | D55: =SUM(D30:D54) | E55: =SUM(E30:E54) | F55: =SUM(F30:F54) | G55: =SUM(G30:G54) | H55: =SUM(H30:H54) | I55: =SUM(I30:I54) | J55: =SUM(J30:J54) | ... Z55: =SUM(Z30:Z54) | AA55: -500000 | AB55: -500000 | AC55: =C55+D55+E55+F55+G55+I55+J55+K55+L55+M55+N55+O55+P55+Q55+R55+S55+T55+U55+V55+W55+X55+Y55+Z55 | AD55: =#REF!+#REF!+#REF!+#REF!+#REF!+#REF!+#REF!+#REF!+#REF!+#REF!+#REF!+#REF!+#REF!+#REF!+#REF!+#REF!+#REF!+#REF!+#REF!+#REF!+#REF! | AE55: =AC55-AD55
A56: Подотчет (Рынок сырье, Рынок ТМЦ) | B56: Расход | C56: -300000 | F56: -500000 | G56: -500000 | H56: =C56+D56+E56+F56+G56 | I56: -500000 | L56: -500000 | M56: -500000 | Q56: -800000 | V56: -500000 | W56: -500000 | AA56: -55000 | AC56: =C56+D56+E56+F56+G56+I56+J56+K56+L56+M56+N56+O56+P56+Q56+R56+S56+T56+U56+V56+W56+X56+Y56+Z56 | AD56: =#REF!+#REF!+#REF!+#REF!+#REF!+#REF!+#REF!+#REF!+#REF!+#REF!+#REF!+#REF!+#REF!+#REF!+#REF!+#REF!+#REF!+#REF!+#REF!+#REF!+#REF! | AE56: =AC56-AD56
A57: Административные расходы | B57: Расход | D57: -55000 | E57: -55000 | F57: -55000 | G57: -55000 | H57: =C57+D57+E57+F57+G57 | I57: -30000 | J57: -55000 | K57: -55000 | L57: -55000 | M57: -55000 | N57: -55000 | O57: -55000 | P57: -55000 | Q57: -55000 | R57: -55000 | S57: -55000 | T57: -55000 | U57: -55000 | V57: -55000 | X57: -55000 | Y57: -55000 | Z57: -55000 | AC57: =C57+D57+E57+F57+G57+I57+J57+K57+L57+M57+N57+O57+P57+Q57+R57+S57+T57+U57+V57+W57+X57+Y57+Z57 | AD57: =#REF!+#REF!+#REF!+#REF!+#REF!+#REF!+#REF!+#REF!+#REF!+#REF!+#REF!+#REF!+#REF!+#REF!+#REF!+#REF!+#REF!+#REF!+#REF!+#REF!+#REF! | AE57: =AC57-AD57
A58: Представительские расходы | B58: Расход | H58: =C58+D58+E58+F58+G58 | AC58: =C58+D58+E58+F58+G58+I58+J58+K58+L58+M58+N58+O58+P58+Q58+R58+S58+T58+U58+V58+W58+X58+Y58+Z58 | AD58: =#REF!+#REF!+#REF!+#REF!+#REF!+#REF!+#REF!+#REF!+#REF!+#REF!+#REF!+#REF!+#REF!+#REF!+#REF!+#REF!+#REF!+#REF!+#REF!+#REF!+#REF! | AE58: =AC58-AD58
A59: Аренда квартир | B59: Расход | H59: =C59+D59+E59+F59+G59 | I59: =-175000-300000 | J59: -500000 | M59: -500000 | Q59: -350149 | AC59: =C59+D59+E59+F59+G59+I59+J59+K59+L59+M59+N59+O59+P59+Q59+R59+S59+T59+U59+V59+W59+X59+Y59+Z59 | AD59: =#REF!+#REF!+#REF!+#REF!+#REF!+#REF!+#REF!+#REF!+#REF!+#REF!+#REF!+#REF!+#REF!+#REF!+#REF!+#REF!+#REF!+#REF!+#REF!+#REF!+#REF! | AE59: =AC59-AD59
A60: Налоги и другие платежи в бюджет | B60: Расход | H60: =C60+D60+E60+F60+G60 | AC60: =C60+D60+E60+F60+G60+I60+J60+K60+L60+M60+N60+O60+P60+Q60+R60+S60+T60+U60+V60+W60+X60+Y60+Z60 | AD60: =#REF!+#REF!+#REF!+#REF!+#REF!+#REF!+#REF!+#REF!+#REF!+#REF!+#REF!+#REF!+#REF!+#REF!+#REF!+#REF!+#REF!+#REF!+#REF!+#REF!+#REF! | AE60: =AC60-AD60
A61: Маркетинг | B61: Расход | F61: -450000 | H61: =C61+D61+E61+F61+G61 | AA61: -3000000 | AB61: -2000000 | AC61: =C61+D61+E61+F61+G61+I61+J61+K61+L61+M61+N61+O61+P61+Q61+R61+S61+T61+U61+V61+W61+X61+Y61+Z61 | AD61: =#REF!+#REF!+#REF!+#REF!+#REF!+#REF!+#REF!+#REF!+#REF!+#REF!+#REF!+#REF!+#REF!+#REF!+#REF!+#REF!+#REF!+#REF!+#REF!+#REF!+#REF! | AE61: =AC61-AD61
A62: Оплата труда | B62: Расход | C62: -3000000 | D62: -3000000 | F62: -15000000 | H62: =C62+D62+E62+F62+G62 | K62: -2500000 | L62: -8000000 | M62: -7000000 | Q62: -800000 | R62: -7000000 | S62: -5000000 | T62: -2000000 | U62: -2000000 | V62: -3000000 | W62: -2000000 | X62: -5000000 | Y62: -2000000 | Z62: -2000000 | AC62: =C62+D62+E62+F62+G62+I62+J62+K62+L62+M62+N62+O62+P62+Q62+R62+S62+T62+U62+V62+W62+X62+Y62+Z62 | AD62: =#REF!+#REF!+#REF!+#REF!+#REF!+#REF!+#REF!+#REF!+#REF!+#REF!+#REF!+#REF!+#REF!+#REF!+#REF!+#REF!+#REF!+#REF!+#REF!+#REF!+#REF! | AE62: =AC62-AD62
A63: Платежи поставщикам Прочее | B63: Расход | H63: =C63+D63+E63+F63+G63 | AC63: =C63+D63+E63+F63+G63+I63+J63+K63+L63+M63+N63+O63+P63+Q63+R63+S63+T63+U63+V63+W63+X63+Y63+Z63 | AD63: =#REF!+#REF!+#REF!+#REF!+#REF!+#REF!+#REF!+#REF!+#REF!+#REF!+#REF!+#REF!+#REF!+#REF!+#REF!+#REF!+#REF!+#REF!+#REF!+#REF!+#REF! | AE63: =AC63-AD63
A64: Производственные расходы | B64: Расход | C64: -48000 | F64: -48000 | H64: =C64+D64+E64+F64+G64 | I64: -42000 | J64: -42000 | O64: -48000 | Q64: -48000 | T64: -48000 | Y64: -48000 | AC64: =C64+D64+E64+F64+G64+I64+J64+K64+L64+M64+N64+O64+P64+Q64+R64+S64+T64+U64+V64+W64+X64+Y64+Z64 | AD64: =#REF!+#REF!+#REF!+#REF!+#REF!+#REF!+#REF!+#REF!+#REF!+#REF!+#REF!+#REF!+#REF!+#REF!+#REF!+#REF!+#REF!+#REF!+#REF!+#REF!+#REF! | AE64: =AC64-AD64
A65: Инвентарь | B65: Расход | C65: =-15000-27000 | D65: -40000 | H65: =C65+D65+E65+F65+G65 | J65: =-116000-19100 | O65: -32000 | P65: -35000 | AC65: =C65+D65+E65+F65+G65+I65+J65+K65+L65+M65+N65+O65+P65+Q65+R65+S65+T65+U65+V65+W65+X65+Y65+Z65 | AD65: =#REF!+#REF!+#REF!+#REF!+#REF!+#REF!+#REF!+#REF!+#REF!+#REF!+#REF!+#REF!+#REF!+#REF!+#REF!+#REF!+#REF!+#REF!+#REF!+#REF!+#REF! | AE65: =AC65-AD65
A66: Погашение кредита и %% | B66: Расход | H66: =C66+D66+E66+F66+G66 | AC66: =C66+D66+E66+F66+G66+I66+J66+K66+L66+M66+N66+O66+P66+Q66+R66+S66+T66+U66+V66+W66+X66+Y66+Z66 | AD66: =#REF!+#REF!+#REF!+#REF!+#REF!+#REF!+#REF!+#REF!+#REF!+#REF!+#REF!+#REF!+#REF!+#REF!+#REF!+#REF!+#REF!+#REF!+#REF!+#REF!+#REF! | AE66: =AC66-AD66
A67: Хоз.товара | B67: Расход | H67: =C67+D67+E67+F67+G67 | AC67: =C67+D67+E67+F67+G67+I67+J67+K67+L67+M67+N67+O67+P67+Q67+R67+S67+T67+U67+V67+W67+X67+Y67+Z67 | AD67: =#REF!+#REF!+#REF!+#REF!+#REF!+#REF!+#REF!+#REF!+#REF!+#REF!+#REF!+#REF!+#REF!+#REF!+#REF!+#REF!+#REF!+#REF!+#REF!+#REF!+#REF! | AE67: =AC67-AD67
A68: Канц.товары | B68: Расход | H68: =C68+D68+E68+F68+G68 | AC68: =C68+D68+E68+F68+G68+I68+J68+K68+L68+M68+N68+O68+P68+Q68+R68+S68+T68+U68+V68+W68+X68+Y68+Z68 | AD68: =#REF!+#REF!+#REF!+#REF!+#REF!+#REF!+#REF!+#REF!+#REF!+#REF!+#REF!+#REF!+#REF!+#REF!+#REF!+#REF!+#REF!+#REF!+#REF!+#REF!+#REF! | AE68: =AC68-AD68
A69: Расходы по реализации Разные | B69: Расход | H69: =C69+D69+E69+F69+G69 | AC69: =C69+D69+E69+F69+G69+I69+J69+K69+L69+M69+N69+O69+P69+Q69+R69+S69+T69+U69+V69+W69+X69+Y69+Z69 | AD69: =#REF!+#REF!+#REF!+#REF!+#REF!+#REF!+#REF!+#REF!+#REF!+#REF!+#REF!+#REF!+#REF!+#REF!+#REF!+#REF!+#REF!+#REF!+#REF!+#REF!+#REF! | AE69: =AC69-AD69
A70: Ремонт помещений | B70: Расход | H70: =C70+D70+E70+F70+G70 | AC70: =C70+D70+E70+F70+G70+I70+J70+K70+L70+M70+N70+O70+P70+Q70+R70+S70+T70+U70+V70+W70+X70+Y70+Z70 | AD70: =#REF!+#REF!+#REF!+#REF!+#REF!+#REF!+#REF!+#REF!+#REF!+#REF!+#REF!+#REF!+#REF!+#REF!+#REF!+#REF!+#REF!+#REF!+#REF!+#REF!+#REF! | AE70: =AC70-AD70
A71: Ремонт оборудования | B71: Расход | H71: =C71+D71+E71+F71+G71 | AC71: =C71+D71+E71+F71+G71+I71+J71+K71+L71+M71+N71+O71+P71+Q71+R71+S71+T71+U71+V71+W71+X71+Y71+Z71 | AD71: =#REF!+#REF!+#REF!+#REF!+#REF!+#REF!+#REF!+#REF!+#REF!+#REF!+#REF!+#REF!+#REF!+#REF!+#REF!+#REF!+#REF!+#REF!+#REF!+#REF!+#REF! | AE71: =AC71-AD71
A72: Приобретение основных средств | B72: Расход | H72: =C72+D72+E72+F72+G72 | AA72: -500000 | AC72: =C72+D72+E72+F72+G72+I72+J72+K72+L72+M72+N72+O72+P72+Q72+R72+S72+T72+U72+V72+W72+X72+Y72+Z72 | AD72: =#REF!+#REF!+#REF!+#REF!+#REF!+#REF!+#REF!+#REF!+#REF!+#REF!+#REF!+#REF!+#REF!+#REF!+#REF!+#REF!+#REF!+#REF!+#REF!+#REF!+#REF! | AE72: =AC72-AD72
A73: Сырье Платежи поставщикам | B73: Расход | D73: -1500000 | E73: -1500000 | F73: -500000 | H73: =C73+D73+E73+F73+G73 | J73: -500000 | K73: -500000 | L73: -500000 | O73: -500000 | P73: -500000 | Q73: -500000 | T73: -500000 | U73: -500000 | V73: -500000 | Y73: -500000 | Z73: -500000 | AA73: =SUM(AA55:AA72) | AB73: =SUM(AB55:AB72) | AC73: =C73+D73+E73+F73+G73+I73+J73+K73+L73+M73+N73+O73+P73+Q73+R73+S73+T73+U73+V73+W73+X73+Y73+Z73 | AD73: =#REF!+#REF!+#REF!+#REF!+#REF!+#REF!+#REF!+#REF!+#REF!+#REF!+#REF!+#REF!+#REF!+#REF!+#REF!+#REF!+#REF!+#REF!+#REF!+#REF!+#REF! | AE73: =AC73-AD73
A74: Итого по кассе | B74: Расход | C74: =SUM(C56:C73) | D74: =SUM(D56:D73) | E74: =SUM(E56:E73) | F74: =SUM(F56:F73) | G74: =SUM(G56:G73) | H74: =SUM(H56:H73) | I74: =SUM(I56:I73) | J74: =SUM(J56:J73) | ... Z74: =SUM(Z56:Z73) | AA74: =AA54+AA73 | AB74: =AB54+AB73 | AC74: =SUM(AC56:AC73) | AD74: =#REF!+#REF!+#REF!+#REF!+#REF!+#REF!+#REF!+#REF!+#REF!+#REF!+#REF!+#REF!+#REF!+#REF!+#REF!+#REF!+#REF!+#REF!+#REF!+#REF!+#REF! | AE74: =AC74-AD74
A75: ИТОГО РАСХОДЫ | C75: =C55+C74 | D75: =D55+D74 | E75: =E55+E74 | F75: =F55+F74 | G75: =G55+G74 | H75: =H55+H74 | I75: =I55+I74 | J75: =J55+J74 | ... Z75: =Z55+Z74 | AA75: =AA28-(-AA54-AA73) | AB75: =AB28-(-AB54-AB73) | AC75: =AC55+AC74 | AD75: =#REF!+#REF!+#REF!+#REF!+#REF!+#REF!+#REF!+#REF!+#REF!+#REF!+#REF!+#REF!+#REF!+#REF!+#REF!+#REF!+#REF!+#REF!+#REF!+#REF!+#REF! | AE75: =AC75-AD75
A76: Операционная деятельность | C76: =C29-(-C55-C74) | D76: =D29-(-D55-D74) | E76: =E29-(-E55-E74) | F76: =F29-(-F55-F74) | G76: =G29-(-G55-G74) | H76: =H29-(-H55-H74) | I76: =I29-(-I55-I74) | J76: =J29-(-J55-J74) | ... L76: =L29-(-L55-L74) | N76: =N29-(-N55-N74) | O76: =O29-(-O55-O74) | P76: =P29-(-#REF!-P74) | Q76: =Q29-(-Q74) | R76: =R29-(-#REF!-R74) | S76: =S29-(-S55-S74) | T76: =T29-(-T55-T74) | U76: =U29-(-U55-U74) | V76: =V29-(-V55-V74) | W76: =W29-(-W55-W74) | X76: =X29-(-X55-X74) | Y76: =Y29-(-Y55-Y74) | Z76: =Z29-(-Z55-Z74) | AC76: =AC29-(-AC55-AC74) | AD76: =#REF!+#REF!+#REF!+#REF!+#REF!+#REF!+#REF!+#REF!+#REF!+#REF!+#REF!+#REF!+#REF!+#REF!+#REF!+#REF!+#REF!+#REF!+#REF!+#REF!+#REF!
A77: ВФП Учредители поступление (НАЛ) | B77: Приход | AC77: =AC30-(-AC56-AC75) | AD77: =#REF!+#REF!+#REF!+#REF!+#REF!+#REF!+#REF!+#REF!+#REF!+#REF!+#REF!+#REF!+#REF!+#REF!+#REF!+#REF!+#REF!+#REF!+#REF!+#REF!+#REF!
B78: Расход | AC78: =AC31-(-AC57-AC76) | AD78: =#REF!+#REF!+#REF!+#REF!+#REF!+#REF!+#REF!+#REF!+#REF!+#REF!+#REF!+#REF!+#REF!+#REF!+#REF!+#REF!+#REF!+#REF!+#REF!+#REF!+#REF!
A79: Касса взаиморасчета банк | B79: Расход | H79: -10500000 | AC79: =AC32-(-AC58-AC77) | AD79: =#REF!+#REF!+#REF!+#REF!+#REF!+#REF!+#REF!+#REF!+#REF!+#REF!+#REF!+#REF!+#REF!+#REF!+#REF!+#REF!+#REF!+#REF!+#REF!+#REF!+#REF!
A80: Касса взаиморасчета касса | B80: Приход | H80: 10500000 | AA80: =AA4+AA20-(-AA54)-AA78+AA76-AA77 | AB80: =AB4+AB20-(-AB54)-AB78+AB76-AB77 | AC80: =AC33-(-AC59-AC78) | AD80: =#REF!+#REF!+#REF!+#REF!+#REF!+#REF!+#REF!+#REF!+#REF!+#REF!+#REF!+#REF!+#REF!+#REF!+#REF!+#REF!+#REF!+#REF!+#REF!+#REF!+#REF!
A81: Остаток на конец ПО БАНКУ | C81: =C5+C21-(-C55)-C79 | D81: =D5+D21-(-D55)-D79 | E81: =E5+E21-(-E55)-E79 | F81: =F5+F21-(-F55)-F79 | G81: =G5+G21-(-G55)-G79 | H81: =G81+H79 | I81: =I5+I21-(-I55)-I79 | J81: =J5+J21-(-J55)-J79 | K81: =K5+K21-(-K55)-K79 | L81: =L5+L21-(-L55)-L79 | M81: =M5+M21-(-M55)-M79 | N81: =N5+N21-(-N55)-N79 | O81: =O5+O21-(-O55)-O79 | P81: =P5+P21-(-P55)-P79 | ... U81: =U5+U21-(-U55)-U79 | V81: =V5+V21-(-V55)-V79+V77-V78 | W81: =W5+W21-(-W55)-W79+W77-W78 | X81: =X5+X21-(-X55)-X79 | Y81: =Y5+Y21-(-Y55)-Y79 | Z81: =Z5+Z21-(-Z55)-Z79 | AA81: =AA5+AA27-(-AA73)+AA79 | AB81: =AB5+AB27-(-AB73)+AB79 | AC81: =AC5+AC21-(-AC55)-AC79 | AD81: =AD5+AD21-(-AD55)-AD79
A82: Остаток на конец ПО КАССЕ | C82: =C6+C28-(-C74)+C77-C78+C80 | D82: =D6+D28-(-D74)+D77-D78+D80 | E82: =E6+E28-(-E74)+E77-E78+E80 | F82: =F6+F28-(-F74)+F77-F78+F80 | G82: =G6+G28-(-G74)+G77-G78+G80 | H82: =G82+H80 | I82: =I6+I28-(-I74)+I77-I78+I80 | J82: =J6+J28-(-J74)+J77-J78+J80 | K82: =K6+K28-(-K74)+K77-K78+K80 | L82: =L6+L28-(-L74)+L77-L78+L80 | M82: =M6+M28-(-M74)+M77-M78+M80 | N82: =N6+N28-(-N74)+N77-N78+N80 | O82: =O6+O28-(-O74)+O77-O78+O80 | P82: =P6+P28-(-P74)+P77-P78+P80 | ... U82: =U6+U28-(-U74)+U77-U78+U80 | V82: =V6+V28-(-V74)+V80 | W82: =W6+W28-(-W74)+W80 | X82: =X6+X28-(-X74)+X77-X78+X80 | Y82: =Y6+Y28-(-Y74)+Y77-Y78+Y80 | Z82: =Z6+Z28-(-Z74)+Z77-Z78+Z80 | AA82: =AA80+AA81 | AB82: =AB80+AB81 | AC82: =AC6+AC28-(-AC74)+AC77-AC78+AC80 | AD82: =AD6+AD28-(-AD74)+AD77-AD78+AD80
A83: Итого | C83: =C81+C82 | D83: =D81+D82 | E83: =E81+E82 | F83: =F81+F82 | G83: =G81+G82 | H83: =G83 | I83: =I81+I82 | J83: =J81+J82 | K83: =K81+K82 | L83: =L81+L82 | M83: =M81+M82 | N83: =N81+N82 | O83: =O81+O82 | P83: =P81+P82 | ... AD83: =AD81+AD82
AC84: Итого май (+если есть деньги, - кас.разрыв) | AE84: =AE75+AE29
AC85: План | AD85: Факт | AE85: Отклонение
G86: Выплата поставщикам | M86: Выплата поставщикам | W86: Выплата поставщикам | AC86: =AC31+AC46+AC47+AC53+AC73+AC56+AC49 | AD86: =AD31+AD46+AD47+AD53+AD73+AD56 | AE86: =AC86-AD86
G87: Налоги | M87: Налоги | W87: Налоги | AC87: =AC39 | AD87: =AD39 | AE87: =AC87-AD87
G88: Оплата труда | M88: Оплата труда | W88: Оплата труда | AC88: =AC40+AC62 | AD88: =AD40+AD62 | AE88: =AC88-AD88
G89: Ремонт | M89: Ремонт | W89: Произв. расх | AC89: =AC64+AC43+AC44+AC51+AC65 | AD89: =AD51+AD50+AD70+AD71 | AE89: =AC89-AD89
G90: ОС | M90: ОС | W90: ОС | AC90: =AC52+AC72 | AD90: =AD52+AD72 | AE90: =AC90-AD90

Sheet ВОЗВРАТ маймарт
B2: реализация | C2: возвраты | D2: %
A3: январь | B3: 11770526 | C3: 1232140 | D3: =C3/B3*100%
A4: февраль | B4: 14039988 | C4: 1973959 | D4: =C4/B4*100%
A5: март | B5: 15399728 | C5: 2054000 | D5: =C5/B5*100%
A6: апрель | B6: 21349838 | C6: 2168666 | D6: =C6/B6*100%

Sheet 3.3.5
A1: счёт 3.3.5 комиссия банка
A3: апрель | F3: Алгоритм: снятие по Фуд заводу, только через Жусан Банк. 5 000 000 через карту, 15 000 000 через Банк. Карту оставить в кассе, снимает Акерке. Олеся Сергеевна - 1 р. в месяц снимает деньги в банке. Любые переводы с Джусан банка (безналичные) под запретом. Остаток снимается с РБК.Уточнить есть ли карта в РБК!!!!!!!!!!!!!!!!!!!!!!!!!!!!!!!!!!! | H3: Пакет Comfort в РБК
A4: БАНК | B4: АПРЕЛЬ (тенге) | C4: май (тенге) | D4: вид платежа
A5: ФЗ РБК Каламкас | B5: 129175 | C5: =SUMIF($A$23:$A$35,A5,$R$23:$R$35) | D5: за перевод с РБК на каспи
A6: ФЗ Каспи | B6: 150470 | C6: =SUMIF($A$23:$A$35,A6,$R$23:$R$35) | D6: (комиссия за поступления торты, оплаты QR кодом)
A7: ФЗ Жусан Банк | B7: 27250 | C7: =SUMIF($A$23:$A$35,A7,$R$23:$R$35)
A8: ФЗ Айдана каспи | B8: 137150 | C8: =SUMIF($A$23:$A$35,A8,$R$23:$R$35)
A9: Касса Взаиморасчеты | B9: 156750 | C9: =SUMIF($A$23:$A$35,A9,$R$23:$R$35) | D9: обналичивание ИП Демьянов
A10: ИТОГО | B10: =B5+B6+B7+B8+B9 | C10: =C5+C6+C7+C8+C9
A13: Банк | B13: Комиссия за обналичивание | C13: Комиссия при снятии 10 млн ₸ | D13: Комиссия при снятии 50 млн ₸ | E13: Комментарий | F13: Лимит на снятие, мес без документов | G13: Лимит на снятие, с документами | H13: Корпоративная карточка | I13: Менеджер банка, тел
A14: Jusan Bank | B14: от 0,2% до 0,35% | C14: 20 000 – 30 000 ₸ (надо уточнить наши условия) | D14: 100 000 – 150 000 ₸ | E14: без заявки не принимают | F14: 5 на карту и 15 000 000 со счёта
A15: Bank RBK (COMFORT) | B15: от 0,2% до 0,55% | C15: 55 000 тенге по заявке, без заявки 77 000 тенге | D15: 100 000 – 225 000 ₸ | E15: принимают без заявки, % выше | F15: 10000000 | G15: 20000000
A16: Kaspi Business | B16: 0,95% сверх 1 млн ₸ | C16: 95 000 тенге | D16: 465 500 ₸ | E16: есть лимит - 4 млн./день
A17: Forte bank | B17: 0.006 | C17: 60 000 тенге | E17: лимит 10 млн. в день | F17: 20 000 000
C18: 9500 | D18: 4 | E18: =C18*D18
A19: Для регулярного снятия крупных сумм (от 10 млн ₸ и выше) наиболее выгодны Jusan Bank и Bank RBK. Kaspi удобен для расчетов и платежей, но менее выгоден для обналичивания крупных сумм.
A22: Счет/Банк | B22: январь 2025 | C22: февраль 2025 | D22: март 2025 | E22: апрель 2025 | F22: май 2025 | G22: июнь 2025 | H22: июль 2025 | I22: август 2025 | J22: сентябрь 2025 | K22: октябрь 2025 | L22: ноябрь 2025 | M22: декабрь 2025 | N22: январь 2026 | O22: февраль 2026 | P22: март 2026 | Q22: апрель 2026 | R22: май 2026 | S22: Итого
A23: ФЗ Каспи | B23: 21750 | C23: 31050 | D23: 233450 | E23: 242450 | F23: 232950 | G23: 496470 | H23: 261971 | I23: 435082 | J23: 248232 | K23: 465437 | L23: 381458 | M23: 231585 | N23: 177046 | O23: 55846 | P23: 121929 | Q23: 150470 | R23: 151441 | S23: 3938617
A24: ФЗ Ермагамбет отдел продаж | B24: 86623 | C24: 38050 | D24: 56803 | E24: 42800 | F24: 37100 | G24: 36245 | H24: 1950 | I24: 1950 | J24: 0 | K24: 1950 | L24: 0 | M24: 0 | N24: 0 | O24: 0 | P24: 0 | Q24: 0 | R24: 0 | S24: 303471
A25: ФЗ РБК Каламкас | B25: 89879 | C25: 101157 | D25: 56935 | E25: 28116 | F25: 134232 | G25: 78264 | H25: 78925 | I25: 75694 | J25: 132168 | K25: 100980 | L25: 76661 | M25: 58212 | N25: 62822 | O25: 61100 | P25: 49750 | Q25: 129175 | R25: 127040 | S25: 1441110
A26: ФЗ Жусан Банк | B26: 70670 | C26: 17855 | D26: 29239 | E26: 56322 | F26: 38050 | G26: 37300 | H26: 65500 | I26: 60200 | J26: 47400 | K26: 53750 | L26: 24187 | M26: 0 | N26: 17000 | O26: 8500 | P26: 8500 | Q26: 27250 | R26: 8500 | S26: 570223
A27: ФЗ Народный Банк (закр.) | B27: 0 | C27: 0 | D27: 15288 | E27: 0 | F27: 0 | G27: 0 | H27: 0 | I27: 0 | J27: 0 | K27: 0 | L27: 0 | M27: 0 | N27: 0 | O27: 0 | P27: 0 | Q27: 0 | R27: 0 | S27: 15288
A28: ФЗ ВТБ банк (закр.) | B28: 0 | C28: 0 | D28: 26948 | E28: 0 | F28: 0 | G28: 0 | H28: 0 | I28: 0 | J28: 0 | K28: 0 | L28: 0 | M28: 0 | N28: 0 | O28: 0 | P28: 0 | Q28: 0 | R28: 0 | S28: 26948
A29: Цой Д.Л.Каспи | B29: 0 | C29: 0 | D29: 0 | E29: 1290 | F29: 0 | G29: 0 | H29: 7600 | I29: 0 | J29: 0 | K29: 0 | L29: 0 | M29: 0 | N29: 0 | O29: 8859 | P29: 0 | Q29: 0 | R29: 0 | S29: 17749
A30: Алимова Каспи | B30: 0 | C30: 0 | D30: 0 | E30: 0 | F30: 0 | G30: 0 | H30: 0 | I30: 318 | J30: 0 | K30: 0 | L30: 0 | M30: 0 | N30: 0 | O30: 0 | P30: 0 | Q30: 0 | R30: 0 | S30: 318
A31: ФЗ РБК кредит | B31: 0 | C31: 0 | D31: 0 | E31: 0 | F31: 0 | G31: 0 | H31: 0 | I31: 0 | J31: 0 | K31: 0 | L31: 1000 | M31: 14500 | N31: 0 | O31: 0 | P31: 0 | Q31: 0 | R31: 0 | S31: 15500
A32: ФЗ Сапакова Кредит (Нурбанк) | B32: 0 | C32: 0 | D32: 0 | E32: 0 | F32: 0 | G32: 0 | H32: 0 | I32: 0 | J32: 0 | K32: 0 | L32: 0 | M32: 3450 | N32: 0 | O32: 5460 | P32: 3330 | Q32: 2400 | R32: 2400 | S32: 17040
A33: Касса Взаиморасчеты | B33: 0 | C33: 0 | D33: 0 | E33: 0 | F33: 0 | G33: 0 | H33: 0 | I33: 0 | J33: 0 | K33: 0 | L33: 0 | M33: 250230 | N33: 190000 | O33: 0 | P33: 38000 | Q33: 156750 | R33: 205200 | S33: 840180
A34: ФЗ Малышев каспи | B34: 0 | C34: 0 | D34: 0 | E34: 0 | F34: 0 | G34: 0 | H34: 0 | I34: 0 | J34: 0 | K34: 0 | L34: 0 | M34: 208985 | N34: 126900 | O34: 40000 | P34: 15000 | Q34: 0 | R34: 0 | S34: 390885
... A36: Итого | B36: 268922 | C36: 188112 | D36: 418663 | E36: 370978 | F36: 442332 | G36: 648279 | H36: 415946 | I36: 573244 | J36: 427800 | K36: 622117 | L36: 483306 | M36: 766962 | N36: 573768 | O36: 179765 | P36: 298309 | Q36: 603195 | R36: 676513 | S36: 7958211
B38: Банк
B39: РБК справки для снятия свыше 20 млн | C39: Описание
B40: 1. Справка по субъекту предпринимательства. | C40: справка подтверждающая, что у нас малый или средний бизнес, возможно с егов
B41: 2. Документы по источнику происхождения денежных средств. | C41: Договора с покупателями
B42: 3. Документы по целевому использованию. | C42: Письмо официальное, что мы закупаем за безналичный расчёт или выдаём зп налом
B44: Банк | C44: Наименование покупателя
B45: РБК | C45: 102-Яндекс лавка ОСНОВНОЙ
B46: РБК | C46: 103-Бобух ИП, ул. Торетай 92, бутик 103
B47: РБК | C47: 104-DQ12 ТОО г.Тараз, Конаева 12
B48: РБК | C48: 105-Алга экспресс ОСНОВНОЙ
B49: РБК | C49: 108-GO Market KRG ИП ОСНОВНОЙ
B50: РБК | C50: 110 АЗС "Sinooil" (Шымкент/Тараз)
B51: РБК | C51: 111 ТОО ГЛОВО ОСНОВНОЙ
... B64: Jusan Bank | C64: 110 АЗС "Sinooil"
A67: Алгоритм действий | B67: Действие | C67: Что даёт? | D67: Комиссия
A68: 1. | B68: Открыть карту в Жусан банке | C68: оперативность снятия наличных до 5 млн. тенге | D68: 0.0035
A69: 2.. | B69: Пакет документов для РБК | C69: Снятие до 20 млн, по предварительной заявке | D69: 0.003
A70: 3. | B70: Открыть карту в РБК | C70: оперативность снятия наличных до 10 млн. тенге | D70: 1 млн. тенге бесплатно, далее 0,4%

Sheet Заявка ТМЦ
B1: Правило: все заявки поступающие в отдел снабжения до конца дня должны быть внесены в реестр, по мере согласования факта закупа перейти в лист День оплат, спланированы. Далее по факту отработки, пределаны инициатору
B5: Отработка ЗАЯВОК
B6: Дата поступления заявки | C6: Дата закупа | D6: Наименование товара | E6: Сумма | F6: ОТВЕТСТВЕННЫЙ | G6: Комментарий
B7: 46160 | C7: 46161 | D7: закуп в тех отдел Жансултан | E7: 456000 | F7: Александр | G7: Выполнено
C8: 46164 | D8: закуп | F8: Александр | G8: Закуп
B9: 46181 | D9: заявка дворник Владимир К. | E9: 30-50 тыс | F9: Жибек | G9: Закуп
A10: Asdecor | B10: 46182 | C10: 46197 | D10: в конд. цех коврики силиконовые 10 шт. | E10: 14900 | F10: Жибек | G10: Выполнено
A11: Horeca supplies | B11: 46182 | C11: 46203 | D11: блендер погружной Robot Coupe MINI MP190 V.V. 34750 1шт. | E11: 484000 | F11: Жибек | G11: Закуп
B12: 46182 | D12: овощорезка Китай | E12: 1200000 | F12: Александр | G12: Выполнено
A13: цена? | B13: 46188 | C13: 46195 | D13: сейф, для хранения документов А4 и печати | F13: Жибек | G13: Закуп
A14: Asdecor | B14: 46190 | C14: 46197 | D14: силиконовые лопатки 2 шт | E14: 1560 | F14: Жибек | G14: Выполнено
A15: Kaspi | B15: 46190 | C15: 46195 | D15: венчики маленькие 2 шт по 649 тг в каспи | E15: 1298 | F15: Жибек | G15: Закуп
A16: Kaspi | B16: 46190 | C16: 46195 | D16: сито для орешков 2 шт по 790 тг в каспи | E16: 1580 | F16: Жибек | G16: Закуп
B17: 46197 | D17: закуп расширительного бака на производство | E17: 95700 | F17: Александр | G17: Выполнено
A18: Химбаза | B18: 46199 | C18: 46204 | D18: промывалка с узким горлом для заполнения гигрометра | E18: 3500 | F18: Жибек | G18: Закуп
F19: Александр | G19: Закуп
F20: Александр | G20: Закуп
F21: Александр | G21: Закуп
F22: Александр | G22: Закуп
F23: Александр | G23: Закуп
F24: Александр | G24: Закуп
F25: Александр | G25: Закуп
F26: Александр | G26: Закуп
F27: Александр | G27: Закуп
F28: Александр | G28: Закуп
F29: Александр | G29: Закуп
F30: Александр | G30: Закуп
... F69: Александр | G69: Закуп

Sheet оборудование

Sheet ДДС МЕСЯЦ ИЮНЬ
K1: 46174 | M1: 46175 | O1: 46176 | Q1: 46177 | S1: 46178 | U1: 46181 | W1: 46182 | Y1: 46183 | AA1: 46184 | AC1: 46185 | AE1: 46188 | AG1: 46189 | AI1: 46190 | AK1: 46191 | AM1: 46192 | AO1: 46195 | AQ1: 46196 | AS1: 46197 | AU1: 46198 | AW1: 46199 | AY1: 46202 | BA1: 46203 | BC1: 46204
K2: понедельник | M2: вторник | O2: среда | Q2: четверг | S2: пятница | U2: понедельник | W2: вторник | Y2: среда | AA2: четверг | AC2: пятница | AE2: понедельник | AG2: вторник | AI2: среда | AK2: четверг | AM2: пятница | AO2: понедельник | AQ2: вторник | AS2: среда | AU2: четверг | AW2: пятница | AY2: понедельник | BA2: вторник | BC2: среда | BE2: прирост 18% к факту апреля
K3: 46174 | M3: 46175 | O3: 46176 | Q3: 46177 | S3: 46178 | U3: 46181 | W3: 46182 | Y3: 46183 | AA3: 46184 | AC3: 46185 | AE3: 46188 | AG3: 46189 | AI3: 46190 | AK3: 46191 | AM3: 46192 | AO3: 46195 | AQ3: 46196 | AS3: 46197 | AU3: 46198 | AW3: 46199 | AY3: 46202 | BA3: 46203 | BC3: 46204 | BE3: Итого план | BF3: Итого факт | BG3: Отклонение
C4: План | D4: Факт | E4: План | F4: Факт | G4: План | H4: Факт | I4: План | J4: Факт | K4: План | L4: Факт | M4: План | N4: Факт | O4: План | P4: Факт | Q4: План | R4: Факт | S4: План | T4: Факт | U4: План | V4: Факт | W4: План | X4: Факт | Y4: План | Z4: Факт | AA4: План | AB4: Факт | AC4: План | AD4: Факт | AE4: План | AF4: Факт | AG4: План | AH4: Факт | AI4: План | AJ4: Факт | AK4: План | AL4: Факт | AM4: План | AN4: Факт
A5: Остаток на начало по Банку | C5: 3140328 | D5: =C5 | E5: =C81 | F5: =D81 | G5: =E81 | H5: =3139916 | I5: =G81 | J5: =H81 | K5: 0 | L5: 0 | M5: =K81 | N5: =L81 | O5: =M81 | P5: =N81 | Q5: =O81 | R5: =P81 | S5: =Q81 | T5: =R81 | ... BD5: =BB81 | BE5: =C5 | BF5: =BE5 | BG5: =BF5-BE5
A6: Остаток на начало по Кассе | C6: 917728 | D6: =C6 | E6: =C82 | F6: =D82 | G6: =E82 | H6: =F82+62744 | I6: =G82 | J6: =H82 | K6: 0 | L6: 0 | M6: =K82 | N6: =L82 | O6: =M82 | P6: =N82 | Q6: =O82 | R6: =P82 | S6: =Q82 | T6: =R82 | ... BD6: =BB82 | BE6: =C6 | BF6: =BE6 | BG6: =BF6-BE6
A7: Прочие | B7: Приход | G7: 1000000 | K7: 1000000 | O7: 1000000 | S7: 1000000 | U7: 1000000 | Y7: 1000000 | AC7: 1000000 | AE7: 1000000 | AI7: 1000000 | AM7: 1000000 | AO7: 1000000 | AS7: 1000000 | AW7: 1000000 | AY7: 1000000 | BC7: 1000000 | BE7: =K7+M7+O7+Q7+S7+U7+W7+Y7+AA7+AC7+AE7+AG7+AI7+AK7+AM7+AO7+AQ7+AS7+AU7+AW7+AY7+BA7+BC7 | BF7: =#REF!+L7+N7+P7+R7+T7+V7+X7+Z7+AB7+AD7+AF7+AH7+AJ7+AL7+AN7+AP7+AR7+AT7+AV7+AX7 | BG7: =BE7-BF7
A8: Б1, Б2, Б5 | B8: Приход | M8: 1000000 | O8: 1000000 | Q8: 1000000 | S8: 1000000 | W8: 1000000 | AA8: 1000000 | AC8: 1000000 | AG8: 1000000 | AK8: 1000000 | AM8: 1000000 | AQ8: 1000000 | AS8: 1000000 | AU8: 1000000 | BA8: 1000000 | BC8: 1000000 | BE8: =K8+M8+O8+Q8+S8+U8+W8+Y8+AA8+AC8+AE8+AG8+AI8+AK8+AM8+AO8+AQ8+AS8+AU8+AW8+AY8+BA8+BC8 | BF8: =#REF!+L8+N8+P8+R8+T8+V8+X8+Z8+AB8+AD8+AF8+AH8+AJ8+AL8+AN8+AP8+AR8+AT8+AV8+AX8 | BG8: =BE8-BF8
A9: Яндекс | B9: Приход | I9: 6000000 | M9: 6000000 | Q9: 10000000 | W9: 6000000 | AA9: 10000000 | AG9: 6000000 | AK9: 10000000 | AQ9: 9000000 | AU9: 10000000 | BA9: 9000000 | BE9: =K9+M9+O9+Q9+S9+U9+W9+Y9+AA9+AC9+AE9+AG9+AI9+AK9+AM9+AO9+AQ9+AS9+AU9+AW9+AY9+BA9+BC9 | BF9: =#REF!+L9+N9+P9+R9+T9+V9+X9+Z9+AB9+AD9+AF9+AH9+AJ9+AL9+AN9+AP9+AR9+AT9+AV9+AX9 | BG9: =BE9-BF9
A10: Май Март | B10: Приход | G10: 1000000 | M10: 2000000 | Q10: 2000000 | AA10: 2000000 | AK10: 2000000 | AQ10: 2000000 | AU10: 2000000 | BA10: 2000000 | BE10: =K10+M10+O10+Q10+S10+U10+W10+Y10+AA10+AC10+AE10+AG10+AI10+AK10+AM10+AO10+AQ10+AS10+AU10+AW10+AY10+BA10+BC10 | BF10: =#REF!+L10+N10+P10+R10+T10+V10+X10+Z10+AB10+AD10+AF10+AH10+AJ10+AL10+AN10+AP10+AR10+AT10+AV10+AX10 | BG10: =BE10-BF10
A11: 7-Kaspi Банк | B11: Приход | G11: 1000000 | I11: 1500000 | O11: 1000000 | Q11: 1000000 | S11: 1000000 | U11: 1000000 | W11: 1000000 | Y11: 1000000 | AA11: 1000000 | AC11: 1000000 | AE11: 1000000 | AG11: 1000000 | AI11: 1000000 | AK11: 1000000 | AM11: 1000000 | AO11: 1000000 | AS11: 1000000 | AW11: 1000000 | AY11: 1000000 | BC11: 1000000 | BE11: =K11+M11+O11+Q11+S11+U11+W11+Y11+AA11+AC11+AE11+AG11+AI11+AK11+AM11+AO11+AQ11+AS11+AU11+AW11+AY11+BA11+BC11 | BF11: =#REF!+L11+N11+P11+R11+T11+V11+X11+Z11+AB11+AD11+AF11+AH11+AJ11+AL11+AN11+AP11+AR11+AT11+AV11+AX11 | BG11: =BE11-BF11
A12: Crave | B12: Приход | U12: 3000000 | Y12: 3000000 | AC12: 3000000 | AE12: 3000000 | AI12: 3000000 | AS12: 3000000 | AW12: 3000000 | AY12: 3000000 | BC12: 3000000 | BE12: =K12+M12+O12+Q12+S12+U12+W12+Y12+AA12+AC12+AE12+AG12+AI12+AK12+AM12+AO12+AQ12+AS12+AU12+AW12+AY12+BA12+BC12 | BF12: =#REF!+L12+N12+P12+R12+T12+V12+X12+Z12+AB12+AD12+AF12+AH12+AJ12+AL12+AN12+AP12+AR12+AT12+AV12+AX12 | BG12: =BE12-BF12
A13: 99-RP АЗС | B13: Приход | I13: 5000000 | Q13: 8000000 | AA13: 6000000 | AK13: 6000000 | AU13: 6000000 | BE13: =K13+M13+O13+Q13+S13+U13+W13+Y13+AA13+AC13+AE13+AG13+AI13+AK13+AM13+AO13+AQ13+AS13+AU13+AW13+AY13+BA13+BC13 | BF13: =#REF!+L13+N13+P13+R13+T13+V13+X13+Z13+AB13+AD13+AF13+AH13+AJ13+AL13+AN13+AP13+AR13+AT13+AV13+AX13 | BG13: =BE13-BF13
A14: 96- DSF покупатель | B14: Приход | G14: 5000000 | M14: 4000000 | AC14: 2000000 | AK14: 2000000 | AS14: 1000000 | BC14: 1000000 | BE14: =K14+M14+O14+Q14+S14+U14+W14+Y14+AA14+AC14+AE14+AG14+AI14+AK14+AM14+AO14+AQ14+AS14+AU14+AW14+AY14+BA14+BC14 | BF14: =#REF!+L14+N14+P14+R14+T14+V14+X14+Z14+AB14+AD14+AF14+AH14+AJ14+AL14+AN14+AP14+AR14+AT14+AV14+AX14 | BG14: =BE14-BF14
A15: 85-ДФЗ дистрибьютер ФЗ | B15: Приход | G15: 2000000 | I15: 2200000 | K15: 11900000 | M15: 4000000 | O15: 10000000 | Q15: 4000000 | S15: 2000000 | U15: 2000000 | W15: 2000000 | Y15: 10000000 | AA15: 4000000 | AC15: 2000000 | AE15: 4000000 | AG15: 1000000 | AI15: 10000000 | AK15: 4000000 | AM15: 2000000 | AO15: 2000000 | AQ15: 5000000 | AS15: 10000000 | AU15: 4000000 | AW15: 4000000 | AY15: 2000000 | BA15: 5000000 | BC15: 10000000 | BE15: =K15+M15+O15+Q15+S15+U15+W15+Y15+AA15+AC15+AE15+AG15+AI15+AK15+AM15+AO15+AQ15+AS15+AU15+AW15+AY15+BA15+BC15 | BF15: =#REF!+L15+N15+P15+R15+T15+V15+X15+Z15+AB15+AD15+AF15+AH15+AJ15+AL15+AN15+AP15+AR15+AT15+AV15+AX15 | BG15: =BE15-BF15
A16: 110 АЗС №67 "Sinooil" | B16: Приход | S16: 1000000 | W16: 1500000 | AE16: 1000000 | AS16: 2000000 | BC16: 2000000 | BE16: =K16+M16+O16+Q16+S16+U16+W16+Y16+AA16+AC16+AE16+AG16+AI16+AK16+AM16+AO16+AQ16+AS16+AU16+AW16+AY16+BA16+BC16 | BF16: =#REF!+L16+N16+P16+R16+T16+V16+X16+Z16+AB16+AD16+AF16+AH16+AJ16+AL16+AN16+AP16+AR16+AT16+AV16+AX16 | BG16: =BE16-BF16
A17: 100 ТУАР (шинлайн) | B17: Приход | G17: 150000 | BE17: =K17+M17+O17+Q17+S17+U17+W17+Y17+AA17+AC17+AE17+AG17+AI17+AK17+AM17+AO17+AQ17+AS17+AU17+AW17+AY17+BA17+BC17 | BF17: =#REF!+L17+N17+P17+R17+T17+V17+X17+Z17+AB17+AD17+AF17+AH17+AJ17+AL17+AN17+AP17+AR17+AT17+AV17+AX17 | BG17: =BE17-BF17
A18: Даркстор Чоко | B18: Приход | M18: 600000 | U18: 500000 | Y18: 500000 | AK18: 650000 | AO18: 150000 | AS18: 150000 | AY18: 150000 | BC18: 150000 | BE18: =K18+M18+O18+Q18+S18+U18+W18+Y18+AA18+AC18+AE18+AG18+AI18+AK18+AM18+AO18+AQ18+AS18+AU18+AW18+AY18+BA18+BC18 | BF18: =#REF!+L18+N18+P18+R18+T18+V18+X18+Z18+AB18+AD18+AF18+AH18+AJ18+AL18+AN18+AP18+AR18+AT18+AV18+AX18 | BG18: =BE18-BF18
A19: Глово, Вольт | B19: Приход | K19: 100000 | O19: 200000 | Q19: 200000 | S19: 100000 | W19: 100000 | AC19: 100000 | AE19: 100000 | AG19: 100000 | AI19: 100000 | AK19: 100000 | AM19: 100000 | AO19: 200000 | AQ19: 100000 | AS19: 200000 | AU19: 200000 | AW19: 200000 | AY19: 200000 | BA19: 100000 | BC19: 200000 | BE19: =K19+M19+O19+Q19+S19+U19+W19+Y19+AA19+AC19+AE19+AG19+AI19+AK19+AM19+AO19+AQ19+AS19+AU19+AW19+AY19+BA19+BC19 | BF19: =#REF!+L19+N19+P19+R19+T19+V19+X19+Z19+AB19+AD19+AF19+AH19+AJ19+AL19+AN19+AP19+AR19+AT19+AV19+AX19 | BG19: =BE19-BF19
A20: Торты | B20: Приход | Q20: 500000 | AK20: 300000 | AU20: 300000 | BE20: =K20+M20+O20+Q20+S20+U20+W20+Y20+AA20+AC20+AE20+AG20+AI20+AK20+AM20+AO20+AQ20+AS20+AU20+AW20+AY20+BA20+BC20 | BF20: =#REF!+L20+N20+P20+R20+T20+V20+X20+Z20+AB20+AD20+AF20+AH20+AJ20+AL20+AN20+AP20+AR20+AT20+AV20+AX20 | BG20: =BE20-BF20
A21: Итого по банку | B21: Приход | C21: 0 | D21: =SUM(D7:D20) | E21: =SUM(E7:E20) | F21: =SUM(F7:F20) | G21: =SUM(G7:G20) | H21: =SUM(H7:H20) | I21: =SUM(I7:I20) | J21: =SUM(J7:J20) | K21: =SUM(K7:K20) | ... BD21: =SUM(BD7:BD20) | BE21: =K21+M21+O21+Q21+S21+U21+W21+Y21+AA21+AC21+AE21+AG21+AI21+AK21+AM21+AO21+AQ21+AS21+AU21+AW21+AY21+BA21+BC21 | BF21: =#REF!+L21+N21+P21+R21+T21+V21+X21+Z21+AB21+AD21+AF21+AH21+AJ21+AL21+AN21+AP21+AR21+AT21+AV21+AX21 | BG21: =BE21-BF21
A22: 97- Кейтеринг гость | B22: Приход | Q22: 450000 | AA22: 250000 | AG22: 300000 | AQ22: 500000 | BA22: 500000 | BE22: =K22+M22+O22+Q22+S22+U22+W22+Y22+AA22+AC22+AE22+AG22+AI22+AK22+AM22+AO22+AQ22+AS22+AU22+AW22+AY22+BA22+BC22 | BF22: =#REF!+L22+N22+P22+R22+T22+V22+X22+Z22+AB22+AD22+AF22+AH22+AJ22+AL22+AN22+AP22+AR22+AT22+AV22+AX22 | BG22: =BE22-BF22
A23: Возврат с подотчета, Кредит | B23: Приход | H23: 40000 | BE23: =K23+M23+O23+Q23+S23+U23+W23+Y23+AA23+AC23+AE23+AG23+AI23+AK23+AM23+AO23+AQ23+AS23+AU23+AW23+AY23+BA23+BC23 | BF23: =#REF!+L23+N23+P23+R23+T23+V23+X23+Z23+AB23+AD23+AF23+AH23+AJ23+AL23+AN23+AP23+AR23+AT23+AV23+AX23 | BG23: =BE23-BF23
A24: Crave | B24: Приход | J24: 600000 | K24: 600000 | Q24: 600000 | U24: 600000 | AA24: 600000 | AE24: 600000 | AK24: 600000 | AO24: 600000 | AU24: 600000 | AY24: 600000 | BE24: =K24+M24+O24+Q24+S24+U24+W24+Y24+AA24+AC24+AE24+AG24+AI24+AK24+AM24+AO24+AQ24+AS24+AU24+AW24+AY24+BA24+BC24 | BF24: =#REF!+L24+N24+P24+R24+T24+V24+X24+Z24+AB24+AD24+AF24+AH24+AJ24+AL24+AN24+AP24+AR24+AT24+AV24+AX24 | BG24: =BE24-BF24
A25: 7-Kaspi Банк (нал) | B25: Приход | Q25: 1000000 | AA25: 1000000 | AK25: 1000000 | AU25: 1000000 | BE25: =K25+M25+O25+Q25+S25+U25+W25+Y25+AA25+AC25+AE25+AG25+AI25+AK25+AM25+AO25+AQ25+AS25+AU25+AW25+AY25+BA25+BC25 | BF25: =#REF!+L25+N25+P25+R25+T25+V25+X25+Z25+AB25+AD25+AF25+AH25+AJ25+AL25+AN25+AP25+AR25+AT25+AV25+AX25 | BG25: =BE25-BF25
A26: Частное лицо (Покупатель) | B26: Приход | Q26: 200000 | AA26: 400000 | AK26: 200000 | AQ26: 200000 | BA26: 200000 | BE26: =K26+M26+O26+Q26+S26+U26+W26+Y26+AA26+AC26+AE26+AG26+AI26+AK26+AM26+AO26+AQ26+AS26+AU26+AW26+AY26+BA26+BC26 | BF26: =#REF!+L26+N26+P26+R26+T26+V26+X26+Z26+AB26+AD26+AF26+AH26+AJ26+AL26+AN26+AP26+AR26+AT26+AV26+AX26 | BG26: =BE26-BF26
A27: 98-FOOD vending : СКЛАД АППАРАТ №1 (ФЗ Ермагамбет) | B27: Приход | Q27: 1500000 | AA27: 1500000 | AK27: 1500000 | AU27: 1500000 | BE27: =K27+M27+O27+Q27+S27+U27+W27+Y27+AA27+AC27+AE27+AG27+AI27+AK27+AM27+AO27+AQ27+AS27+AU27+AW27+AY27+BA27+BC27 | BF27: =#REF!+L27+N27+P27+R27+T27+V27+X27+Z27+AB27+AD27+AF27+AH27+AJ27+AL27+AN27+AP27+AR27+AT27+AV27+AX27 | BG27: =BE27-BF27
A28: Итого по кассе | B28: Приход | C28: 0 | D28: =SUM(D22:D27) | E28: =SUM(E22:E27) | F28: =SUM(F22:F27) | G28: =SUM(G22:G27) | H28: =SUM(H22:H27) | I28: =SUM(I22:I27) | J28: =SUM(J22:J27) | K28: =SUM(K22:K27) | ... BD28: =SUM(BD22:BD27) | BE28: =K28+M28+O28+Q28+S28+U28+W28+Y28+AA28+AC28+AE28+AG28+AI28+AK28+AM28+AO28+AQ28+AS28+AU28+AW28+AY28+BA28+BC28 | BF28: =#REF!+L28+N28+P28+R28+T28+V28+X28+Z28+AB28+AD28+AF28+AH28+AJ28+AL28+AN28+AP28+AR28+AT28+AV28+AX28 | BG28: =BE28-BF28
A29: 1.Выручка | B29: Приход | C29: 0 | D29: =D21+D28 | E29: =E21+E28 | F29: =F21+F28 | G29: =G21+G28 | H29: =H21+H28 | I29: =I21+I28 | J29: =J21+J28 | K29: =K21+K28 | ... BD29: =BD21+BD28 | BE29: =K29+M29+O29+Q29+S29+U29+W29+Y29+AA29+AC29+AE29+AG29+AI29+AK29+AM29+AO29+AQ29+AS29+AU29+AW29+AY29+BA29+BC29 | BF29: =#REF!+L29+N29+P29+R29+T29+V29+X29+Z29+AB29+AD29+AF29+AH29+AJ29+AL29+AN29+AP29+AR29+AT29+AV29+AX29 | BG29: =BE29-BF29
A30: IT-обслуживание,телефония,интернет | B30: Расход | G30: -82240 | H30: =-85400-85177 | I30: -220400 | M30: -90000 | Q30: -220400 | AO30: -90000 | AQ30: -90000 | AY30: -90000 | BA30: -90000 | BE30: =K30+M30+O30+Q30+S30+U30+W30+Y30+AA30+AC30+AE30+AG30+AI30+AK30+AM30+AO30+AQ30+AS30+AU30+AW30+AY30+BA30+BC30 | BF30: =#REF!+L30+N30+P30+R30+T30+V30+X30+Z30+AB30+AD30+AF30+AH30+AJ30+AL30+AN30+AP30+AR30+AT30+AV30+AX30 | BG30: =BE30-BF30
A31: Авансы поставщикам | B31: Расход | BE31: =K31+M31+O31+Q31+S31+U31+W31+Y31+AA31+AC31+AE31+AG31+AI31+AK31+AM31+AO31+AQ31+AS31+AU31+AW31+AY31+BA31+BC31 | BF31: =#REF!+L31+N31+P31+R31+T31+V31+X31+Z31+AB31+AD31+AF31+AH31+AJ31+AL31+AN31+AP31+AR31+AT31+AV31+AX31 | BG31: =BE31-BF31
A32: Административные расходы | B32: Расход | H32: =-4000-1950 | I32: -3000 | J32: -6050 | K32: -55000 | M32: =-400000 | O32: -55000 | Q32: -55000 | S32: -55000 | U32: -55000 | W32: -30000 | Y32: -55000 | AA32: -55000 | AC32: -55000 | AE32: -55000 | AG32: -55000 | AI32: -55000 | AK32: -55000 | AM32: -55000 | AO32: -55000 | AQ32: -55000 | AS32: -55000 | AU32: -55000 | AW32: -55000 | AY32: -55000 | BA32: -55000 | BC32: -55000 | BE32: =K32+M32+O32+Q32+S32+U32+W32+Y32+AA32+AC32+AE32+AG32+AI32+AK32+AM32+AO32+AQ32+AS32+AU32+AW32+AY32+BA32+BC32 | BF32: =#REF!+L32+N32+P32+R32+T32+V32+X32+Z32+AB32+AD32+AF32+AH32+AJ32+AL32+AN32+AP32+AR32+AT32+AV32+AX32 | BG32: =BE32-BF32
A33: Возврат ВФП | B33: Расход | BE33: =K33+M33+O33+Q33+S33+U33+W33+Y33+AA33+AC33+AE33+AG33+AI33+AK33+AM33+AO33+AQ33+AS33+AU33+AW33+AY33+BA33+BC33 | BF33: =#REF!+L33+N33+P33+R33+T33+V33+X33+Z33+AB33+AD33+AF33+AH33+AJ33+AL33+AN33+AP33+AR33+AT33+AV33+AX33 | BG33: =BE33-BF33
A34: Представительские расходы | B34: Расход | BE34: =K34+M34+O34+Q34+S34+U34+W34+Y34+AA34+AC34+AE34+AG34+AI34+AK34+AM34+AO34+AQ34+AS34+AU34+AW34+AY34+BA34+BC34 | BF34: =#REF!+L34+N34+P34+R34+T34+V34+X34+Z34+AB34+AD34+AF34+AH34+AJ34+AL34+AN34+AP34+AR34+AT34+AV34+AX34 | BG34: =BE34-BF34
A35: Аренда помещений | B35: Расход | W35: -6655000 | BE35: =K35+M35+O35+Q35+S35+U35+W35+Y35+AA35+AC35+AE35+AG35+AI35+AK35+AM35+AO35+AQ35+AS35+AU35+AW35+AY35+BA35+BC35 | BF35: =#REF!+L35+N35+P35+R35+T35+V35+X35+Z35+AB35+AD35+AF35+AH35+AJ35+AL35+AN35+AP35+AR35+AT35+AV35+AX35 | BG35: =BE35-BF35
A36: Газ | B36: Расход | AO36: -630000 | AY36: -630000 | BE36: =K36+M36+O36+Q36+S36+U36+W36+Y36+AA36+AC36+AE36+AG36+AI36+AK36+AM36+AO36+AQ36+AS36+AU36+AW36+AY36+BA36+BC36 | BF36: =#REF!+L36+N36+P36+R36+T36+V36+X36+Z36+AB36+AD36+AF36+AH36+AJ36+AL36+AN36+AP36+AR36+AT36+AV36+AX36 | BG36: =BE36-BF36
A37: Маркетинг | B37: Расход | BE37: =K37+M37+O37+Q37+S37+U37+W37+Y37+AA37+AC37+AE37+AG37+AI37+AK37+AM37+AO37+AQ37+AS37+AU37+AW37+AY37+BA37+BC37 | BF37: =#REF!+L37+N37+P37+R37+T37+V37+X37+Z37+AB37+AD37+AF37+AH37+AJ37+AL37+AN37+AP37+AR37+AT37+AV37+AX37 | BG37: =BE37-BF37
A38: Мусор | B38: Расход | AC38: -100000 | AK38: -642920 | BE38: =K38+M38+O38+Q38+S38+U38+W38+Y38+AA38+AC38+AE38+AG38+AI38+AK38+AM38+AO38+AQ38+AS38+AU38+AW38+AY38+BA38+BC38 | BF38: =#REF!+L38+N38+P38+R38+T38+V38+X38+Z38+AB38+AD38+AF38+AH38+AJ38+AL38+AN38+AP38+AR38+AT38+AV38+AX38 | BG38: =BE38-BF38
A39: Налоги и другие платежи в бюджет | B39: Расход | AC39: -8000000 | AE39: -6000000 | AQ39: -12000000 | BA39: -12000000 | BE39: =K39+M39+O39+Q39+S39+U39+W39+Y39+AA39+AC39+AE39+AG39+AI39+AK39+AM39+AO39+AQ39+AS39+AU39+AW39+AY39+BA39+BC39 | BF39: =#REF!+L39+N39+P39+R39+T39+V39+X39+Z39+AB39+AD39+AF39+AH39+AJ39+AL39+AN39+AP39+AR39+AT39+AV39+AX39 | BG39: =BE39-BF39
A40: Оплата труда | B40: Расход | Q40: -18500000 | AK40: -2030000 | BE40: =K40+M40+O40+Q40+S40+U40+W40+Y40+AA40+AC40+AE40+AG40+AI40+AK40+AM40+AO40+AQ40+AS40+AU40+AW40+AY40+BA40+BC40 | BF40: =#REF!+L40+N40+P40+R40+T40+V40+X40+Z40+AB40+AD40+AF40+AH40+AJ40+AL40+AN40+AP40+AR40+AT40+AV40+AX40 | BG40: =BE40-BF40
A41: Охрана | B41: Расход | W41: -1000000 | BE41: =K41+M41+O41+Q41+S41+U41+W41+Y41+AA41+AC41+AE41+AG41+AI41+AK41+AM41+AO41+AQ41+AS41+AU41+AW41+AY41+BA41+BC41 | BF41: =#REF!+L41+N41+P41+R41+T41+V41+X41+Z41+AB41+AD41+AF41+AH41+AJ41+AL41+AN41+AP41+AR41+AT41+AV41+AX41 | BG41: =BE41-BF41
A42: Платежи поставщикам Прочее | B42: Расход | G42: -180000 | BE42: =K42+M42+O42+Q42+S42+U42+W42+Y42+AA42+AC42+AE42+AG42+AI42+AK42+AM42+AO42+AQ42+AS42+AU42+AW42+AY42+BA42+BC42 | BF42: =#REF!+L42+N42+P42+R42+T42+V42+X42+Z42+AB42+AD42+AF42+AH42+AJ42+AL42+AN42+AP42+AR42+AT42+AV42+AX42 | BG42: =BE42-BF42
A43: Производственные расходы | B43: Расход | M43: -3000000 | Q43: -3000000 | W43: -3000000 | Y43: -3000000 | AA43: -3000000 | AK43: -3000000 | AO43: -3000000 | AU43: -3000000 | AY43: -3000000 | BE43: =K43+M43+O43+Q43+S43+U43+W43+Y43+AA43+AC43+AE43+AG43+AI43+AK43+AM43+AO43+AQ43+AS43+AU43+AW43+AY43+BA43+BC43 | BF43: =#REF!+L43+N43+P43+R43+T43+V43+X43+Z43+AB43+AD43+AF43+AH43+AJ43+AL43+AN43+AP43+AR43+AT43+AV43+AX43 | BG43: =BE43-BF43
A44: Инвентарь | B44: Расход | BE44: =K44+M44+O44+Q44+S44+U44+W44+Y44+AA44+AC44+AE44+AG44+AI44+AK44+AM44+AO44+AQ44+AS44+AU44+AW44+AY44+BA44+BC44 | BF44: =#REF!+L44+N44+P44+R44+T44+V44+X44+Z44+AB44+AD44+AF44+AH44+AJ44+AL44+AN44+AP44+AR44+AT44+AV44+AX44 | BG44: =BE44-BF44
A45: Униформа | B45: Расход | BE45: =K45+M45+O45+Q45+S45+U45+W45+Y45+AA45+AC45+AE45+AG45+AI45+AK45+AM45+AO45+AQ45+AS45+AU45+AW45+AY45+BA45+BC45 | BF45: =#REF!+L45+N45+P45+R45+T45+V45+X45+Z45+AB45+AD45+AF45+AH45+AJ45+AL45+AN45+AP45+AR45+AT45+AV45+AX45 | BG45: =BE45-BF45
A46: Упаковка | B46: Расход | J46: =-510400 | M46: -2500000 | S46: -2000000 | Y46: -1500000 | AA46: -900000 | AC46: -600000 | AG46: -1000000 | AK46: -1000000 | AM46: -2000000 | BE46: =K46+M46+O46+Q46+S46+U46+W46+Y46+AA46+AC46+AE46+AG46+AI46+AK46+AM46+AO46+AQ46+AS46+AU46+AW46+AY46+BA46+BC46 | BF46: =#REF!+L46+N46+P46+R46+T46+V46+X46+Z46+AB46+AD46+AF46+AH46+AJ46+AL46+AN46+AP46+AR46+AT46+AV46+AX46 | BG46: =BE46-BF46
A47: Хоз.товара | B47: Расход | AC47: -300000 | BE47: =K47+M47+O47+Q47+S47+U47+W47+Y47+AA47+AC47+AE47+AG47+AI47+AK47+AM47+AO47+AQ47+AS47+AU47+AW47+AY47+BA47+BC47 | BF47: =#REF!+L47+N47+P47+R47+T47+V47+X47+Z47+AB47+AD47+AF47+AH47+AJ47+AL47+AN47+AP47+AR47+AT47+AV47+AX47 | BG47: =BE47-BF47
A48: Погашение кредита и %% | B48: Расход | AO48: -1198352 | AU48: =-915358-1770150 | AW48: =-915358-1770150 | AY48: -1198352 | BE48: =K48+M48+O48+Q48+S48+U48+W48+Y48+AA48+AC48+AE48+AG48+AI48+AK48+AM48+AO48+AQ48+AS48+AU48+AW48+AY48+BA48+BC48 | BF48: =#REF!+L48+N48+P48+R48+T48+V48+X48+Z48+AB48+AD48+AF48+AH48+AJ48+AL48+AN48+AP48+AR48+AT48+AV48+AX48 | BG48: =BE48-BF48
A49: Расходы по реализации Разные(Логистика) | B49: Расход | I49: -2000000 | M49: -800000 | S49: -2725000 | W49: -800000 | AC49: -2725000 | AG49: -800000 | AM49: -2725000 | AQ49: -800000 | AW49: -2725000 | BA49: -800000 | BE49: =K49+M49+O49+Q49+S49+U49+W49+Y49+AA49+AC49+AE49+AG49+AI49+AK49+AM49+AO49+AQ49+AS49+AU49+AW49+AY49+BA49+BC49 | BF49: =#REF!+L49+N49+P49+R49+T49+V49+X49+Z49+AB49+AD49+AF49+AH49+AJ49+AL49+AN49+AP49+AR49+AT49+AV49+AX49 | BG49: =BE49-BF49
A50: Ремонт помещений | B50: Расход | BE50: =K50+M50+O50+Q50+S50+U50+W50+Y50+AA50+AC50+AE50+AG50+AI50+AK50+AM50+AO50+AQ50+AS50+AU50+AW50+AY50+BA50+BC50 | BF50: =#REF!+L50+N50+P50+R50+T50+V50+X50+Z50+AB50+AD50+AF50+AH50+AJ50+AL50+AN50+AP50+AR50+AT50+AV50+AX50 | BG50: =BE50-BF50
A51: Ремонт оборудования | B51: Расход | BE51: =K51+M51+O51+Q51+S51+U51+W51+Y51+AA51+AC51+AE51+AG51+AI51+AK51+AM51+AO51+AQ51+AS51+AU51+AW51+AY51+BA51+BC51 | BF51: =#REF!+L51+N51+P51+R51+T51+V51+X51+Z51+AB51+AD51+AF51+AH51+AJ51+AL51+AN51+AP51+AR51+AT51+AV51+AX51 | BG51: =BE51-BF51
A52: Приобретение основных средств | B52: Расход | BE52: =K52+M52+O52+Q52+S52+U52+W52+Y52+AA52+AC52+AE52+AG52+AI52+AK52+AM52+AO52+AQ52+AS52+AU52+AW52+AY52+BA52+BC52 | BF52: =#REF!+L52+N52+P52+R52+T52+V52+X52+Z52+AB52+AD52+AF52+AH52+AJ52+AL52+AN52+AP52+AR52+AT52+AV52+AX52 | BG52: =BE52-BF52
A53: Сырье Платежи поставщикам | B53: Расход | H53: =-7743006 | J53: =-7167264 | K53: -5000000 | M53: -5000000 | O53: -5000000 | Q53: -5000000 | S53: -5000000 | U53: -5000000 | W53: -8000000 | Y53: -5000000 | AA53: -6000000 | AC53: -5000000 | AE53: -5000000 | AG53: -5000000 | AI53: -5000000 | AK53: -5000000 | AM53: -5000000 | AO53: -5000000 | AQ53: -5000000 | AS53: -5000000 | AU53: -5000000 | AW53: -5000000 | AY53: -5000000 | BA53: -5000000 | BC53: -5000000 | BE53: =K53+M53+O53+Q53+S53+U53+W53+Y53+AA53+AC53+AE53+AG53+AI53+AK53+AM53+AO53+AQ53+AS53+AU53+AW53+AY53+BA53+BC53 | BF53: =#REF!+L53+N53+P53+R53+T53+V53+X53+Z53+AB53+AD53+AF53+AH53+AJ53+AL53+AN53+AP53+AR53+AT53+AV53+AX53 | BG53: =BE53-BF53
A54: Электроэнергия | B54: Расход | AO54: -6900000 | AY54: -6900000 | BE54: =K54+M54+O54+Q54+S54+U54+W54+Y54+AA54+AC54+AE54+AG54+AI54+AK54+AM54+AO54+AQ54+AS54+AU54+AW54+AY54+BA54+BC54 | BF54: =#REF!+L54+N54+P54+R54+T54+V54+X54+Z54+AB54+AD54+AF54+AH54+AJ54+AL54+AN54+AP54+AR54+AT54+AV54+AX54 | BG54: =BE54-BF54
A55: Итого по банку | B55: Расход | C55: 0 | D55: =SUM(D30:D54) | E55: =SUM(E30:E54) | F55: =SUM(F30:F54) | G55: =SUM(G30:G54) | H55: =SUM(H30:H54) | I55: =SUM(I30:I54) | J55: =SUM(J30:J54) | K55: =SUM(K30:K54) | ... BD55: =SUM(BD30:BD54) | BE55: =K55+M55+O55+Q55+S55+U55+W55+Y55+AA55+AC55+AE55+AG55+AI55+AK55+AM55+AO55+AQ55+AS55+AU55+AW55+AY55+BA55+BC55 | BF55: =#REF!+L55+N55+P55+R55+T55+V55+X55+Z55+AB55+AD55+AF55+AH55+AJ55+AL55+AN55+AP55+AR55+AT55+AV55+AX55 | BG55: =BE55-BF55
A56: Подотчет (Рынок сырье, Рынок ТМЦ) | B56: Расход | H56: =-500000 | I56: -500000 | K56: -300000 | Q56: -500000 | S56: -500000 | U56: -500000 | AA56: -500000 | AC56: -500000 | AK56: -800000 | AU56: -500000 | AW56: -500000 | BE56: =K56+M56+O56+Q56+S56+U56+W56+Y56+AA56+AC56+AE56+AG56+AI56+AK56+AM56+AO56+AQ56+AS56+AU56+AW56+AY56+BA56+BC56 | BF56: =#REF!+L56+N56+P56+R56+T56+V56+X56+Z56+AB56+AD56+AF56+AH56+AJ56+AL56+AN56+AP56+AR56+AT56+AV56+AX56 | BG56: =BE56-BF56
A57: Административные расходы | B57: Расход | H57: =-2580 | I57: -109000 | M57: -55000 | O57: -55000 | Q57: -55000 | S57: -55000 | U57: -30000 | W57: -55000 | Y57: -55000 | AA57: -55000 | AC57: -55000 | AE57: -55000 | AG57: -55000 | AI57: -55000 | AK57: -55000 | AM57: -55000 | AO57: -55000 | AQ57: -55000 | AS57: -55000 | AU57: -55000 | AY57: -55000 | BA57: -55000 | BC57: -55000 | BE57: =K57+M57+O57+Q57+S57+U57+W57+Y57+AA57+AC57+AE57+AG57+AI57+AK57+AM57+AO57+AQ57+AS57+AU57+AW57+AY57+BA57+BC57 | BF57: =#REF!+L57+N57+P57+R57+T57+V57+X57+Z57+AB57+AD57+AF57+AH57+AJ57+AL57+AN57+AP57+AR57+AT57+AV57+AX57 | BG57: =BE57-BF57
A58: Представительские расходы | B58: Расход | BE58: =K58+M58+O58+Q58+S58+U58+W58+Y58+AA58+AC58+AE58+AG58+AI58+AK58+AM58+AO58+AQ58+AS58+AU58+AW58+AY58+BA58+BC58 | BF58: =#REF!+L58+N58+P58+R58+T58+V58+X58+Z58+AB58+AD58+AF58+AH58+AJ58+AL58+AN58+AP58+AR58+AT58+AV58+AX58 | BG58: =BE58-BF58
A59: Аренда квартир | B59: Расход | U59: =-175000-300000 | W59: -500000 | AC59: -500000 | AK59: -350149 | BE59: =K59+M59+O59+Q59+S59+U59+W59+Y59+AA59+AC59+AE59+AG59+AI59+AK59+AM59+AO59+AQ59+AS59+AU59+AW59+AY59+BA59+BC59 | BF59: =#REF!+L59+N59+P59+R59+T59+V59+X59+Z59+AB59+AD59+AF59+AH59+AJ59+AL59+AN59+AP59+AR59+AT59+AV59+AX59 | BG59: =BE59-BF59
A60: Налоги и другие платежи в бюджет | B60: Расход | F60: -746 | BE60: =K60+M60+O60+Q60+S60+U60+W60+Y60+AA60+AC60+AE60+AG60+AI60+AK60+AM60+AO60+AQ60+AS60+AU60+AW60+AY60+BA60+BC60 | BF60: =#REF!+L60+N60+P60+R60+T60+V60+X60+Z60+AB60+AD60+AF60+AH60+AJ60+AL60+AN60+AP60+AR60+AT60+AV60+AX60 | BG60: =BE60-BF60
A61: Маркетинг | B61: Расход | Q61: -450000 | BE61: =K61+M61+O61+Q61+S61+U61+W61+Y61+AA61+AC61+AE61+AG61+AI61+AK61+AM61+AO61+AQ61+AS61+AU61+AW61+AY61+BA61+BC61 | BF61: =#REF!+L61+N61+P61+R61+T61+V61+X61+Z61+AB61+AD61+AF61+AH61+AJ61+AL61+AN61+AP61+AR61+AT61+AV61+AX61 | BG61: =BE61-BF61
A62: Оплата труда | B62: Расход | H62: =-100000-40000 | J62: -1261000 | K62: -3000000 | M62: -3000000 | Q62: -10000000 | Y62: -2500000 | AA62: -8000000 | AC62: -7000000 | AK62: -800000 | AM62: -7000000 | AO62: -5000000 | AQ62: -2000000 | AS62: -2000000 | AU62: -3000000 | AW62: -2000000 | AY62: -5000000 | BA62: -2000000 | BC62: -2000000 | BE62: =K62+M62+O62+Q62+S62+U62+W62+Y62+AA62+AC62+AE62+AG62+AI62+AK62+AM62+AO62+AQ62+AS62+AU62+AW62+AY62+BA62+BC62 | BF62: =#REF!+L62+N62+P62+R62+T62+V62+X62+Z62+AB62+AD62+AF62+AH62+AJ62+AL62+AN62+AP62+AR62+AT62+AV62+AX62 | BG62: =BE62-BF62
A63: Платежи поставщикам Прочее | B63: Расход | BE63: =K63+M63+O63+Q63+S63+U63+W63+Y63+AA63+AC63+AE63+AG63+AI63+AK63+AM63+AO63+AQ63+AS63+AU63+AW63+AY63+BA63+BC63 | BF63: =#REF!+L63+N63+P63+R63+T63+V63+X63+Z63+AB63+AD63+AF63+AH63+AJ63+AL63+AN63+AP63+AR63+AT63+AV63+AX63 | BG63: =BE63-BF63
A64: Производственные расходы | B64: Расход | I64: -48000 | J64: =-48000 | K64: -48000 | Q64: -48000 | U64: -42000 | W64: -42000 | AG64: -48000 | AK64: -48000 | AQ64: -48000 | BA64: -48000 | BE64: =K64+M64+O64+Q64+S64+U64+W64+Y64+AA64+AC64+AE64+AG64+AI64+AK64+AM64+AO64+AQ64+AS64+AU64+AW64+AY64+BA64+BC64 | BF64: =#REF!+L64+N64+P64+R64+T64+V64+X64+Z64+AB64+AD64+AF64+AH64+AJ64+AL64+AN64+AP64+AR64+AT64+AV64+AX64 | BG64: =BE64-BF64
A65: Инвентарь | B65: Расход | I65: =-15000-69000 | K65: =-15000-27000 | M65: -40000 | W65: =-116000-19100 | AG65: -32000 | AI65: -35000 | BE65: =K65+M65+O65+Q65+S65+U65+W65+Y65+AA65+AC65+AE65+AG65+AI65+AK65+AM65+AO65+AQ65+AS65+AU65+AW65+AY65+BA65+BC65 | BF65: =#REF!+L65+N65+P65+R65+T65+V65+X65+Z65+AB65+AD65+AF65+AH65+AJ65+AL65+AN65+AP65+AR65+AT65+AV65+AX65 | BG65: =BE65-BF65
A66: Погашение кредита и %% | B66: Расход | BE66: =K66+M66+O66+Q66+S66+U66+W66+Y66+AA66+AC66+AE66+AG66+AI66+AK66+AM66+AO66+AQ66+AS66+AU66+AW66+AY66+BA66+BC66 | BF66: =#REF!+L66+N66+P66+R66+T66+V66+X66+Z66+AB66+AD66+AF66+AH66+AJ66+AL66+AN66+AP66+AR66+AT66+AV66+AX66 | BG66: =BE66-BF66
A67: Хоз.товара | B67: Расход | BE67: =K67+M67+O67+Q67+S67+U67+W67+Y67+AA67+AC67+AE67+AG67+AI67+AK67+AM67+AO67+AQ67+AS67+AU67+AW67+AY67+BA67+BC67 | BF67: =#REF!+L67+N67+P67+R67+T67+V67+X67+Z67+AB67+AD67+AF67+AH67+AJ67+AL67+AN67+AP67+AR67+AT67+AV67+AX67 | BG67: =BE67-BF67
A68: Канц.товары | B68: Расход | BE68: =K68+M68+O68+Q68+S68+U68+W68+Y68+AA68+AC68+AE68+AG68+AI68+AK68+AM68+AO68+AQ68+AS68+AU68+AW68+AY68+BA68+BC68 | BF68: =#REF!+L68+N68+P68+R68+T68+V68+X68+Z68+AB68+AD68+AF68+AH68+AJ68+AL68+AN68+AP68+AR68+AT68+AV68+AX68 | BG68: =BE68-BF68
A69: Расходы по реализации Разные | B69: Расход | J69: -8000 | BE69: =K69+M69+O69+Q69+S69+U69+W69+Y69+AA69+AC69+AE69+AG69+AI69+AK69+AM69+AO69+AQ69+AS69+AU69+AW69+AY69+BA69+BC69 | BF69: =#REF!+L69+N69+P69+R69+T69+V69+X69+Z69+AB69+AD69+AF69+AH69+AJ69+AL69+AN69+AP69+AR69+AT69+AV69+AX69 | BG69: =BE69-BF69
A70: Ремонт помещений | B70: Расход | BE70: =K70+M70+O70+Q70+S70+U70+W70+Y70+AA70+AC70+AE70+AG70+AI70+AK70+AM70+AO70+AQ70+AS70+AU70+AW70+AY70+BA70+BC70 | BF70: =#REF!+L70+N70+P70+R70+T70+V70+X70+Z70+AB70+AD70+AF70+AH70+AJ70+AL70+AN70+AP70+AR70+AT70+AV70+AX70 | BG70: =BE70-BF70
A71: Ремонт оборудования | B71: Расход | I71: -171500 | J71: =-75000 | BE71: =K71+M71+O71+Q71+S71+U71+W71+Y71+AA71+AC71+AE71+AG71+AI71+AK71+AM71+AO71+AQ71+AS71+AU71+AW71+AY71+BA71+BC71 | BF71: =#REF!+L71+N71+P71+R71+T71+V71+X71+Z71+AB71+AD71+AF71+AH71+AJ71+AL71+AN71+AP71+AR71+AT71+AV71+AX71 | BG71: =BE71-BF71
A72: Приобретение основных средств | B72: Расход | BE72: =K72+M72+O72+Q72+S72+U72+W72+Y72+AA72+AC72+AE72+AG72+AI72+AK72+AM72+AO72+AQ72+AS72+AU72+AW72+AY72+BA72+BC72 | BF72: =#REF!+L72+N72+P72+R72+T72+V72+X72+Z72+AB72+AD72+AF72+AH72+AJ72+AL72+AN72+AP72+AR72+AT72+AV72+AX72 | BG72: =BE72-BF72
A73: Сырье Платежи поставщикам | B73: Расход | H73: =-248600 | M73: -500000 | O73: -500000 | Q73: -500000 | W73: -500000 | Y73: -500000 | AA73: -500000 | AG73: -500000 | AI73: -500000 | AK73: -500000 | AQ73: -500000 | AS73: -500000 | AU73: -500000 | BA73: -500000 | BC73: -500000 | BE73: =K73+M73+O73+Q73+S73+U73+W73+Y73+AA73+AC73+AE73+AG73+AI73+AK73+AM73+AO73+AQ73+AS73+AU73+AW73+AY73+BA73+BC73 | BF73: =#REF!+L73+N73+P73+R73+T73+V73+X73+Z73+AB73+AD73+AF73+AH73+AJ73+AL73+AN73+AP73+AR73+AT73+AV73+AX73 | BG73: =BE73-BF73
A74: Итого по кассе | B74: Расход | C74: 0 | D74: =SUM(D56:D73) | E74: =SUM(E56:E73) | F74: =SUM(F56:F73) | G74: =SUM(G56:G73) | H74: =SUM(H56:H73) | I74: =SUM(I56:I73) | J74: =SUM(J56:J73) | K74: =SUM(K56:K73) | ... BE74: =SUM(BE56:BE73) | BF74: =#REF!+L74+N74+P74+R74+T74+V74+X74+Z74+AB74+AD74+AF74+AH74+AJ74+AL74+AN74+AP74+AR74+AT74+AV74+AX74 | BG74: =BE74-BF74
A75: ИТОГО РАСХОДЫ | C75: 0 | D75: =D55+D74 | E75: =E55+E74 | F75: =F55+F74 | G75: =G55+G74 | H75: =H55+H74 | I75: =I55+I74 | J75: =J55+J74 | K75: =K55+K74 | ... BE75: =BE55+BE74 | BF75: =#REF!+L75+N75+P75+R75+T75+V75+X75+Z75+AB75+AD75+AF75+AH75+AJ75+AL75+AN75+AP75+AR75+AT75+AV75+AX75 | BG75: =BE75-BF75
A76: Операционная деятельность | C76: 0 | D76: =D29-(-D55-D74) | E76: =E29-(-E55-E74) | F76: =F29-(-F55-F74) | G76: =G29-(-G55-G74) | H76: =H29-(-H55-H74) | I76: =I29-(-I55-I74) | J76: =J29-(-J55-J74) | K76: =K29-(-K55-K74) | M76: =M29-(-M55-M74) | N76: =N29-(-N55-N74) | O76: =O29-(-O55-O74) | P76: =P29-(-P55-P74) | Q76: =Q29-(-Q55-Q74) | R76: =R29-(-R55-R74) | S76: =S29-(-S55-S74) | T76: =T29-(-T55-T74) | ... AB76: =AB29-(-AB55-AB74) | AE76: =AE29-(-AE55-AE74) | AF76: =AF29-(-AF55-AF74) | AG76: =AG29-(-AG55-AG74) | AH76: =AH29-(-AH55-AH74) | AI76: =AI29-(-AJ56-AI74) | AJ76: =AJ29-(-AJ55-AJ74) | AK76: =AK29-(-AK74) | AL76: =AL29-(-AL55-AL74) | AM76: =AM29-(-AN56-AM74) | AN76: =AN29-(-AN55-AN74) | AO76: =AO29-(-AO55-AO74) | AP76: =AP29-(-AP55-AP74) | AQ76: =AQ29-(-AQ55-AQ74) | AR76: =AR29-(-AR55-AR74) | AS76: =AS29-(-AS55-AS74) | AT76: =AT29-(-AT55-AT74) | AU76: =AU29-(-AU55-AU74) | ... BE76: =BE29-(-BE55-BE74) | BF76: =#REF!+L76+N76+P76+R76+T76+V76+X76+Z76+AB76+AD76+AF76+AH76+AJ76+AL76+AN76+AP76+AR76+AT76+AV76+AX76
A77: ВФП Учредители поступление (НАЛ) | B77: Приход | BE77: =BE30-(-BE56-BE75) | BF77: =#REF!+L77+N77+P77+R77+T77+V77+X77+Z77+AB77+AD77+AF77+AH77+AJ77+AL77+AN77+AP77+AR77+AT77+AV77+AX77
B78: Расход | BE78: =BE31-(-BE57-BE76) | BF78: =#REF!+L78+N78+P78+R78+T78+V78+X78+Z78+AB78+AD78+AF78+AH78+AJ78+AL78+AN78+AP78+AR78+AT78+AV78+AX78
A79: Касса взаиморасчета банк | B79: Расход | C79: 4000000 | E79: 500000 | G79: 2000000 | J79: 1575000 | BE79: =BE32-(-BE58-BE77) | BF79: =#REF!+L79+N79+P79+R79+T79+V79+X79+Z79+AB79+AD79+AF79+AH79+AJ79+AL79+AN79+AP79+AR79+AT79+AV79+AX79
A80: Касса взаиморасчета касса | B80: Приход | C80: 4000000 | E80: 500000 | G80: 2000000 | J80: 1575000 | R80: 14990 | BE80: =BE33-(-BE59-BE78) | BF80: =#REF!+L80+N80+P80+R80+T80+V80+X80+Z80+AB80+AD80+AF80+AH80+AJ80+AL80+AN80+AP80+AR80+AT80+AV80+AX80
A81: Остаток на конец ПО БАНКУ | C81: -859672 | D81: =D5+D21-(-D55)-D79 | E81: =E5+E21-(-E55)-E79 | F81: =F5+F21-(-F55)-F79 | G81: =G5+G21-(-G55)-G79 | H81: =H5+H21-(-H55)-H79 | I81: =I5+I21-(-I55)-I79 | J81: =J5+J21-(-J55)-J79 | K81: 0 | L81: =L5+L21-(-L55)-L79 | M81: =M5+M21-(-M55)-M79 | N81: =N5+N21-(-N55)-N79 | O81: =O5+O21-(-O55)-O79 | P81: =P5+P21-(-P55)-P79 | Q81: =Q5+Q21-(-Q55)-Q79 | R81: =R5+R21-(-R55)-R79 | S81: =S5+S21-(-S55)-S79 | T81: =T5+T21-(-T55)-T79+T77 | U81: =U5+U21-(-U55)-U79 | V81: =V5+V21+V55-V79+V77 | W81: =W5+W21-(-W55)-W79 | X81: =X5+X21+X55-X79 | Y81: =Y5+Y21-(-Y55)-Y79 | Z81: =Z5+Z21-(-Z55)+Z77-Z79 | AA81: =AA5+AA21-(-AA55)-AA79 | AB81: =AB5+AB21-(-AB55)-AB79 | AC81: =AC5+AC21-(-AC55)-AC79 | AD81: =AD5+AD21-(-AD55)-AD79+AD77 | AE81: =AE5+AE21-(-AE55)-AE79 | AF81: =AF5+AF21-(-AF55)-AF79 | AG81: =AG5+AG21-(-AG55)-AG79 | AH81: =AH5+AH21-(-AH55)-AH79 | AI81: =AI5+AI21-(-AI55)-AI79 | AJ81: =AJ5+AJ21-(-AJ55)-AJ79 | AK81: =AK5+AK21-(-AK55)-AK79 | AL81: =AL5+AL21-(-AL55)-AL79+AL77 | AM81: =AM5+AM21-(-AM55)-AM79 | AN81: =AN5+AN21-(-AN55)-AN79+AN77-AN78 | AO81: =AO5+AO21-(-AO55)-AO79 | AP81: =AP5+AP21-(-AP55)-AP79 | AQ81: =AQ5+AQ21-(-AQ55)-AQ79 | AR81: =AR5+AR21-(-AR55)-AR79 | AS81: =AS5+AS21-(-AS55)-AS79 | AT81: =AT5+AT21-(-AT55)-AT79 | AU81: =AU5+AU21-(-AU55)-AU79+AU77-AU78 | AV81: =AV5+AV21-(-AV55)-AV79 | AW81: =AW5+AW21-(-AW55)-AW79+AW77-AW78 | AX81: =AX5+AX21-(-AX55)-AX79 | AY81: =AY5+AY21-(-AY55)-AY79 | AZ81: =AZ5+AZ21-(-AZ55)-AZ79 | BA81: =BA5+BA21-(-BA55)-BA79 | BB81: =BB5+BB21-(-BB55)-BB79 | BC81: =BC5+BC21-(-BC55)-BC79 | BD81: =BD5+BD21-(-BD55)-BD79 | BE81: =BE5+BE21-(-BE55)-BE79 | BF81: =BF5+BF21-(-BF55)-BF79
A82: Остаток на конец ПО КАССЕ | C82: 4917728 | D82: =D6+D28-(-D74)+D77-D78+D80 | E82: =E6+E28-(-E74)+E77-E78+E80 | F82: =F6+F28-(-F74)+F77-F78+F80 | G82: =G6+G28-(-G74)+G77-G78+G80 | H82: =H6+H28-(-H74)+H77-H78+H80 | I82: =I6+I28-(-I74)+I77-I78+I80 | J82: =J6+J28-(-J74)+J77-J78+J80 | K82: =K6+K28-(-K74)+K77-K78+K80 | ... S82: =S6+S28-(-S74)+S77-S78+S80 | T82: =T6+T28-(-T74)-T78+T80 | U82: =U6+U28-(-U74)+U77-U78+U80 | V82: =V6+V28-(-V74)+V80 | W82: =W6+W28-(-W74)+W77-W78+W80 | X82: =X6+X28-(-X74)+X77-X78+X80 | Y82: =Y6+Y28-(-Y74)+Y77-Y78+Y80 | Z82: =Z6+Z28-(-Z74)+Z80 | AA82: =AA6+AA28-(-AA74)+AA77-AA78+AA80 | AB82: =AB6+AB28-(-AB74)+AB77-AB78+AB80 | AC82: =AC6+AC28-(-AC74)+AC77-AC78+AC80 | AD82: =AD6+AD28-(-AD74)+AD80 | AE82: =AE6+AE28-(-AE74)+AE77-AE78+AE80 | AF82: =AF6+AF28-(-AF74)+AF77-AF78+AF80 | AG82: =AG6+AG28-(-AG74)+AG77-AG78+AG80 | AH82: =AH6+AH28-(-AH74)+AH77-AH78+AH80 | AI82: =AI6+AI28-(-AI74)+AI77-AI78+AI80 | AJ82: =AJ6+AJ28-(-AJ74)+AJ77-AJ78+AJ80 | AK82: =AK6+AK28-(-AK74)+AK77-AK78+AK80 | AL82: =AL6+AL28-(-AL74)-AL78+AL80 | AM82: =AM6+AM28-(-AM74)+AM77-AM78+AM80 | AN82: =AN6+AN28-(-AN74)+AN80 | AO82: =AO6+AO28-(-AO74)+AO77-AO78+AO80 | AP82: =AP6+AP28-(-AP74)+AP77-AP78+AP80 | AQ82: =AQ6+AQ28-(-AQ74)+AQ77-AQ78+AQ80 | AR82: =AR6+AR28-(-AR74)+AR77+AR80 | AS82: =AS6+AS28-(-AS74)+AS77-AS78+AS80 | AT82: =AT6+AT28-(-AT74)+AT77-AT78+AT80 | AU82: =AU6+AU28-(-AU74)+AU80 | AV82: =AV6+AV28-(-AV74)+AV77-AV78+AV80 | AW82: =AW6+AW28-(-AW74)+AW80 | AX82: =AX6+AX28-(-AX74)+AX77-AX78+AX80 | AY82: =AY6+AY28-(-AY74)+AY77-AY78+AY80 | AZ82: =AZ6+AZ28-(-AZ74)+AZ77-AZ78+AZ80 | BA82: =BA6+BA28-(-BA74)+BA77-BA78+BA80 | BB82: =BB6+BB28-(-BB74)+BB77+BB80 | BC82: =BC6+BC28-(-BC74)+BC77-BC78+BC80 | BD82: =BD6+BD28-(-BD74)+BD77-BD78+BD80 | BE82: =BE6+BE28-(-BE74)+BE77-BE78+BE80 | BF82: =BF6+BF28-(-BF74)+BF77-BF78+BF80
A83: Итого | C83: 4058056 | D83: =D81+D82 | E83: =E81+E82 | F83: =F81+F82 | G83: =G81+G82 | H83: =H81+H82 | I83: =I81+I82 | J83: =J81+J82 | K83: =K81+K82 | ... BF83: =BF81+BF82
T84: 2104029 | BE84: Итого май (+если есть деньги, - кас.разрыв) | BG84: =BG75+BG29
AV85: Факт АПРЕЛЬ | BE85: План | BF85: Факт | BG85: Отклонение
S86: Выплата поставщикам | AC86: Выплата поставщикам | AV86: ='ДДС ФАКТ Апрель'!I27+'ДДС ФАКТ Апрель'!I26+'ДДС ФАКТ Апрель'!I34+'ДДС ФАКТ Апрель'!I32+'ДДС ФАКТ Апрель'!I35 | AW86: Выплата поставщикам | BE86: =BE31+BE46+BE47+BE53+BE73+BE56+BE49 | BF86: =BF31+BF46+BF47+BF53+BF73+BF56 | BG86: =BE86-BF86
S87: Налоги | AC87: Налоги | AV87: ='ДДС ФАКТ Апрель'!I24 | AW87: Налоги | BE87: =BE39 | BF87: =BF39 | BG87: =BE87-BF87
S88: Оплата труда | AC88: Оплата труда | AV88: ='ДДС ФАКТ Апрель'!I25 | AW88: Оплата труда | BE88: =BE40+BE62 | BF88: =BF40+BF62 | BG88: =BE88-BF88
S89: Ремонт | AC89: Ремонт | AV89: ='ДДС ФАКТ Апрель'!I28+'ДДС ФАКТ Апрель'!I30 | AW89: Произв. расх | BE89: =BE64+BE43+BE44+BE51+BE65 | BF89: =BF51+BF50+BF70+BF71 | BG89: =BE89-BF89
S90: ОС | AC90: ОС | AW90: ОС | BE90: =BE52+BE72 | BF90: =BF52+BF72 | BG90: =BE90-BF90

Sheet ОБУ ИЮНЬ
A1: Сатья расхода | B1: Безналичныйрасчёт | H1: Наличныйрасчёт | N1: Итого Расходы май
B2: МАЙ 2026 года | G2: Итого без.нал | H2: МАЙ 2026 года | M2: Итого нал
B3: 1 неделя | C3: 2 неделя | D3: 3 неделя | E3: 4 неделя | F3: 5 неделя | H3: 1 неделя | I3: 2 неделя | J3: 3 неделя | K3: 4 неделя | L3: 5 неделя
A4: IT-обслуживание,телефония,интернет | B4: 170577 | C4: 310400 | G4: =B4+C4+D4+E4+F4 | M4: =SUM(H4:L4) | N4: =G4+M4
A5: Авансы поставщикам | G5: =B5+C5+D5+E5+F5 | M5: =SUM(H5:L5) | N5: =G5+M5
A6: Административные расходы | B6: 550000 | D6: 550000 | G6: =B6+C6+D6+E6+F6 | J6: 690000 | K6: 350000 | M6: =SUM(H6:L6) | N6: =G6+M6
A7: Страховка сотрудников | E7: 427718 | G7: =B7+C7+D7+E7+F7 | M7: =SUM(H7:L7) | N7: =G7+M7
A8: Возврат ВФП | G8: =B8+C8+D8+E8+F8 | M8: =SUM(H8:L8) | N8: =G8+M8
A9: Представительские расходы | G9: =B9+C9+D9+E9+F9 | M9: =SUM(H9:L9) | N9: =G9+M9
A10: Аренда помещений | D10: 6050000 | G10: =B10+C10+D10+E10+F10 | M10: =SUM(H10:L10) | N10: =G10+M10
A11: Газ | G11: =B11+C11+D11+E11+F11 | H11: 90000 | I11: 90000 | J11: 90000 | K11: 90000 | L11: 90000 | M11: =SUM(H11:L11) | N11: =G11+M11
A12: Маркетинг | G12: =B12+C12+D12+E12+F12 | M12: =SUM(H12:L12) | N12: =G12+M12
A13: Мусор | D13: 750000 | G13: =B13+C13+D13+E13+F13 | M13: =SUM(H13:L13) | N13: =G13+M13
A14: Налоги и другие платежи в бюджет (ЗАРПЛАТНЫЕ) | G14: =B14+C14+D14+E14+F14 | M14: =SUM(H14:L14) | N14: =G14+M14
A15: Налоги и другие платежи в бюджет (НДС) | G15: =B15+C15+D15+E15+F15 | M15: =SUM(H15:L15) | N15: =G15+M15
A16: Оплата труда (пятница-уволенные) (четверг-лагманщики) каждую неделю | G16: =B16+C16+D16+E16+F16 | H16: 2400000 | I16: 3000000 | J16: 2400000 | K16: 2400000 | L16: 2400000 | M16: =SUM(H16:L16) | N16: =G16+M16
A17: Оплата труда | C17: 16000000 | E17: 20000000 | G17: =B17+C17+D17+E17+F17 | I17: 20000000 | J17: 20000000 | K17: 20000000 | L17: 20000000 | M17: =SUM(H17:L17) | N17: =G17+M17
A18: Охрана | G18: =B18+C18+D18+E18+F18 | M18: =SUM(H18:L18) | N18: =G18+M18
A19: Платежи поставщикам Прочее | C19: 950000 | D19: 172450 | G19: =B19+C19+D19+E19+F19 | M19: =SUM(H19:L19) | N19: =G19+M19
A20: Производственные расходы | G20: =B20+C20+D20+E20+F20 | H20: 100000 | I20: 100000 | J20: 100000 | K20: 100000 | L20: 100000 | M20: =SUM(H20:L20) | N20: =G20+M20
A21: Инвентарь | G21: =B21+C21+D21+E21+F21 | M21: =SUM(H21:L21) | N21: =G21+M21
A22: Униформа | G22: =B22+C22+D22+E22+F22 | M22: =SUM(H22:L22) | N22: =G22+M22
A23: Упаковка | G23: =B23+C23+D23+E23+F23 | M23: =SUM(H23:L23) | N23: =G23+M23
A24: Хоз.товары | G24: =B24+C24+D24+E24+F24 | M24: =SUM(H24:L24) | N24: =G24+M24
A25: Погашение кредита и %% | B25: 1749942 | E25: 4013564 | G25: =B25+C25+D25+E25+F25 | M25: =SUM(H25:L25) | N25: =G25+M25
A26: Расходы по реализации Разные(Логистика) | D26: 1500000 | F26: 2000000 | G26: =B26+C26+D26+E26+F26 | M26: =SUM(H26:L26) | N26: =G26+M26
A27: Ремонт помещений | B27: 500000 | C27: 500000 | D27: 500000 | E27: 500000 | G27: =B27+C27+D27+E27+F27 | M27: =SUM(H27:L27) | N27: =G27+M27
A28: Ремонт оборудования | B28: 1000000 | C28: 500000 | D28: 500000 | E28: 1000000 | G28: =B28+C28+D28+E28+F28 | M28: =SUM(H28:L28) | N28: =G28+M28
A29: Приобретение основных средств | G29: =B29+C29+D29+E29+F29 | M29: =SUM(H29:L29) | N29: =G29+M29
A30: Сырье Платежи поставщикам Стас | G30: =B30+C30+D30+E30+F30 | H30: 2 000 000 | I30: 2 000 000 | J30: 2 000 000 | K30: 2 000 000 | L30: 2 000 000 | M30: =SUM(H30:L30) | N30: =G30+M30
A31: Электроэнергия и комун расходы | E31: 9000000 | G31: =B31+C31+D31+E31+F31 | M31: =SUM(H31:L31) | N31: =G31+M31
A32: ИТОГО | B32: =SUM(B4:B31) | C32: =SUM(C4:C31) | D32: =SUM(D4:D31) | E32: =SUM(E4:E31) | F32: =SUM(F4:F31) | G32: =B32+C32+D32+E32+F32 | H32: =SUM(H4:H31) | I32: =SUM(I4:I31) | J32: =SUM(J4:J31) | K32: =SUM(K4:K31) | L32: =SUM(L4:L31) | M32: =SUM(M4:M31) | N32: =G32+M32

Sheet ДДС МЕСЯЦ МАЙ
K1: 46143 | M1: 46146 | O1: 46147 | Q1: 46148 | S1: 46149 | U1: 46150 | W1: 46153 | Y1: 46154 | AA1: 46155 | AC1: 46156 | AE1: 46157 | AG1: 46160 | AI1: 46161 | AK1: 46162 | AM1: 46163 | AO1: 46164 | AQ1: 46167 | AS1: 46168 | AU1: 46169 | AW1: 46170 | AY1: 46171
K2: пятница | M2: понедельник | O2: вторник | Q2: среда | S2: четверг | U2: пятница | W2: понедельник | Y2: вторник | AA2: среда | AC2: четверг | AE2: пятница | AG2: понедельник | AI2: вторник | AK2: среда | AM2: четверг | AO2: пятница | AQ2: понедельник | AS2: вторник | AU2: среда | AW2: четверг | AY2: пятница | BA2: прирост 18% к факту апреля
K3: 46143 | M3: 46146 | O3: 46147 | Q3: 46148 | S3: 46149 | U3: 46150 | W3: 46153 | Y3: 46154 | AA3: 46155 | AC3: 46156 | AE3: 46157 | AG3: 46160 | AI3: 46161 | AK3: 46162 | AM3: 46163 | AO3: 46164 | AQ3: 46167 | AS3: 46168 | AU3: 46169 | AW3: 46170 | AY3: 46171 | BA3: Итого план | BB3: Итого факт | BC3: Отклонение
C4: План | D4: Факт | E4: План | F4: Факт | G4: План | H4: Факт | I4: План | J4: Факт | K4: План | L4: Факт | M4: План | N4: Факт | O4: План | P4: Факт | Q4: План | R4: Факт | S4: План | T4: Факт | U4: План | V4: Факт | W4: План | X4: Факт | Y4: План | Z4: Факт | AA4: План | AB4: Факт | AC4: План | AD4: Факт | AE4: План | AF4: Факт | AG4: План | AH4: Факт | AI4: План | AJ4: Факт | AK4: План | AL4: Факт | AM4: План | AN4: Факт | AO4: План | AP4: Факт
A5: Остаток на начало по Банку | C5: 3140328 | D5: =C5 | E5: =C81 | F5: =D81 | G5: =E81 | H5: =3139916 | I5: =G81 | J5: =H81 | K5: 0 | L5: 0 | M5: =K81 | N5: =L81 | O5: =M81 | P5: =N81 | Q5: =O81 | R5: =P81 | S5: =Q81 | T5: =R81 | ... AZ5: =AX81 | BA5: =C5 | BB5: =BA5 | BC5: =BB5-BA5
A6: Остаток на начало по Кассе | C6: 917728 | D6: =C6 | E6: =C82 | F6: =D82 | G6: =E82 | H6: =F82+62744 | I6: =G82 | J6: =H82 | K6: 0 | L6: 0 | M6: =K82 | N6: =L82 | O6: =M82 | P6: =N82 | Q6: =O82 | R6: =P82 | S6: =Q82 | T6: =R82 | ... AZ6: =AX82 | BA6: =C6 | BB6: =BA6 | BC6: =BB6-BA6
A7: Прочие | B7: Приход | G7: 1000000 | M7: 1000000 | Q7: 1000000 | U7: 1000000 | W7: 1000000 | AA7: 1000000 | AE7: 1000000 | AG7: 1000000 | AK7: 1000000 | AO7: 1000000 | AQ7: 1000000 | AU7: 1000000 | AY7: 1000000 | BA7: =K7+M7+O7+Q7+S7+U7+W7+Y7+AA7+AC7+AE7+AG7+AI7+AK7+AM7+AO7+AQ7+AS7+AU7+AW7+AY7 | BB7: =L7+N7+P7+R7+T7+V7+X7+Z7+AB7+AD7+AF7+AH7+AJ7+AL7+AN7+AP7+AR7+AT7+AV7+AX7+AZ7 | BC7: =BA7-BB7
A8: Б1, Б2, Б5 | B8: Приход | K8: 1000000 | O8: 1000000 | Q8: 1000000 | S8: 1000000 | U8: 1000000 | Y8: 1000000 | AC8: 1000000 | AE8: 1000000 | AI8: 1000000 | AM8: 1000000 | AO8: 1000000 | AS8: 1000000 | AU8: 1000000 | AW8: 1000000 | BA8: =K8+M8+O8+Q8+S8+U8+W8+Y8+AA8+AC8+AE8+AG8+AI8+AK8+AM8+AO8+AQ8+AS8+AU8+AW8+AY8 | BB8: =L8+N8+P8+R8+T8+V8+X8+Z8+AB8+AD8+AF8+AH8+AJ8+AL8+AN8+AP8+AR8+AT8+AV8+AX8+AZ8 | BC8: =BA8-BB8
A9: Яндекс | B9: Приход | I9: 6000000 | O9: 6000000 | S9: 10000000 | Y9: 6000000 | AC9: 10000000 | AI9: 6000000 | AM9: 10000000 | AS9: 9000000 | AW9: 10000000 | BA9: =K9+M9+O9+Q9+S9+U9+W9+Y9+AA9+AC9+AE9+AG9+AI9+AK9+AM9+AO9+AQ9+AS9+AU9+AW9+AY9 | BB9: =L9+N9+P9+R9+T9+V9+X9+Z9+AB9+AD9+AF9+AH9+AJ9+AL9+AN9+AP9+AR9+AT9+AV9+AX9+AZ9 | BC9: =BA9-BB9
A10: Май Март | B10: Приход | G10: 1000000 | O10: 2000000 | S10: 2000000 | AC10: 2000000 | AM10: 2000000 | AS10: 2000000 | AW10: 2000000 | BA10: =K10+M10+O10+Q10+S10+U10+W10+Y10+AA10+AC10+AE10+AG10+AI10+AK10+AM10+AO10+AQ10+AS10+AU10+AW10+AY10 | BB10: =L10+N10+P10+R10+T10+V10+X10+Z10+AB10+AD10+AF10+AH10+AJ10+AL10+AN10+AP10+AR10+AT10+AV10+AX10+AZ10 | BC10: =BA10-BB10
A11: 7-Kaspi Банк | B11: Приход | G11: 1000000 | I11: 1500000 | K11: 1000000 | Q11: 1000000 | S11: 1000000 | U11: 1000000 | W11: 1000000 | Y11: 1000000 | AA11: 1000000 | AC11: 1000000 | AE11: 1000000 | AG11: 1000000 | AI11: 1000000 | AK11: 1000000 | AM11: 1000000 | AO11: 1000000 | AQ11: 1000000 | AU11: 1000000 | AY11: 1000000 | BA11: =K11+M11+O11+Q11+S11+U11+W11+Y11+AA11+AC11+AE11+AG11+AI11+AK11+AM11+AO11+AQ11+AS11+AU11+AW11+AY11 | BB11: =L11+N11+P11+R11+T11+V11+X11+Z11+AB11+AD11+AF11+AH11+AJ11+AL11+AN11+AP11+AR11+AT11+AV11+AX11+AZ11 | BC11: =BA11-BB11
A12: Crave | B12: Приход | M12: 3000000 | Q12: 3000000 | U12: 3000000 | W12: 3000000 | AA12: 3000000 | AE12: 3000000 | AG12: 3000000 | AK12: 3000000 | AO12: 3000000 | BA12: =K12+M12+O12+Q12+S12+U12+W12+Y12+AA12+AC12+AE12+AG12+AI12+AK12+AM12+AO12+AQ12+AS12+AU12+AW12+AY12 | BB12: =L12+N12+P12+R12+T12+V12+X12+Z12+AB12+AD12+AF12+AH12+AJ12+AL12+AN12+AP12+AR12+AT12+AV12+AX12+AZ12 | BC12: =BA12-BB12
A13: 99-RP АЗС | B13: Приход | I13: 5000000 | S13: 8000000 | AC13: 6000000 | AM13: 6000000 | AW13: 6000000 | BA13: =K13+M13+O13+Q13+S13+U13+W13+Y13+AA13+AC13+AE13+AG13+AI13+AK13+AM13+AO13+AQ13+AS13+AU13+AW13+AY13 | BB13: =L13+N13+P13+R13+T13+V13+X13+Z13+AB13+AD13+AF13+AH13+AJ13+AL13+AN13+AP13+AR13+AT13+AV13+AX13+AZ13 | BC13: =BA13-BB13
A14: 96- DSF покупатель | B14: Приход | G14: 5000000 | K14: 1000000 | M14: 4000000 | O14: 4000000 | AE14: 2000000 | AM14: 2000000 | AU14: 1000000 | BA14: =K14+M14+O14+Q14+S14+U14+W14+Y14+AA14+AC14+AE14+AG14+AI14+AK14+AM14+AO14+AQ14+AS14+AU14+AW14+AY14 | BB14: =L14+N14+P14+R14+T14+V14+X14+Z14+AB14+AD14+AF14+AH14+AJ14+AL14+AN14+AP14+AR14+AT14+AV14+AX14+AZ14 | BC14: =BA14-BB14
A15: 85-ДФЗ дистрибьютер ФЗ | B15: Приход | G15: 2000000 | I15: 2200000 | K15: 2000000 | M15: 11900000 | O15: 4000000 | Q15: 10000000 | S15: 4000000 | U15: 2000000 | W15: 2000000 | Y15: 2000000 | AA15: 10000000 | AC15: 4000000 | AE15: 2000000 | AG15: 4000000 | AI15: 1000000 | AK15: 10000000 | AM15: 4000000 | AO15: 2000000 | AQ15: 2000000 | AS15: 5000000 | AU15: 10000000 | AW15: 4000000 | AY15: 4000000 | BA15: =K15+M15+O15+Q15+S15+U15+W15+Y15+AA15+AC15+AE15+AG15+AI15+AK15+AM15+AO15+AQ15+AS15+AU15+AW15+AY15 | BB15: =L15+N15+P15+R15+T15+V15+X15+Z15+AB15+AD15+AF15+AH15+AJ15+AL15+AN15+AP15+AR15+AT15+AV15+AX15+AZ15 | BC15: =BA15-BB15
A16: 110 АЗС №67 "Sinooil" | B16: Приход | U16: 1000000 | Y16: 1500000 | AG16: 1000000 | AU16: 2000000 | BA16: =K16+M16+O16+Q16+S16+U16+W16+Y16+AA16+AC16+AE16+AG16+AI16+AK16+AM16+AO16+AQ16+AS16+AU16+AW16+AY16 | BB16: =L16+N16+P16+R16+T16+V16+X16+Z16+AB16+AD16+AF16+AH16+AJ16+AL16+AN16+AP16+AR16+AT16+AV16+AX16+AZ16 | BC16: =BA16-BB16
A17: 100 ТУАР (шинлайн) | B17: Приход | G17: 150000 | BA17: =K17+M17+O17+Q17+S17+U17+W17+Y17+AA17+AC17+AE17+AG17+AI17+AK17+AM17+AO17+AQ17+AS17+AU17+AW17+AY17 | BB17: =L17+N17+P17+R17+T17+V17+X17+Z17+AB17+AD17+AF17+AH17+AJ17+AL17+AN17+AP17+AR17+AT17+AV17+AX17+AZ17 | BC17: =BA17-BB17
A18: Даркстор Чоко | B18: Приход | O18: 600000 | W18: 500000 | AA18: 500000 | AM18: 650000 | AQ18: 150000 | AU18: 150000 | BA18: =K18+M18+O18+Q18+S18+U18+W18+Y18+AA18+AC18+AE18+AG18+AI18+AK18+AM18+AO18+AQ18+AS18+AU18+AW18+AY18 | BB18: =L18+N18+P18+R18+T18+V18+X18+Z18+AB18+AD18+AF18+AH18+AJ18+AL18+AN18+AP18+AR18+AT18+AV18+AX18+AZ18 | BC18: =BA18-BB18
A19: Глово, Вольт | B19: Приход | M19: 100000 | Q19: 200000 | S19: 200000 | U19: 100000 | Y19: 100000 | AE19: 100000 | AG19: 100000 | AI19: 100000 | AK19: 100000 | AM19: 100000 | AO19: 100000 | AQ19: 200000 | AS19: 100000 | AU19: 200000 | AW19: 200000 | AY19: 200000 | BA19: =K19+M19+O19+Q19+S19+U19+W19+Y19+AA19+AC19+AE19+AG19+AI19+AK19+AM19+AO19+AQ19+AS19+AU19+AW19+AY19 | BB19: =L19+N19+P19+R19+T19+V19+X19+Z19+AB19+AD19+AF19+AH19+AJ19+AL19+AN19+AP19+AR19+AT19+AV19+AX19+AZ19 | BC19: =BA19-BB19
A20: Торты | B20: Приход | S20: 500000 | AM20: 300000 | AW20: 300000 | BA20: =K20+M20+O20+Q20+S20+U20+W20+Y20+AA20+AC20+AE20+AG20+AI20+AK20+AM20+AO20+AQ20+AS20+AU20+AW20+AY20 | BB20: =L20+N20+P20+R20+T20+V20+X20+Z20+AB20+AD20+AF20+AH20+AJ20+AL20+AN20+AP20+AR20+AT20+AV20+AX20+AZ20 | BC20: =BA20-BB20
A21: Итого по банку | B21: Приход | C21: 0 | D21: =SUM(D7:D20) | E21: =SUM(E7:E20) | F21: =SUM(F7:F20) | G21: =SUM(G7:G20) | H21: =SUM(H7:H20) | I21: =SUM(I7:I20) | J21: =SUM(J7:J20) | K21: =SUM(K7:K20) | ... AZ21: =SUM(AZ7:AZ20) | BA21: =K21+M21+O21+Q21+S21+U21+W21+Y21+AA21+AC21+AE21+AG21+AI21+AK21+AM21+AO21+AQ21+AS21+AU21+AW21+AY21 | BB21: =L21+N21+P21+R21+T21+V21+X21+Z21+AB21+AD21+AF21+AH21+AJ21+AL21+AN21+AP21+AR21+AT21+AV21+AX21+AZ21 | BC21: =BA21-BB21
A22: 97- Кейтеринг гость | B22: Приход | S22: 450000 | AC22: 250000 | AI22: 300000 | AS22: 500000 | BA22: =K22+M22+O22+Q22+S22+U22+W22+Y22+AA22+AC22+AE22+AG22+AI22+AK22+AM22+AO22+AQ22+AS22+AU22+AW22+AY22 | BB22: =L22+N22+P22+R22+T22+V22+X22+Z22+AB22+AD22+AF22+AH22+AJ22+AL22+AN22+AP22+AR22+AT22+AV22+AX22+AZ22 | BC22: =BA22-BB22
A23: Возврат с подотчета, Кредит | B23: Приход | H23: 40000 | BA23: =K23+M23+O23+Q23+S23+U23+W23+Y23+AA23+AC23+AE23+AG23+AI23+AK23+AM23+AO23+AQ23+AS23+AU23+AW23+AY23 | BB23: =L23+N23+P23+R23+T23+V23+X23+Z23+AB23+AD23+AF23+AH23+AJ23+AL23+AN23+AP23+AR23+AT23+AV23+AX23+AZ23 | BC23: =BA23-BB23
A24: Crave | B24: Приход | J24: 600000 | M24: 600000 | S24: 600000 | W24: 600000 | AC24: 600000 | AG24: 600000 | AM24: 600000 | AQ24: 600000 | AW24: 600000 | BA24: =K24+M24+O24+Q24+S24+U24+W24+Y24+AA24+AC24+AE24+AG24+AI24+AK24+AM24+AO24+AQ24+AS24+AU24+AW24+AY24 | BB24: =L24+N24+P24+R24+T24+V24+X24+Z24+AB24+AD24+AF24+AH24+AJ24+AL24+AN24+AP24+AR24+AT24+AV24+AX24+AZ24 | BC24: =BA24-BB24
A25: 7-Kaspi Банк (нал) | B25: Приход | S25: 1000000 | AC25: 1000000 | AM25: 1000000 | AW25: 1000000 | BA25: =K25+M25+O25+Q25+S25+U25+W25+Y25+AA25+AC25+AE25+AG25+AI25+AK25+AM25+AO25+AQ25+AS25+AU25+AW25+AY25 | BB25: =L25+N25+P25+R25+T25+V25+X25+Z25+AB25+AD25+AF25+AH25+AJ25+AL25+AN25+AP25+AR25+AT25+AV25+AX25+AZ25 | BC25: =BA25-BB25
A26: Частное лицо (Покупатель) | B26: Приход | S26: 200000 | AC26: 400000 | AM26: 200000 | AS26: 200000 | BA26: =K26+M26+O26+Q26+S26+U26+W26+Y26+AA26+AC26+AE26+AG26+AI26+AK26+AM26+AO26+AQ26+AS26+AU26+AW26+AY26 | BB26: =L26+N26+P26+R26+T26+V26+X26+Z26+AB26+AD26+AF26+AH26+AJ26+AL26+AN26+AP26+AR26+AT26+AV26+AX26+AZ26 | BC26: =BA26-BB26
A27: 98-FOOD vending : СКЛАД АППАРАТ №1 (ФЗ Ермагамбет) | B27: Приход | S27: 1500000 | AC27: 1500000 | AM27: 1500000 | AW27: 1500000 | BA27: =K27+M27+O27+Q27+S27+U27+W27+Y27+AA27+AC27+AE27+AG27+AI27+AK27+AM27+AO27+AQ27+AS27+AU27+AW27+AY27 | BB27: =L27+N27+P27+R27+T27+V27+X27+Z27+AB27+AD27+AF27+AH27+AJ27+AL27+AN27+AP27+AR27+AT27+AV27+AX27+AZ27 | BC27: =BA27-BB27
A28: Итого по кассе | B28: Приход | C28: 0 | D28: =SUM(D22:D27) | E28: =SUM(E22:E27) | F28: =SUM(F22:F27) | G28: =SUM(G22:G27) | H28: =SUM(H22:H27) | I28: =SUM(I22:I27) | J28: =SUM(J22:J27) | K28: =SUM(K22:K27) | ... AZ28: =SUM(AZ22:AZ27) | BA28: =K28+M28+O28+Q28+S28+U28+W28+Y28+AA28+AC28+AE28+AG28+AI28+AK28+AM28+AO28+AQ28+AS28+AU28+AW28+AY28 | BB28: =L28+N28+P28+R28+T28+V28+X28+Z28+AB28+AD28+AF28+AH28+AJ28+AL28+AN28+AP28+AR28+AT28+AV28+AX28+AZ28 | BC28: =BA28-BB28
A29: 1.Выручка | B29: Приход | C29: 0 | D29: =D21+D28 | E29: =E21+E28 | F29: =F21+F28 | G29: =G21+G28 | H29: =H21+H28 | I29: =I21+I28 | J29: =J21+J28 | K29: =K21+K28 | ... AZ29: =AZ21+AZ28 | BA29: =K29+M29+O29+Q29+S29+U29+W29+Y29+AA29+AC29+AE29+AG29+AI29+AK29+AM29+AO29+AQ29+AS29+AU29+AW29+AY29 | BB29: =L29+N29+P29+R29+T29+V29+X29+Z29+AB29+AD29+AF29+AH29+AJ29+AL29+AN29+AP29+AR29+AT29+AV29+AX29+AZ29 | BC29: =BA29-BB29
A30: IT-обслуживание,телефония,интернет | B30: Расход | G30: -82240 | H30: =-85400-85177 | I30: -220400 | K30: -80000 | O30: -90000 | S30: -220400 | AQ30: -90000 | AS30: -90000 | BA30: =K30+M30+O30+Q30+S30+U30+W30+Y30+AA30+AC30+AE30+AG30+AI30+AK30+AM30+AO30+AQ30+AS30+AU30+AW30+AY30 | BB30: =L30+N30+P30+R30+T30+V30+X30+Z30+AB30+AD30+AF30+AH30+AJ30+AL30+AN30+AP30+AR30+AT30+AV30+AX30+AZ30 | BC30: =BA30-BB30
A31: Авансы поставщикам | B31: Расход | BA31: =K31+M31+O31+Q31+S31+U31+W31+Y31+AA31+AC31+AE31+AG31+AI31+AK31+AM31+AO31+AQ31+AS31+AU31+AW31+AY31 | BB31: =L31+N31+P31+R31+T31+V31+X31+Z31+AB31+AD31+AF31+AH31+AJ31+AL31+AN31+AP31+AR31+AT31+AV31+AX31+AZ31 | BC31: =BA31-BB31
A32: Административные расходы | B32: Расход | H32: =-4000-1950 | I32: -3000 | J32: -6050 | M32: -55000 | O32: =-400000 | Q32: -55000 | S32: -55000 | U32: -55000 | W32: -55000 | Y32: -30000 | AA32: -55000 | AC32: -55000 | AE32: -55000 | AG32: -55000 | AI32: -55000 | AK32: -55000 | AM32: -55000 | AO32: -55000 | AQ32: -55000 | AS32: -55000 | AU32: -55000 | AW32: -55000 | AY32: -55000 | BA32: =K32+M32+O32+Q32+S32+U32+W32+Y32+AA32+AC32+AE32+AG32+AI32+AK32+AM32+AO32+AQ32+AS32+AU32+AW32+AY32 | BB32: =L32+N32+P32+R32+T32+V32+X32+Z32+AB32+AD32+AF32+AH32+AJ32+AL32+AN32+AP32+AR32+AT32+AV32+AX32+AZ32 | BC32: =BA32-BB32
A33: Возврат ВФП | B33: Расход | BA33: =K33+M33+O33+Q33+S33+U33+W33+Y33+AA33+AC33+AE33+AG33+AI33+AK33+AM33+AO33+AQ33+AS33+AU33+AW33+AY33 | BB33: =L33+N33+P33+R33+T33+V33+X33+Z33+AB33+AD33+AF33+AH33+AJ33+AL33+AN33+AP33+AR33+AT33+AV33+AX33+AZ33 | BC33: =BA33-BB33
A34: Представительские расходы | B34: Расход | BA34: =K34+M34+O34+Q34+S34+U34+W34+Y34+AA34+AC34+AE34+AG34+AI34+AK34+AM34+AO34+AQ34+AS34+AU34+AW34+AY34 | BB34: =L34+N34+P34+R34+T34+V34+X34+Z34+AB34+AD34+AF34+AH34+AJ34+AL34+AN34+AP34+AR34+AT34+AV34+AX34+AZ34 | BC34: =BA34-BB34
A35: Аренда помещений | B35: Расход | Y35: -6655000 | BA35: =K35+M35+O35+Q35+S35+U35+W35+Y35+AA35+AC35+AE35+AG35+AI35+AK35+AM35+AO35+AQ35+AS35+AU35+AW35+AY35 | BB35: =L35+N35+P35+R35+T35+V35+X35+Z35+AB35+AD35+AF35+AH35+AJ35+AL35+AN35+AP35+AR35+AT35+AV35+AX35+AZ35 | BC35: =BA35-BB35
A36: Газ | B36: Расход | AQ36: -630000 | BA36: =K36+M36+O36+Q36+S36+U36+W36+Y36+AA36+AC36+AE36+AG36+AI36+AK36+AM36+AO36+AQ36+AS36+AU36+AW36+AY36 | BB36: =L36+N36+P36+R36+T36+V36+X36+Z36+AB36+AD36+AF36+AH36+AJ36+AL36+AN36+AP36+AR36+AT36+AV36+AX36+AZ36 | BC36: =BA36-BB36
A37: Маркетинг | B37: Расход | BA37: =K37+M37+O37+Q37+S37+U37+W37+Y37+AA37+AC37+AE37+AG37+AI37+AK37+AM37+AO37+AQ37+AS37+AU37+AW37+AY37 | BB37: =L37+N37+P37+R37+T37+V37+X37+Z37+AB37+AD37+AF37+AH37+AJ37+AL37+AN37+AP37+AR37+AT37+AV37+AX37+AZ37 | BC37: =BA37-BB37
A38: Мусор | B38: Расход | AE38: -100000 | AM38: -642920 | BA38: =K38+M38+O38+Q38+S38+U38+W38+Y38+AA38+AC38+AE38+AG38+AI38+AK38+AM38+AO38+AQ38+AS38+AU38+AW38+AY38 | BB38: =L38+N38+P38+R38+T38+V38+X38+Z38+AB38+AD38+AF38+AH38+AJ38+AL38+AN38+AP38+AR38+AT38+AV38+AX38+AZ38 | BC38: =BA38-BB38
A39: Налоги и другие платежи в бюджет | B39: Расход | AE39: -8000000 | AG39: -6000000 | AS39: -12000000 | BA39: =K39+M39+O39+Q39+S39+U39+W39+Y39+AA39+AC39+AE39+AG39+AI39+AK39+AM39+AO39+AQ39+AS39+AU39+AW39+AY39 | BB39: =L39+N39+P39+R39+T39+V39+X39+Z39+AB39+AD39+AF39+AH39+AJ39+AL39+AN39+AP39+AR39+AT39+AV39+AX39+AZ39 | BC39: =BA39-BB39
A40: Оплата труда | B40: Расход | S40: -18500000 | AM40: -2030000 | BA40: =K40+M40+O40+Q40+S40+U40+W40+Y40+AA40+AC40+AE40+AG40+AI40+AK40+AM40+AO40+AQ40+AS40+AU40+AW40+AY40 | BB40: =L40+N40+P40+R40+T40+V40+X40+Z40+AB40+AD40+AF40+AH40+AJ40+AL40+AN40+AP40+AR40+AT40+AV40+AX40+AZ40 | BC40: =BA40-BB40
A41: Охрана | B41: Расход | Y41: -1000000 | BA41: =K41+M41+O41+Q41+S41+U41+W41+Y41+AA41+AC41+AE41+AG41+AI41+AK41+AM41+AO41+AQ41+AS41+AU41+AW41+AY41 | BB41: =L41+N41+P41+R41+T41+V41+X41+Z41+AB41+AD41+AF41+AH41+AJ41+AL41+AN41+AP41+AR41+AT41+AV41+AX41+AZ41 | BC41: =BA41-BB41
A42: Платежи поставщикам Прочее | B42: Расход | G42: -180000 | BA42: =K42+M42+O42+Q42+S42+U42+W42+Y42+AA42+AC42+AE42+AG42+AI42+AK42+AM42+AO42+AQ42+AS42+AU42+AW42+AY42 | BB42: =L42+N42+P42+R42+T42+V42+X42+Z42+AB42+AD42+AF42+AH42+AJ42+AL42+AN42+AP42+AR42+AT42+AV42+AX42+AZ42 | BC42: =BA42-BB42
A43: Производственные расходы | B43: Расход | K43: -2000000 | O43: -3000000 | S43: -3000000 | Y43: -3000000 | AA43: -3000000 | AC43: -3000000 | AM43: -3000000 | AQ43: -3000000 | AW43: -3000000 | BA43: =K43+M43+O43+Q43+S43+U43+W43+Y43+AA43+AC43+AE43+AG43+AI43+AK43+AM43+AO43+AQ43+AS43+AU43+AW43+AY43 | BB43: =L43+N43+P43+R43+T43+V43+X43+Z43+AB43+AD43+AF43+AH43+AJ43+AL43+AN43+AP43+AR43+AT43+AV43+AX43+AZ43 | BC43: =BA43-BB43
A44: Инвентарь | B44: Расход | BA44: =K44+M44+O44+Q44+S44+U44+W44+Y44+AA44+AC44+AE44+AG44+AI44+AK44+AM44+AO44+AQ44+AS44+AU44+AW44+AY44 | BB44: =L44+N44+P44+R44+T44+V44+X44+Z44+AB44+AD44+AF44+AH44+AJ44+AL44+AN44+AP44+AR44+AT44+AV44+AX44+AZ44 | BC44: =BA44-BB44
A45: Униформа | B45: Расход | K45: -150000 | BA45: =K45+M45+O45+Q45+S45+U45+W45+Y45+AA45+AC45+AE45+AG45+AI45+AK45+AM45+AO45+AQ45+AS45+AU45+AW45+AY45 | BB45: =L45+N45+P45+R45+T45+V45+X45+Z45+AB45+AD45+AF45+AH45+AJ45+AL45+AN45+AP45+AR45+AT45+AV45+AX45+AZ45 | BC45: =BA45-BB45
A46: Упаковка | B46: Расход | J46: =-510400 | K46: -2000000 | O46: -2500000 | U46: -2000000 | AA46: -1500000 | AC46: -900000 | AE46: -600000 | AI46: -1000000 | AM46: -1000000 | AO46: -2000000 | BA46: =K46+M46+O46+Q46+S46+U46+W46+Y46+AA46+AC46+AE46+AG46+AI46+AK46+AM46+AO46+AQ46+AS46+AU46+AW46+AY46 | BB46: =L46+N46+P46+R46+T46+V46+X46+Z46+AB46+AD46+AF46+AH46+AJ46+AL46+AN46+AP46+AR46+AT46+AV46+AX46+AZ46 | BC46: =BA46-BB46
A47: Хоз.товара | B47: Расход | AE47: -300000 | BA47: =K47+M47+O47+Q47+S47+U47+W47+Y47+AA47+AC47+AE47+AG47+AI47+AK47+AM47+AO47+AQ47+AS47+AU47+AW47+AY47 | BB47: =L47+N47+P47+R47+T47+V47+X47+Z47+AB47+AD47+AF47+AH47+AJ47+AL47+AN47+AP47+AR47+AT47+AV47+AX47+AZ47 | BC47: =BA47-BB47
A48: Погашение кредита и %% | B48: Расход | AQ48: -1198352 | AW48: =-915358-1770150 | AY48: =-915358-1770150 | BA48: =K48+M48+O48+Q48+S48+U48+W48+Y48+AA48+AC48+AE48+AG48+AI48+AK48+AM48+AO48+AQ48+AS48+AU48+AW48+AY48 | BB48: =L48+N48+P48+R48+T48+V48+X48+Z48+AB48+AD48+AF48+AH48+AJ48+AL48+AN48+AP48+AR48+AT48+AV48+AX48+AZ48 | BC48: =BA48-BB48
A49: Расходы по реализации Разные(Логистика) | B49: Расход | I49: -2000000 | O49: -800000 | U49: -2725000 | Y49: -800000 | AE49: -2725000 | AI49: -800000 | AO49: -2725000 | AS49: -800000 | AY49: -2725000 | BA49: =K49+M49+O49+Q49+S49+U49+W49+Y49+AA49+AC49+AE49+AG49+AI49+AK49+AM49+AO49+AQ49+AS49+AU49+AW49+AY49 | BB49: =L49+N49+P49+R49+T49+V49+X49+Z49+AB49+AD49+AF49+AH49+AJ49+AL49+AN49+AP49+AR49+AT49+AV49+AX49+AZ49 | BC49: =BA49-BB49
A50: Ремонт помещений | B50: Расход | BA50: =K50+M50+O50+Q50+S50+U50+W50+Y50+AA50+AC50+AE50+AG50+AI50+AK50+AM50+AO50+AQ50+AS50+AU50+AW50+AY50 | BB50: =L50+N50+P50+R50+T50+V50+X50+Z50+AB50+AD50+AF50+AH50+AJ50+AL50+AN50+AP50+AR50+AT50+AV50+AX50+AZ50 | BC50: =BA50-BB50
A51: Ремонт оборудования | B51: Расход | BA51: =K51+M51+O51+Q51+S51+U51+W51+Y51+AA51+AC51+AE51+AG51+AI51+AK51+AM51+AO51+AQ51+AS51+AU51+AW51+AY51 | BB51: =L51+N51+P51+R51+T51+V51+X51+Z51+AB51+AD51+AF51+AH51+AJ51+AL51+AN51+AP51+AR51+AT51+AV51+AX51+AZ51 | BC51: =BA51-BB51
A52: Приобретение основных средств | B52: Расход | BA52: =K52+M52+O52+Q52+S52+U52+W52+Y52+AA52+AC52+AE52+AG52+AI52+AK52+AM52+AO52+AQ52+AS52+AU52+AW52+AY52 | BB52: =L52+N52+P52+R52+T52+V52+X52+Z52+AB52+AD52+AF52+AH52+AJ52+AL52+AN52+AP52+AR52+AT52+AV52+AX52+AZ52 | BC52: =BA52-BB52
A53: Сырье Платежи поставщикам | B53: Расход | H53: =-7743006 | J53: =-7167264 | K53: -5000000 | M53: -5000000 | O53: -5000000 | Q53: -5000000 | S53: -5000000 | U53: -5000000 | W53: -5000000 | Y53: -8000000 | AA53: -5000000 | AC53: -6000000 | AE53: -5000000 | AG53: -5000000 | AI53: -5000000 | AK53: -5000000 | AM53: -5000000 | AO53: -5000000 | AQ53: -5000000 | AS53: -5000000 | AU53: -5000000 | AW53: -5000000 | AY53: -5000000 | BA53: =K53+M53+O53+Q53+S53+U53+W53+Y53+AA53+AC53+AE53+AG53+AI53+AK53+AM53+AO53+AQ53+AS53+AU53+AW53+AY53 | BB53: =L53+N53+P53+R53+T53+V53+X53+Z53+AB53+AD53+AF53+AH53+AJ53+AL53+AN53+AP53+AR53+AT53+AV53+AX53+AZ53 | BC53: =BA53-BB53
A54: Электроэнергия | B54: Расход | AQ54: -6900000 | BA54: =K54+M54+O54+Q54+S54+U54+W54+Y54+AA54+AC54+AE54+AG54+AI54+AK54+AM54+AO54+AQ54+AS54+AU54+AW54+AY54 | BB54: =L54+N54+P54+R54+T54+V54+X54+Z54+AB54+AD54+AF54+AH54+AJ54+AL54+AN54+AP54+AR54+AT54+AV54+AX54+AZ54 | BC54: =BA54-BB54
A55: Итого по банку | B55: Расход | C55: 0 | D55: =SUM(D30:D54) | E55: =SUM(E30:E54) | F55: =SUM(F30:F54) | G55: =SUM(G30:G54) | H55: =SUM(H30:H54) | I55: =SUM(I30:I54) | J55: =SUM(J30:J54) | K55: =SUM(K30:K54) | ... AZ55: =SUM(AZ30:AZ54) | BA55: =K55+M55+O55+Q55+S55+U55+W55+Y55+AA55+AC55+AE55+AG55+AI55+AK55+AM55+AO55+AQ55+AS55+AU55+AW55+AY55 | BB55: =L55+N55+P55+R55+T55+V55+X55+Z55+AB55+AD55+AF55+AH55+AJ55+AL55+AN55+AP55+AR55+AT55+AV55+AX55+AZ55 | BC55: =BA55-BB55
A56: Подотчет (Рынок сырье, Рынок ТМЦ) | B56: Расход | H56: =-500000 | I56: -500000 | K56: -500000 | M56: -300000 | S56: -500000 | U56: -500000 | W56: -500000 | AC56: -500000 | AE56: -500000 | AM56: -800000 | AW56: -500000 | AY56: -500000 | BA56: =K56+M56+O56+Q56+S56+U56+W56+Y56+AA56+AC56+AE56+AG56+AI56+AK56+AM56+AO56+AQ56+AS56+AU56+AW56+AY56 | BB56: =L56+N56+P56+R56+T56+V56+X56+Z56+AB56+AD56+AF56+AH56+AJ56+AL56+AN56+AP56+AR56+AT56+AV56+AX56+AZ56 | BC56: =BA56-BB56
A57: Административные расходы | B57: Расход | H57: =-2580 | I57: -109000 | O57: -55000 | Q57: -55000 | S57: -55000 | U57: -55000 | W57: -30000 | Y57: -55000 | AA57: -55000 | AC57: -55000 | AE57: -55000 | AG57: -55000 | AI57: -55000 | AK57: -55000 | AM57: -55000 | AO57: -55000 | AQ57: -55000 | AS57: -55000 | AU57: -55000 | AW57: -55000 | BA57: =K57+M57+O57+Q57+S57+U57+W57+Y57+AA57+AC57+AE57+AG57+AI57+AK57+AM57+AO57+AQ57+AS57+AU57+AW57+AY57 | BB57: =L57+N57+P57+R57+T57+V57+X57+Z57+AB57+AD57+AF57+AH57+AJ57+AL57+AN57+AP57+AR57+AT57+AV57+AX57+AZ57 | BC57: =BA57-BB57
A58: Представительские расходы | B58: Расход | K58: -60329 | BA58: =K58+M58+O58+Q58+S58+U58+W58+Y58+AA58+AC58+AE58+AG58+AI58+AK58+AM58+AO58+AQ58+AS58+AU58+AW58+AY58 | BB58: =L58+N58+P58+R58+T58+V58+X58+Z58+AB58+AD58+AF58+AH58+AJ58+AL58+AN58+AP58+AR58+AT58+AV58+AX58+AZ58 | BC58: =BA58-BB58
A59: Аренда квартир | B59: Расход | W59: =-175000-300000 | Y59: -500000 | AE59: -500000 | AM59: -350149 | BA59: =K59+M59+O59+Q59+S59+U59+W59+Y59+AA59+AC59+AE59+AG59+AI59+AK59+AM59+AO59+AQ59+AS59+AU59+AW59+AY59 | BB59: =L59+N59+P59+R59+T59+V59+X59+Z59+AB59+AD59+AF59+AH59+AJ59+AL59+AN59+AP59+AR59+AT59+AV59+AX59+AZ59 | BC59: =BA59-BB59
A60: Налоги и другие платежи в бюджет | B60: Расход | F60: -746 | BA60: =K60+M60+O60+Q60+S60+U60+W60+Y60+AA60+AC60+AE60+AG60+AI60+AK60+AM60+AO60+AQ60+AS60+AU60+AW60+AY60 | BB60: =L60+N60+P60+R60+T60+V60+X60+Z60+AB60+AD60+AF60+AH60+AJ60+AL60+AN60+AP60+AR60+AT60+AV60+AX60+AZ60 | BC60: =BA60-BB60
A61: Маркетинг | B61: Расход | S61: -450000 | BA61: =K61+M61+O61+Q61+S61+U61+W61+Y61+AA61+AC61+AE61+AG61+AI61+AK61+AM61+AO61+AQ61+AS61+AU61+AW61+AY61 | BB61: =L61+N61+P61+R61+T61+V61+X61+Z61+AB61+AD61+AF61+AH61+AJ61+AL61+AN61+AP61+AR61+AT61+AV61+AX61+AZ61 | BC61: =BA61-BB61
A62: Оплата труда | B62: Расход | H62: =-100000-40000 | J62: -1261000 | K62: -3000000 | M62: -3000000 | O62: -3000000 | S62: -10000000 | AA62: -2500000 | AC62: -8000000 | AE62: -7000000 | AM62: -800000 | AO62: -7000000 | AQ62: -5000000 | AS62: -2000000 | AU62: -2000000 | AW62: -3000000 | AY62: -2000000 | BA62: =K62+M62+O62+Q62+S62+U62+W62+Y62+AA62+AC62+AE62+AG62+AI62+AK62+AM62+AO62+AQ62+AS62+AU62+AW62+AY62 | BB62: =L62+N62+P62+R62+T62+V62+X62+Z62+AB62+AD62+AF62+AH62+AJ62+AL62+AN62+AP62+AR62+AT62+AV62+AX62+AZ62 | BC62: =BA62-BB62
A63: Платежи поставщикам Прочее | B63: Расход | BA63: =K63+M63+O63+Q63+S63+U63+W63+Y63+AA63+AC63+AE63+AG63+AI63+AK63+AM63+AO63+AQ63+AS63+AU63+AW63+AY63 | BB63: =L63+N63+P63+R63+T63+V63+X63+Z63+AB63+AD63+AF63+AH63+AJ63+AL63+AN63+AP63+AR63+AT63+AV63+AX63+AZ63 | BC63: =BA63-BB63
A64: Производственные расходы | B64: Расход | I64: -48000 | J64: =-48000 | M64: -48000 | S64: -48000 | W64: -42000 | Y64: -42000 | AI64: -48000 | AM64: -48000 | AS64: -48000 | BA64: =K64+M64+O64+Q64+S64+U64+W64+Y64+AA64+AC64+AE64+AG64+AI64+AK64+AM64+AO64+AQ64+AS64+AU64+AW64+AY64 | BB64: =L64+N64+P64+R64+T64+V64+X64+Z64+AB64+AD64+AF64+AH64+AJ64+AL64+AN64+AP64+AR64+AT64+AV64+AX64+AZ64 | BC64: =BA64-BB64
A65: Инвентарь | B65: Расход | I65: =-15000-69000 | K65: -144600 | M65: =-15000-27000 | O65: -40000 | Y65: =-116000-19100 | AI65: -32000 | AK65: -35000 | BA65: =K65+M65+O65+Q65+S65+U65+W65+Y65+AA65+AC65+AE65+AG65+AI65+AK65+AM65+AO65+AQ65+AS65+AU65+AW65+AY65 | BB65: =L65+N65+P65+R65+T65+V65+X65+Z65+AB65+AD65+AF65+AH65+AJ65+AL65+AN65+AP65+AR65+AT65+AV65+AX65+AZ65 | BC65: =BA65-BB65
A66: Погашение кредита и %% | B66: Расход | BA66: =K66+M66+O66+Q66+S66+U66+W66+Y66+AA66+AC66+AE66+AG66+AI66+AK66+AM66+AO66+AQ66+AS66+AU66+AW66+AY66 | BB66: =L66+N66+P66+R66+T66+V66+X66+Z66+AB66+AD66+AF66+AH66+AJ66+AL66+AN66+AP66+AR66+AT66+AV66+AX66+AZ66 | BC66: =BA66-BB66
A67: Хоз.товара | B67: Расход | BA67: =K67+M67+O67+Q67+S67+U67+W67+Y67+AA67+AC67+AE67+AG67+AI67+AK67+AM67+AO67+AQ67+AS67+AU67+AW67+AY67 | BB67: =L67+N67+P67+R67+T67+V67+X67+Z67+AB67+AD67+AF67+AH67+AJ67+AL67+AN67+AP67+AR67+AT67+AV67+AX67+AZ67 | BC67: =BA67-BB67
A68: Канц.товары | B68: Расход | BA68: =K68+M68+O68+Q68+S68+U68+W68+Y68+AA68+AC68+AE68+AG68+AI68+AK68+AM68+AO68+AQ68+AS68+AU68+AW68+AY68 | BB68: =L68+N68+P68+R68+T68+V68+X68+Z68+AB68+AD68+AF68+AH68+AJ68+AL68+AN68+AP68+AR68+AT68+AV68+AX68+AZ68 | BC68: =BA68-BB68
A69: Расходы по реализации Разные | B69: Расход | J69: -8000 | BA69: =K69+M69+O69+Q69+S69+U69+W69+Y69+AA69+AC69+AE69+AG69+AI69+AK69+AM69+AO69+AQ69+AS69+AU69+AW69+AY69 | BB69: =L69+N69+P69+R69+T69+V69+X69+Z69+AB69+AD69+AF69+AH69+AJ69+AL69+AN69+AP69+AR69+AT69+AV69+AX69+AZ69 | BC69: =BA69-BB69
A70: Ремонт помещений | B70: Расход | BA70: =K70+M70+O70+Q70+S70+U70+W70+Y70+AA70+AC70+AE70+AG70+AI70+AK70+AM70+AO70+AQ70+AS70+AU70+AW70+AY70 | BB70: =L70+N70+P70+R70+T70+V70+X70+Z70+AB70+AD70+AF70+AH70+AJ70+AL70+AN70+AP70+AR70+AT70+AV70+AX70+AZ70 | BC70: =BA70-BB70
A71: Ремонт оборудования | B71: Расход | I71: -171500 | J71: =-75000 | BA71: =K71+M71+O71+Q71+S71+U71+W71+Y71+AA71+AC71+AE71+AG71+AI71+AK71+AM71+AO71+AQ71+AS71+AU71+AW71+AY71 | BB71: =L71+N71+P71+R71+T71+V71+X71+Z71+AB71+AD71+AF71+AH71+AJ71+AL71+AN71+AP71+AR71+AT71+AV71+AX71+AZ71 | BC71: =BA71-BB71
A72: Приобретение основных средств | B72: Расход | BA72: =K72+M72+O72+Q72+S72+U72+W72+Y72+AA72+AC72+AE72+AG72+AI72+AK72+AM72+AO72+AQ72+AS72+AU72+AW72+AY72 | BB72: =L72+N72+P72+R72+T72+V72+X72+Z72+AB72+AD72+AF72+AH72+AJ72+AL72+AN72+AP72+AR72+AT72+AV72+AX72+AZ72 | BC72: =BA72-BB72
A73: Сырье Платежи поставщикам | B73: Расход | H73: =-248600 | O73: -500000 | Q73: -500000 | S73: -500000 | Y73: -500000 | AA73: -500000 | AC73: -500000 | AI73: -500000 | AK73: -500000 | AM73: -500000 | AS73: -500000 | AU73: -500000 | AW73: -500000 | BA73: =K73+M73+O73+Q73+S73+U73+W73+Y73+AA73+AC73+AE73+AG73+AI73+AK73+AM73+AO73+AQ73+AS73+AU73+AW73+AY73 | BB73: =L73+N73+P73+R73+T73+V73+X73+Z73+AB73+AD73+AF73+AH73+AJ73+AL73+AN73+AP73+AR73+AT73+AV73+AX73+AZ73 | BC73: =BA73-BB73
A74: Итого по кассе | B74: Расход | C74: 0 | D74: =SUM(D56:D73) | E74: =SUM(E56:E73) | F74: =SUM(F56:F73) | G74: =SUM(G56:G73) | H74: =SUM(H56:H73) | I74: =SUM(I56:I73) | J74: =SUM(J56:J73) | K74: =SUM(K56:K73) | ... BA74: =SUM(BA56:BA73) | BB74: =L74+N74+P74+R74+T74+V74+X74+Z74+AB74+AD74+AF74+AH74+AJ74+AL74+AN74+AP74+AR74+AT74+AV74+AX74+AZ74 | BC74: =BA74-BB74
A75: ИТОГО РАСХОДЫ | C75: 0 | D75: =D55+D74 | E75: =E55+E74 | F75: =F55+F74 | G75: =G55+G74 | H75: =H55+H74 | I75: =I55+I74 | J75: =J55+J74 | K75: =K55+K74 | ... BA75: =BA55+BA74 | BB75: =L75+N75+P75+R75+T75+V75+X75+Z75+AB75+AD75+AF75+AH75+AJ75+AL75+AN75+AP75+AR75+AT75+AV75+AX75+AZ75 | BC75: =BA75-BB75
A76: Операционная деятельность | C76: 0 | D76: =D29-(-D55-D74) | E76: =E29-(-E55-E74) | F76: =F29-(-F55-F74) | G76: =G29-(-G55-G74) | H76: =H29-(-H55-H74) | I76: =I29-(-I55-I74) | J76: =J29-(-J55-J74) | K76: =K29-(-K55-K74) | ... M76: =M29-(-M55-M74) | O76: =O29-(-O55-O74) | P76: =P29-(-P55-P74) | Q76: =Q29-(-Q55-Q74) | R76: =R29-(-R55-R74) | S76: =S29-(-S55-S74) | T76: =T29-(-T55-T74) | U76: =U29-(-U55-U74) | V76: =V29-(-V55-V74) | ... AD76: =AD29-(-AD55-AD74) | AG76: =AG29-(-AG55-AG74) | AH76: =AH29-(-AH55-AH74) | AI76: =AI29-(-AI55-AI74) | AJ76: =AJ29-(-AJ55-AJ74) | AK76: =AK29-(-AL56-AK74) | AL76: =AL29-(-AL55-AL74) | AM76: =AM29-(-AM74) | AN76: =AN29-(-AN55-AN74) | AO76: =AO29-(-AP56-AO74) | AP76: =AP29-(-AP55-AP74) | AQ76: =AQ29-(-AQ55-AQ74) | AR76: =AR29-(-AR55-AR74) | AS76: =AS29-(-AS55-AS74) | AT76: =AT29-(-AT55-AT74) | AU76: =AU29-(-AU55-AU74) | AV76: =AV29-(-AV55-AV74) | AW76: =AW29-(-AW55-AW74) | ... BA76: =BA29-(-BA55-BA74) | BB76: =L76+N76+P76+R76+T76+V76+X76+Z76+AB76+AD76+AF76+AH76+AJ76+AL76+AN76+AP76+AR76+AT76+AV76+AX76+AZ76
A77: ВФП Учредители поступление (НАЛ) | B77: Приход | BA77: =BA30-(-BA56-BA75) | BB77: =L77+N77+P77+R77+T77+V77+X77+Z77+AB77+AD77+AF77+AH77+AJ77+AL77+AN77+AP77+AR77+AT77+AV77+AX77+AZ77
B78: Расход | BA78: =BA31-(-BA57-BA76) | BB78: =L78+N78+P78+R78+T78+V78+X78+Z78+AB78+AD78+AF78+AH78+AJ78+AL78+AN78+AP78+AR78+AT78+AV78+AX78+AZ78
A79: Касса взаиморасчета банк | B79: Расход | C79: 4000000 | E79: 500000 | G79: 2000000 | J79: 1575000 | BA79: =BA32-(-BA58-BA77) | BB79: =L79+N79+P79+R79+T79+V79+X79+Z79+AB79+AD79+AF79+AH79+AJ79+AL79+AN79+AP79+AR79+AT79+AV79+AX79+AZ79
A80: Касса взаиморасчета касса | B80: Приход | C80: 4000000 | E80: 500000 | G80: 2000000 | J80: 1575000 | T80: 14990 | BA80: =BA33-(-BA59-BA78) | BB80: =L80+N80+P80+R80+T80+V80+X80+Z80+AB80+AD80+AF80+AH80+AJ80+AL80+AN80+AP80+AR80+AT80+AV80+AX80+AZ80
A81: Остаток на конец ПО БАНКУ | C81: -859672 | D81: =D5+D21-(-D55)-D79 | E81: =E5+E21-(-E55)-E79 | F81: =F5+F21-(-F55)-F79 | G81: =G5+G21-(-G55)-G79 | H81: =H5+H21-(-H55)-H79 | I81: =I5+I21-(-I55)-I79 | J81: =J5+J21-(-J55)-J79 | K81: =K5+K21-(-K55)-K79 | ... U81: =U5+U21-(-U55)-U79 | V81: =V5+V21-(-V55)-V79+V77 | W81: =W5+W21-(-W55)-W79 | X81: =X5+X21+X55-X79+X77 | Y81: =Y5+Y21-(-Y55)-Y79 | Z81: =Z5+Z21+Z55-Z79 | AA81: =AA5+AA21-(-AA55)-AA79 | AB81: =AB5+AB21-(-AB55)+AB77-AB79 | AC81: =AC5+AC21-(-AC55)-AC79 | AD81: =AD5+AD21-(-AD55)-AD79 | AE81: =AE5+AE21-(-AE55)-AE79 | AF81: =AF5+AF21-(-AF55)-AF79+AF77 | AG81: =AG5+AG21-(-AG55)-AG79 | AH81: =AH5+AH21-(-AH55)-AH79 | AI81: =AI5+AI21-(-AI55)-AI79 | AJ81: =AJ5+AJ21-(-AJ55)-AJ79 | AK81: =AK5+AK21-(-AK55)-AK79 | AL81: =AL5+AL21-(-AL55)-AL79 | AM81: =AM5+AM21-(-AM55)-AM79 | AN81: =AN5+AN21-(-AN55)-AN79+AN77 | AO81: =AO5+AO21-(-AO55)-AO79 | AP81: =AP5+AP21-(-AP55)-AP79+AP77-AP78 | AQ81: =AQ5+AQ21-(-AQ55)-AQ79 | AR81: =AR5+AR21-(-AR55)-AR79 | AS81: =AS5+AS21-(-AS55)-AS79 | AT81: =AT5+AT21-(-AT55)-AT79 | AU81: =AU5+AU21-(-AU55)-AU79 | AV81: =AV5+AV21-(-AV55)-AV79 | AW81: =AW5+AW21-(-AW55)-AW79+AW77-AW78 | AX81: =AX5+AX21-(-AX55)-AX79 | AY81: =AY5+AY21-(-AY55)-AY79+AY77-AY78 | AZ81: =AZ5+AZ21-(-AZ55)-AZ79 | BA81: =BA5+BA21-(-BA55)-BA79 | BB81: =BB5+BB21-(-BB55)-BB79
A82: Остаток на конец ПО КАССЕ | C82: 4917728 | D82: =D6+D28-(-D74)+D77-D78+D80 | E82: =E6+E28-(-E74)+E77-E78+E80 | F82: =F6+F28-(-F74)+F77-F78+F80 | G82: =G6+G28-(-G74)+G77-G78+G80 | H82: =H6+H28-(-H74)+H77-H78+H80 | I82: =I6+I28-(-I74)+I77-I78+I80 | J82: =J6+J28-(-J74)+J77-J78+J80 | K82: =K6+K28-(-K74)+K77-K78+K80 | ... U82: =U6+U28-(-U74)+U77-U78+U80 | V82: =V6+V28-(-V74)-V78+V80 | W82: =W6+W28-(-W74)+W77-W78+W80 | X82: =X6+X28-(-X74)+X80 | Y82: =Y6+Y28-(-Y74)+Y77-Y78+Y80 | Z82: =Z6+Z28-(-Z74)+Z77-Z78+Z80 | AA82: =AA6+AA28-(-AA74)+AA77-AA78+AA80 | AB82: =AB6+AB28-(-AB74)+AB80 | AC82: =AC6+AC28-(-AC74)+AC77-AC78+AC80 | AD82: =AD6+AD28-(-AD74)+AD77-AD78+AD80 | AE82: =AE6+AE28-(-AE74)+AE77-AE78+AE80 | AF82: =AF6+AF28-(-AF74)+AF80 | AG82: =AG6+AG28-(-AG74)+AG77-AG78+AG80 | AH82: =AH6+AH28-(-AH74)+AH77-AH78+AH80 | AI82: =AI6+AI28-(-AI74)+AI77-AI78+AI80 | AJ82: =AJ6+AJ28-(-AJ74)+AJ77-AJ78+AJ80 | AK82: =AK6+AK28-(-AK74)+AK77-AK78+AK80 | AL82: =AL6+AL28-(-AL74)+AL77-AL78+AL80 | AM82: =AM6+AM28-(-AM74)+AM77-AM78+AM80 | AN82: =AN6+AN28-(-AN74)-AN78+AN80 | AO82: =AO6+AO28-(-AO74)+AO77-AO78+AO80 | AP82: =AP6+AP28-(-AP74)+AP80 | AQ82: =AQ6+AQ28-(-AQ74)+AQ77-AQ78+AQ80 | AR82: =AR6+AR28-(-AR74)+AR77-AR78+AR80 | AS82: =AS6+AS28-(-AS74)+AS77-AS78+AS80 | AT82: =AT6+AT28-(-AT74)+AT77+AT80 | AU82: =AU6+AU28-(-AU74)+AU77-AU78+AU80 | AV82: =AV6+AV28-(-AV74)+AV77-AV78+AV80 | AW82: =AW6+AW28-(-AW74)+AW80 | AX82: =AX6+AX28-(-AX74)+AX77-AX78+AX80 | AY82: =AY6+AY28-(-AY74)+AY80 | AZ82: =AZ6+AZ28-(-AZ74)+AZ77-AZ78+AZ80 | BA82: =BA6+BA28-(-BA74)+BA77-BA78+BA80 | BB82: =BB6+BB28-(-BB74)+BB77-BB78+BB80
A83: Итого | C83: 4058056 | D83: =D81+D82 | E83: =E81+E82 | F83: =F81+F82 | G83: =G81+G82 | H83: =H81+H82 | I83: =I81+I82 | J83: =J81+J82 | K83: =K81+K82 | ... BB83: =BB81+BB82
V84: 2104029 | BA84: Итого май (+если есть деньги, - кас.разрыв) | BC84: =BC75+BC29
AX85: Факт АПРЕЛЬ | BA85: План | BB85: Факт | BC85: Отклонение
K86: Выплата поставщикам | U86: Выплата поставщикам | AE86: Выплата поставщикам | AX86: ='ДДС ФАКТ Апрель'!I27+'ДДС ФАКТ Апрель'!I26+'ДДС ФАКТ Апрель'!I34+'ДДС ФАКТ Апрель'!I32+'ДДС ФАКТ Апрель'!I35 | AY86: Выплата поставщикам | BA86: =BA31+BA46+BA47+BA53+BA73+BA56+BA49 | BB86: =BB31+BB46+BB47+BB53+BB73+BB56 | BC86: =BA86-BB86
K87: Налоги | U87: Налоги | AE87: Налоги | AX87: ='ДДС ФАКТ Апрель'!I24 | AY87: Налоги | BA87: =BA39 | BB87: =BB39 | BC87: =BA87-BB87
K88: Оплата труда | U88: Оплата труда | AE88: Оплата труда | AX88: ='ДДС ФАКТ Апрель'!I25 | AY88: Оплата труда | BA88: =BA40+BA62 | BB88: =BB40+BB62 | BC88: =BA88-BB88
K89: Ремонт | U89: Ремонт | AE89: Ремонт | AX89: ='ДДС ФАКТ Апрель'!I28+'ДДС ФАКТ Апрель'!I30 | AY89: Произв. расх | BA89: =BA64+BA43+BA44+BA51+BA65 | BB89: =BB51+BB50+BB70+BB71 | BC89: =BA89-BB89
K90: ОС | U90: ОС | AE90: ОС | AY90: ОС | BA90: =BA52+BA72 | BB90: =BB52+BB72 | BC90: =BA90-BB90

Sheet ОБУ МАЙ
A1: Сатья расхода | B1: Безналичныйрасчёт | H1: Наличныйрасчёт | N1: Итого Расходы май
B2: МАЙ 2026 года | G2: Итого без.нал | H2: МАЙ 2026 года | M2: Итого нал
B3: 1 неделя | C3: 2 неделя | D3: 3 неделя | E3: 4 неделя | F3: 5 неделя | H3: 1 неделя | I3: 2 неделя | J3: 3 неделя | K3: 4 неделя | L3: 5 неделя
A4: IT-обслуживание,телефония,интернет | B4: 170 577 | C4: 310 400 | G4: 480 977 | M4: 0 | N4: 480 977
A5: Авансы поставщикам | G5: 0 | M5: 0 | N5: 0
A6: Административные расходы | B6: 555 000 | D6: 555 000 | G6: 1 110 000 | J6: 690000 | K6: 350000 | M6: 1040000 | N6: 2 150 000
A7: Страховка сотрудников | E7: 427 718 | G7: 427 718 | M7: 0 | N7: 427 718
A8: Возврат ВФП | G8: 0 | M8: 0 | N8: 0
A9: Представительские расходы | G9: 0 | M9: 0 | N9: 0
A10: Аренда помещений | D10: 6 050 000 | G10: 6 050 000 | M10: 0 | N10: 6 050 000
A11: Газ | G11: 0 | H11: 90000 | I11: 90000 | J11: 90000 | K11: 90000 | L11: 90000 | M11: 450000 | N11: 450 000
A12: Маркетинг | G12: 0 | M12: 0 | N12: 0
A13: Мусор | D13: 750 000 | G13: 750 000 | M13: 0 | N13: 750 000
A14: Налоги и другие платежи в бюджет | B14: 7 000 000 | C14: 7 000 000 | D14: 7 000 000 | E14: 15 340 839 | G14: 36 340 839 | M14: 0 | N14: 36 340 839
A15: Оплата труда (пятница-уволенные) (четверг-лагманщики) каждую неделю | G15: 0 | H15: 2 400 000 | I15: 3 000 000 | J15: 2 400 000 | K15: 2 400 000 | L15: 2 400 000 | M15: 12600000 | N15: 12 600 000
A16: Оплата труда | C16: 16 000 000 | E16: 2000000 | G16: 18 000 000 | I16: 20 000 000 | J16: 20 000 000 | K16: 20 000 000 | L16: 2 000 000 | M16: 62000000 | N16: 80 000 000
A17: Охрана | G17: 0 | M17: 0 | N17: 0
A18: Платежи поставщикам Прочее | C18: 950 000 | D18: 172 450 | G18: 1 122 450 | M18: 0 | N18: 1 122 450
A19: Производственные расходы | G19: 0 | H19: 100 000 | I19: 100 000 | J19: 100 000 | K19: 100 000 | L19: 100 000 | M19: 500000 | N19: 500 000
A20: Инвентарь | G20: 0 | M20: 0 | N20: 0
A21: Униформа | G21: 0 | M21: 0 | N21: 0
A22: Упаковка | G22: 0 | M22: 0 | N22: 0
A23: Хоз.товары | G23: 0 | M23: 0 | N23: 0
A24: Погашение кредита и %% | B24: 1 749 942 | E24: 4013564 | G24: 5 763 506 | M24: 0 | N24: 5 763 506
A25: Расходы по реализации Разные(Логистика) | D25: 1 500 000 | F25: 2 000 000 | G25: 3 500 000 | M25: 0 | N25: 3 500 000
A26: Ремонт помещений | B26: 500000 | C26: 500000 | D26: 500000 | E26: 500000 | G26: 2 000 000 | M26: 0 | N26: 2 000 000
A27: Ремонт оборудования | B27: 1000000 | C27: 500000 | D27: 500000 | E27: 1000000 | G27: 3 000 000 | M27: 0 | N27: 3 000 000
A28: Приобретение основных средств | G28: 0 | M28: 0 | N28: 0
A29: Сырье Платежи поставщикам Стас | G29: 0 | H29: 2 000 000 | I29: 2 000 000 | J29: 2 000 000 | K29: 2 000 000 | L29: 2 000 000 | M29: 10000000 | N29: 10 000 000
A30: Электроэнергия и комун расходы | E30: 9 000 000 | G30: 9 000 000 | M30: 0 | N30: 9 000 000
A31: ИТОГО | B31: 10 975 519 | C31: 25 260 400 | D31: 17 027 450 | E31: 32 282 121 | F31: 2 000 000 | G31: 87 545 490 | H31: 4 590 000 | I31: 25 190 000 | J31: 25 280 000 | K31: 24 940 000 | L31: 6 590 000 | M31: 86590000 | N31: 174 135 490

Sheet КРЕДИТ!
B3: ДЗ | C3: КЗ | D3: 40000000
B4: 217340687 | C4: 182009593 | D4: =D3-B7
A6: Поступления | B6: 54000000
A7: Кредит | B7: 35000000
A8: ИТОГО | B8: =B6+B7
A9: Выбытия
A10: Налоги | C10: 28000000
A11: ЗП (производство) | C11: 24109000
A12: Поставщики, подотчёт | C12: 40000000
A13: ЭЭ
A14: кредит | C14: 4013564
B16: =B8 | C16: =C10+C11+C12+C14
C18: =B8-C16
B19: ЗП АУП | C19: 15220000

Sheet Каспи, CRAVE
B3: План выплаты Фуд заводу с каспи банка . Апрель месяц | H3: План выплаты Фуд заводу с Crave café жетысу | K3: План выплаты Фуд заводу с Crave café Сейфуллина
B4: с 06.04 по 10.04 | C4: Каспи банк | H4: с 06.04 по 10.04 | I4: 400 000 | K4: с 06.04 по 10.04 | L4: 200 000
B5: 46119 | C5: 3 000 000 | H5: 13.04-17.04 | I5: 800 000 | K5: 13.04-17.04 | L5: 800 000
B6: 46120 | C6: 1 500 000 | H6: 20.04-24.04 | I6: 500 000 | K6: 20.04-24.04 | L6: 500 000
B7: 46121 | C7: 1 000 000 | H7: 27.04-30.04 | I7: 500 000 | K7: 27.04-30.04 | L7: 500 000
B8: 46122 | C8: не будет. Офиц зп отправим | I8: 2 200 000 | L8: 2 000 000
B9: Итого: | C9: 5 500 000
B11: 13.04-17.04 | C11: Каспи банк
B12: 46125 | C12: не будет.ЗП выдаем
B13: 46126
B14: 46127 | C14: 1 400 000
B15: 46128 | C15: 1 400 000
B16: 46129 | C16: 800 000 | D16: налог оплатим поэтому мало
B17: Итого: | C17: 3 600 000
B19: 20.04-24.04 | C19: Каспи банк
B20: 46132 | C20: 1 400 000
B21: 46133 | C21: 1 400 000
B22: 46134 | C22: 1 400 000
B23: 46135 | C23: 1 400 000
B24: 46136 | C24: 1 400 000
B25: Итого: | C25: 7 000 000
B27: 27.04-30.04 | C27: Каспи банк
B28: 46139 | C28: 1 400 000
B29: 46140 | C29: 1 400 000
B30: 46141 | C30: 1 400 000
B31: 46142 | C31: 1 400 000
B32: Итого: | C32: 5 600 000
B34: Итого: | C34: 21 700 000

Sheet ДДС ФАКТ Апрель
A1: Отчет о движении денежных средств
A2: За период: с 01.04.2026 по 30.04.2026
A3: Подразделение | C3: Концепция
A5: Сумма
A6: Тип статьи | D6: Статья ДДС 1-ого уровня | F6: Статья ДДС 2-ого уровня | G6: Статья ДДС 3-ого уровня | H6: Приход/Расход | I6: Итого
A7: Остаток на начало | I7: 4 034 780 | K7: =TRIM(I7:I41)
A8: Инвестиционная деятельность | D8: Приобретение основных средств | H8: Расход | I8: -173 446 | K8: =TRIM(I8:I42)
A9: Операционная деятельность | D9: 1 Внутренние обороты | H9: Приход | I9: 372 495 755 | K9: =TRIM(I9:I43)
H10: Расход | I10: -357 314 350 | K10: =TRIM(I10:I44)
I11: 15 181 405 | K11: =TRIM(I11:I45)
D12: 1.Выручка | H12: Приход | I12: 260235528 | J12: =I12*1.18 | K12: =TRIM(I12:I46)
D13: 2.Доходы прочие(аренда...) | H13: Приход | I13: 89 157 | K13: =TRIM(I13:I47)
D14: 3.ВнутриГрупп Поступление | H14: Приход | I14: 493 161 | K14: =TRIM(I14:I48)
D15: 4.ВнутриГрупп Выбытие | H15: Расход | I15: -358 000 | K15: =TRIM(I15:I49)
D16: IT-обслуживание,телефония,интернет | H16: Расход | I16: -390977 | K16: =TRIM(I16:I50)
D17: Административные расходы | H17: Расход | I17: -3162568 | K17: =TRIM(I17:I51)
D18: Аренда квартир | H18: Расход | I18: -1530149 | K18: =TRIM(I18:I52)
D19: Аренда помещений | H19: Расход | I19: -6 655 000 | K19: =TRIM(I19:I53)
D20: Возврат с подотчета | H20: Приход | I20: 1 770 | K20: =TRIM(I20:I54)
D21: Инвентарь | H21: Расход | I21: -85000 | K21: =TRIM(I21:I55)
D22: Маркетинг | H22: Расход | I22: -1 454 344 | K22: =TRIM(I22:I56)
D23: Мусор | H23: Расход | I23: -642 920 | K23: =TRIM(I23:I57)
D24: Налоги и другие платежи в бюджет | H24: Расход | I24: -28 737 701 | K24: =TRIM(I24:I58)
D25: Оплата труда | H25: Расход | I25: -76 177 553 | K25: =TRIM(I25:I59)
D26: Платежи поставщикам Прочее | H26: Расход | I26: -1940260 | K26: =TRIM(I26:I60)
D27: Подотчет | H27: Расход | I27: -43340 | K27: =TRIM(I27:I61)
D28: Производственные расходы | H28: Расход | I28: -8424939 | K28: =TRIM(I28:I62)
D29: Расходы по реализации Разные | H29: Расход | I29: -176080 | K29: =TRIM(I29:I63)
D30: Ремонт оборудования | H30: Расход | I30: -1195116 | K30: =TRIM(I30:I64)
D31: Ремонт помещений | H31: Расход | I31: -155000 | K31: =TRIM(I31:I65)
D32: Сырье Платежи поставщикам | H32: Расход | I32: -115230372 | K32: =TRIM(I32:I66)
D33: Униформа | H33: Расход | I33: -475800 | K33: =TRIM(I33:I67)
D34: Упаковка | H34: Расход | I34: -13789130 | K34: =TRIM(I34:I68)
D35: Хоз. товары | H35: Расход | I35: -976593 | K35: =TRIM(I35:I69)
D36: Электроэнергия | H36: Расход | I36: -6534051 | K36: =TRIM(I36:I70)
A37: Операционная деятельность | I37: 7 866 128 | K37: =TRIM(I37:I71)
A38: Финансовая деятельность | D38: Возврат ВФП | H38: Расход | I38: -12 495 000 | K38: =TRIM(I38:I72)
D39: ВФП Учредители поступление | H39: Приход | I39: 6 898 500 | K39: =TRIM(I39:I73)
A40: Финансовая деятельность | I40: -5 596 500 | K40: =TRIM(I40:I74)
A41: Остаток на конец | I41: 6 130 962 | K41: =TRIM(I41:I75)

Sheet Лист13
A1: Статья ДДС 1-ого уровня | B1: Приход/Расход | C1: =E1-D4
C2: 46113
A3: Остаток на начало по Банку | C3: План
A4: Остаток на начало по Кассе | C4: =A83
A5: Прочие | B5: Приход | C5: =A84
A6: Б1, Б2, Б5 | B6: Приход | C6: 1000000
A7: Яндекс | B7: Приход
A8: Май Март | B8: Приход
A9: 7-Kaspi Банк | B9: Приход | C9: 1000000
A10: Crave | B10: Приход | C10: 1000000
A11: 99-RP АЗС | B11: Приход
A12: 96- DSF покупатель | B12: Приход
A13: 85-ДФЗ дистрибьютер ФЗ | B13: Приход | C13: 5000000
A14: 110 АЗС №67 "Sinooil" | B14: Приход | C14: 2000000
A15: 100 ТУАР (шинлайн) | B15: Приход
A16: Даркстор Чоко | B16: Приход | C16: 150000
A17: Глово, Вольт | B17: Приход
A18: Торты | B18: Приход
A19: Итого по банку | B19: Приход
A20: 97- Кейтеринг гость | B20: Приход | C20: =SUM(C6:C19)
A21: Возврат с подотчета, Кредит | B21: Приход
A22: Crave | B22: Приход
A23: 7-Kaspi Банк (нал) | B23: Приход
A24: 9-БАЗИЛИК 5 (АКСАЙ) | B24: Приход
A25: 2-Алматушка (нал) | B25: Приход
A26: 1-Basilic номер1 (нал) | B26: Приход
A27: Частное лицо (Покупатель) | B27: Приход
A28: 98-FOOD vending : СКЛАД АППАРАТ №1 (ФЗ Ермагамбет) | B28: Приход
A29: Итого по кассе | B29: Приход
A30: 1.Выручка | B30: Приход | C30: =SUM(C21:C29)
A31: IT-обслуживание,телефония,интернет | B31: Расход | C31: =C20+C30
A32: Авансы поставщикам | B32: Расход | C32: -82240
A33: Административные расходы | B33: Расход
A34: Возврат ВФП | B34: Расход
A35: Представительские расходы | B35: Расход
A36: Аренда помещений | B36: Расход
A37: Газ | B37: Расход
A38: Маркетинг | B38: Расход
A39: Мусор | B39: Расход
A40: Налоги и другие платежи в бюджет | B40: Расход
A41: Оплата труда | B41: Расход
A42: Охрана | B42: Расход
A43: Платежи поставщикам Прочее | B43: Расход
A44: Производственные расходы | B44: Расход | C44: -180000
A45: Инвентарь | B45: Расход
A46: Униформа | B46: Расход
A47: Упаковка | B47: Расход
A48: Хоз.товара | B48: Расход
A49: Погашение кредита и %% | B49: Расход
A50: Расходы по реализации Разные(Логистика) | B50: Расход
A51: Ремонт помещений | B51: Расход
A52: Ремонт оборудования | B52: Расход
A53: Приобретение основных средств | B53: Расход
A54: Сырье Платежи поставщикам | B54: Расход
A55: Электроэнергия | B55: Расход
A56: Итого по банку | B56: Расход
A57: Подотчет (Рынок сырье, Рынок ТМЦ) | B57: Расход | C57: =SUM(C32:C56)
A58: Административные расходы | B58: Расход
A59: Представительские расходы | B59: Расход
A60: Аренда квартир | B60: Расход
A61: Налоги и другие платежи в бюджет | B61: Расход
A62: Маркетинг | B62: Расход
A63: Оплата труда | B63: Расход
A64: Платежи поставщикам Прочее | B64: Расход
A65: Производственные расходы | B65: Расход
A66: Инвентарь | B66: Расход
A67: Погашение кредита и %% | B67: Расход
A68: Хоз.товара | B68: Расход
A69: Канц.товары | B69: Расход
... A75: Итого по кассе | B75: Расход
A76: ИТОГО РАСХОДЫ | C76: =SUM(C58:C75)
A77: Операционная деятельность | C77: =C57+C76
A78: ВФП Учредители поступление (НАЛ) | B78: Приход | C78: =C31-(-C57-C76)
B79: Расход
A80: Касса взаиморасчета банк | B80: Расход
A81: Касса взаиморасчета касса | B81: Приход | C81: 2000000
A82: Остаток на конец ПО БАНКУ | C82: 2000000
A83: Остаток на конец ПО КАССЕ | C83: =C4+C20-(-C57)-C81
A84: Итого | C84: =C5+C30-(-C76)+C79-C80+C82
C85: =C83+C84

Sheet Проект ДДС
BL1: Итого 4-я неделя
A2: Статья ДДС 1-ого уровня | B2: Приход/Расход | E2: 46113 | F2: 46114 | G2: 46115 | H2: Итого план 1 неделя | I2: Итого факт 1 неделя | J2: Отклонение | K2: 46118 | AD2: 46119 | AF2: 46120 | AH2: 46121 | AJ2: 46122 | AL2: Итого 2-я неделя | AN2: Отклонение | AO2: 46125 | AQ2: 46126 | AS2: 46127 | AU2: 46128 | AW2: 46129 | AY2: Итого 3-я неделя | BA2: Отклонение | BB2: 46132 | BD2: 46133 | BF2: 46134 | BH2: 46135 | BJ2: 46136 | BL2: Итого план 4 неделя | BM2: Итого факт 4 неделя | BN2: Отклонение | BO2: 46139 | BQ2: 46140 | BS2: 46141 | BU2: 46142 | CC2: Итого план 5 неделя | CD2: Итого факт 5 неделя | CE2: Отклонение | CF2: Итого план | CG2: Итого факт | CH2: Отклонение
C3: План | D3: План | E3: План | F3: План | G3: План | K3: 46143 | AB3: Факт | AD3: План | AE3: Факт | AF3: План | AG3: Факт | AH3: План | AI3: Факт | AJ3: План | AK3: Факт | AL3: План | AM3: Факт | AO3: План | AP3: Факт | AQ3: План | AR3: Факт | AS3: План | AT3: Факт | AU3: План | AV3: Факт | AW3: План | AX3: Факт | AY3: План | AZ3: Факт | BB3: План | BC3: Факт | BD3: План | BE3: Факт | BF3: План | BG3: Факт | BH3: План | BI3: Факт | BJ3: План | BK3: Факт
A4: Остаток на начало по Банку | C4: 3140328 | D4: =C83 | E4: =D83 | F4: =E83 | G4: =F83 | H4: =C4 | I4: =H4 | J4: =I4-H4 | K4: =G83 | AB4: =#REF! | AD4: =K83 | AE4: =AB83 | AF4: =AD83 | AG4: =AE83 | AH4: =AF83 | AI4: =AG83 | AJ4: =AH83 | AK4: =AI83 | AL4: =K4 | AM4: =AL4 | AN4: =AM4-AL4 | AO4: =AJ83 | AP4: =AM83 | AQ4: =AO83 | AR4: =AP83 | AS4: =AQ83 | AT4: =AR83 | AU4: =AS83 | AV4: =AT83 | AW4: =AU83 | AX4: =AV83 | AY4: =AO4 | AZ4: =AP4 | BA4: =AZ4-AY4 | BB4: =AW83 | BC4: =AX83 | BD4: =BB83 | BE4: =BC83 | BF4: =BD83 | BG4: =BE83 | BH4: =BF83 | BI4: =BG83 | BJ4: =BH83 | BK4: =BI83 | BL4: =BB4 | BM4: =BC4 | BN4: =BM4-BL4 | BO4: =BJ83 | BP4: =BK83 | BQ4: =BO83 | BR4: =BP83 | BS4: =BQ83 | BT4: =BR83 | BU4: =BS83 | BV4: =BT83 | BW4: =BU83 | BX4: =BV83 | ... CB4: =BZ83 | CC4: =BO4 | CD4: =BP4 | CE4: =CD4+CC4 | CF4: =C4 | CG4: =CF4 | CH4: =CG4-CF4
A5: Остаток на начало по Кассе | C5: 917728 | D5: =C84 | E5: =D84 | F5: =E84 | G5: =F84 | H5: =C5 | I5: =H5 | J5: =I5-H5 | K5: =G84 | AB5: =#REF! | AD5: =K84 | AE5: =AB84 | AF5: =AD84 | AG5: =AE84 | AH5: =AF84 | AI5: =AG84 | AJ5: =AH84 | AK5: =AI84 | AL5: =K5 | AM5: =AL5 | AN5: =AM5-AL5 | AO5: =AJ84 | AP5: =AM84 | AQ5: =AO84 | AR5: =AP84 | AS5: =AQ84 | AT5: =AR84 | AU5: =AS84 | AV5: =AT84 | AW5: =AU84 | AX5: =AV84 | AY5: =AO5 | AZ5: =AP5 | BA5: =AZ5-AY5 | BB5: =AW84 | BC5: =AX84 | BD5: =BB84 | BE5: =BC84 | BF5: =BD84 | BG5: =BE84 | BH5: =BF84 | BI5: =BG84 | BJ5: =BH84 | BK5: =BI84 | BL5: =BB5 | BM5: =BC5 | BN5: =BM5-BL5 | BO5: =BJ84 | BP5: =BK84 | BQ5: =BO84 | BR5: =BP84 | BS5: =BQ84 | BT5: =BR84 | BU5: =BS84 | BV5: =BT84 | BW5: =BU84 | BX5: =BV84 | ... CB5: =BZ84 | CC5: =BO5 | CD5: =BO5 | CE5: =CD5-CC5 | CF5: =C5 | CG5: =CF5 | CH5: =CG5-CF5
A6: Прочие | B6: Приход | E6: 1000000 | H6: =C6+D6+E6+F6+G6 | I6: =#REF!+#REF!+#REF!+#REF!+#REF! | J6: =I6-H6 | K6: 1000000 | AB6: =303750+17890 | AJ6: 500000 | AL6: =K6+AD6+AF6+AH6+AJ6 | AM6: =AB6+AE6+AG6+AI6+AK6 | AN6: =AM6-AL6 | AQ6: 600000 | AW6: 400000 | AY6: =AO6+AQ6+AS6+AU6+AW6 | AZ6: =AP6+AR6+AT6+AV6+AX6 | BA6: =AZ6-AY6 | BH6: 1000000 | BL6: =BB6+BD6+BF6+BH6+BJ6 | BM6: =BC6+BE6+BG6+BI6+BK6 | BN6: =BM6-BL6 | BQ6: 500000 | BU6: 500000 | CC6: =BO6+BQ6+BS6+BU6+BW6+BY6+CA6 | CD6: =BP6+BR6+BT6+BV6+BX6+BZ6+CB6 | CE6: =CD6-CC6 | CF6: =AL6+AY6+BL6+CC6+H6 | CG6: =AM6+AZ6+BM6+CD6+I6 | CH6: =CF6-CG6
A7: Б1, Б2, Б5 | B7: Приход | G7: 1600000 | H7: =C7+D7+E7+F7+G7 | I7: =#REF!+#REF!+#REF!+#REF!+#REF! | J7: =I7-H7 | AB7: 1144435 | AE7: 1168357 | AH7: 2000000 | AL7: =K7+AD7+AF7+AH7+AJ7 | AM7: =AB7+AE7+AG7+AI7+AK7 | AN7: =AM7-AL7 | AW7: 2000000 | AY7: =AO7+AQ7+AS7+AU7+AW7 | AZ7: =AP7+AR7+AT7+AV7+AX7 | BA7: =AZ7-AY7 | BD7: 1000000 | BJ7: 1000000 | BL7: =BB7+BD7+BF7+BH7+BJ7 | BM7: =BC7+BE7+BG7+BI7+BK7 | BN7: =BM7-BL7 | BS7: 1000000 | CC7: =BO7+BQ7+BS7+BU7+BW7+BY7+CA7 | CD7: =BP7+BR7+BT7+BV7+BX7+BZ7+CB7 | CE7: =CD7-CC7 | CF7: =AL7+AY7+BL7+CC7+H7 | CG7: =AM7+AZ7+BM7+CD7+I7 | CH7: =CF7-CG7
A8: Яндекс | B8: Приход | F8: 6000000 | H8: =C8+D8+E8+F8+G8 | I8: =#REF!+#REF!+#REF!+#REF!+#REF! | J8: =I8-H8 | AD8: 8000000 | AE8: 8761731 | AH8: 6000000 | AL8: =K8+AD8+AF8+AH8+AJ8 | AM8: =AB8+AE8+AG8+AI8+AK8 | AN8: =AM8-AL8 | AQ8: 8000000 | AU8: 6000000 | AY8: =AO8+AQ8+AS8+AU8+AW8 | AZ8: =AP8+AR8+AT8+AV8+AX8 | BA8: =AZ8-AY8 | BD8: 8000000 | BH8: 6000000 | BL8: =BB8+BD8+BF8+BH8+BJ8 | BM8: =BC8+BE8+BG8+BI8+BK8 | BN8: =BM8-BL8 | BQ8: 8000000 | BU8: 8000000 | CC8: =BO8+BQ8+BS8+BU8+BW8+BY8+CA8 | CD8: =BP8+BR8+BT8+BV8+BX8+BZ8+CB8 | CE8: =CD8-CC8 | CF8: =AL8+AY8+BL8+CC8+H8 | CG8: =AM8+AZ8+BM8+CD8+I8 | CH8: =CF8-CG8
A9: Май Март | B9: Приход | E9: 1000000 | H9: =C9+D9+E9+F9+G9 | I9: =#REF!+#REF!+#REF!+#REF!+#REF! | J9: =I9-H9 | AD9: 2000000 | AG9: 1406616 | AL9: =K9+AD9+AF9+AH9+AJ9 | AM9: =AB9+AE9+AG9+AI9+AK9 | AN9: =AM9-AL9 | AW9: 2000000 | AY9: =AO9+AQ9+AS9+AU9+AW9 | AZ9: =AP9+AR9+AT9+AV9+AX9 | BA9: =AZ9-AY9 | BF9: 2000000 | BL9: =BB9+BD9+BF9+BH9+BJ9 | BM9: =BC9+BE9+BG9+BI9+BK9 | BN9: =BM9-BL9 | BQ9: 2000000 | CC9: =BO9+BQ9+BS9+BU9+BW9+BY9+CA9 | CD9: =BP9+BR9+BT9+BV9+BX9+BZ9+CB9 | CE9: =CD9-CC9 | CF9: =AL9+AY9+BL9+CC9+H9 | CG9: =AM9+AZ9+BM9+CD9+I9 | CH9: =CF9-CG9
A10: 7-Kaspi Банк | B10: Приход | E10: 1000000 | F10: 1500000 | G10: 1000000 | H10: =C10+D10+E10+F10+G10 | I10: =#REF!+#REF!+#REF!+#REF!+#REF! | J10: =I10-H10 | AE10: 3000000 | AF10: 1000000 | AG10: 1500000 | AH10: 1000000 | AJ10: 1000000 | AL10: =K10+AD10+AF10+AH10+AJ10 | AM10: =AB10+AE10+AG10+AI10+AK10 | AN10: =AM10-AL10 | AO10: 1400000 | AQ10: 1000000 | AS10: 1000000 | AU10: 1000000 | AW10: 1000000 | AY10: =AO10+AQ10+AS10+AU10+AW10 | AZ10: =AP10+AR10+AT10+AV10+AX10 | BA10: =AZ10-AY10 | BB10: 1000000 | BD10: 1000000 | BF10: 1000000 | BH10: 1000000 | BJ10: 1000000 | BL10: =BB10+BD10+BF10+BH10+BJ10 | BM10: =BC10+BE10+BG10+BI10+BK10 | BN10: =BM10-BL10 | BO10: 1000000 | BS10: 1000000 | CC10: =BO10+BQ10+BS10+BU10+BW10+BY10+CA10 | CD10: =BP10+BR10+BT10+BV10+BX10+BZ10+CB10 | CE10: =CD10-CC10 | CF10: =AL10+AY10+BL10+CC10+H10 | CG10: =AM10+AZ10+BM10+CD10+I10 | CH10: =CF10-CG10
A11: Crave | B11: Приход | H11: =C11+D11+E11+F11+G11 | I11: =#REF!+#REF!+#REF!+#REF!+#REF! | J11: =I11-H11 | AL11: =K11+AD11+AF11+AH11+AJ11 | AM11: =AB11+AE11+AG11+AI11+AK11 | AN11: =AM11-AL11 | AY11: =AO11+AQ11+AS11+AU11+AW11 | AZ11: =AP11+AR11+AT11+AV11+AX11 | BA11: =AZ11-AY11 | BD11: 1000000 | BJ11: 1000000 | BL11: =BB11+BD11+BF11+BH11+BJ11 | BM11: =BC11+BE11+BG11+BI11+BK11 | BN11: =BM11-BL11 | BS11: 1000000 | CC11: =BO11+BQ11+BS11+BU11+BW11+BY11+CA11 | CD11: =BP11+BR11+BT11+BV11+BX11+BZ11+CB11 | CE11: =CD11-CC11 | CF11: =AL11+AY11+BL11+CC11+H11 | CG11: =AM11+AZ11+BM11+CD11+I11 | CH11: =CF11-CG11
A12: 99-RP АЗС | B12: Приход | F12: 5000000 | H12: =C12+D12+E12+F12+G12 | I12: =#REF!+#REF!+#REF!+#REF!+#REF! | J12: =I12-H12 | AH12: 6000000 | AL12: =K12+AD12+AF12+AH12+AJ12 | AM12: =AB12+AE12+AG12+AI12+AK12 | AN12: =AM12-AL12 | AU12: 6000000 | AY12: =AO12+AQ12+AS12+AU12+AW12 | AZ12: =AP12+AR12+AT12+AV12+AX12 | BA12: =AZ12-AY12 | BH12: 5000000 | BL12: =BB12+BD12+BF12+BH12+BJ12 | BM12: =BC12+BE12+BG12+BI12+BK12 | BN12: =BM12-BL12 | BU12: 4000000 | CC12: =BO12+BQ12+BS12+BU12+BW12+BY12+CA12 | CD12: =BP12+BR12+BT12+BV12+BX12+BZ12+CB12 | CE12: =CD12-CC12 | CF12: =AL12+AY12+BL12+CC12+H12 | CG12: =AM12+AZ12+BM12+CD12+I12 | CH12: =CF12-CG12
A13: 96- DSF покупатель | B13: Приход | E13: 5000000 | G13: 1000000 | H13: =C13+D13+E13+F13+G13 | I13: =#REF!+#REF!+#REF!+#REF!+#REF! | J13: =I13-H13 | K13: 4000000 | AE13: 2000000 | AL13: =K13+AD13+AF13+AH13+AJ13 | AM13: =AB13+AE13+AG13+AI13+AK13 | AN13: =AM13-AL13 | AW13: 2000000 | AY13: =AO13+AQ13+AS13+AU13+AW13 | AZ13: =AP13+AR13+AT13+AV13+AX13 | BA13: =AZ13-AY13 | BH13: 2000000 | BL13: =BB13+BD13+BF13+BH13+BJ13 | BM13: =BC13+BE13+BG13+BI13+BK13 | BN13: =BM13-BL13 | CC13: =BO13+BQ13+BS13+BU13+BW13+BY13+CA13 | CD13: =BP13+BR13+BT13+BV13+BX13+BZ13+CB13 | CE13: =CD13-CC13 | CF13: =AL13+AY13+BL13+CC13+H13 | CG13: =AM13+AZ13+BM13+CD13+I13 | CH13: =CF13-CG13
A14: 85-ДФЗ дистрибьютер ФЗ | B14: Приход | E14: 2000000 | F14: 2200000 | G14: 3700000 | H14: =C14+D14+E14+F14+G14 | I14: =#REF!+#REF!+#REF!+#REF!+#REF! | J14: =I14-H14 | K14: 10000000 | AB14: =7070000+2800000 | AD14: 4000000 | AE14: =1300000+500000 | AF14: 5000000 | AH14: 1000000 | AJ14: 5000000 | AL14: =K14+AD14+AF14+AH14+AJ14 | AM14: =AB14+AE14+AG14+AI14+AK14 | AN14: =AM14-AL14 | AO14: 10000000 | AQ14: 4000000 | AS14: 3000000 | AU14: 2000000 | AW14: 4000000 | AY14: =AO14+AQ14+AS14+AU14+AW14 | AZ14: =AP14+AR14+AT14+AV14+AX14 | BA14: =AZ14-AY14 | BB14: 11000000 | BD14: 1000000 | BF14: 4000000 | BH14: 4000000 | BJ14: 3000000 | BL14: =BB14+BD14+BF14+BH14+BJ14 | BM14: =BC14+BE14+BG14+BI14+BK14 | BN14: =BM14-BL14 | BO14: 11000000 | BQ14: 1000000 | BS14: 5000000 | BU14: 2000000 | CC14: =BO14+BQ14+BS14+BU14+BW14+BY14+CA14 | CD14: =BP14+BR14+BT14+BV14+BX14+BZ14+CB14 | CE14: =CD14-CC14 | CF14: =AL14+AY14+BL14+CC14+H14 | CG14: =AM14+AZ14+BM14+CD14+I14 | CH14: =CF14-CG14
A15: 110 АЗС №67 "Sinooil" | B15: Приход | H15: =C15+D15+E15+F15+G15 | I15: =#REF!+#REF!+#REF!+#REF!+#REF! | J15: =I15-H15 | AE15: 125725 | AJ15: 1000000 | AL15: =K15+AD15+AF15+AH15+AJ15 | AM15: =AB15+AE15+AG15+AI15+AK15 | AN15: =AM15-AL15 | AQ15: 1500000 | AY15: =AO15+AQ15+AS15+AU15+AW15 | AZ15: =AP15+AR15+AT15+AV15+AX15 | BA15: =AZ15-AY15 | BB15: 1000000 | BL15: =BB15+BD15+BF15+BH15+BJ15 | BM15: =BC15+BE15+BG15+BI15+BK15 | BN15: =BM15-BL15 | BS15: 2000000 | CC15: =BO15+BQ15+BS15+BU15+BW15+BY15+CA15 | CD15: =BP15+BR15+BT15+BV15+BX15+BZ15+CB15 | CE15: =CD15-CC15 | CF15: =AL15+AY15+BL15+CC15+H15 | CG15: =AM15+AZ15+BM15+CD15+I15 | CH15: =CF15-CG15
A16: 100 ТУАР (шинлайн) | B16: Приход | E16: 150000 | H16: =C16+D16+E16+F16+G16 | I16: =#REF!+#REF!+#REF!+#REF!+#REF! | J16: =I16-H16 | AL16: =K16+AD16+AF16+AH16+AJ16 | AM16: =AB16+AE16+AG16+AI16+AK16 | AN16: =AM16-AL16 | AY16: =AO16+AQ16+AS16+AU16+AW16 | AZ16: =AP16+AR16+AT16+AV16+AX16 | BA16: =AZ16-AY16 | BL16: =BB16+BD16+BF16+BH16+BJ16 | BM16: =BC16+BE16+BG16+BI16+BK16 | BN16: =BM16-BL16 | CC16: =BO16+BQ16+BS16+BU16+BW16+BY16+CA16 | CD16: =BP16+BR16+BT16+BV16+BX16+BZ16+CB16 | CE16: =CD16-CC16 | CF16: =AL16+AY16+BL16+CC16+H16 | CG16: =AM16+AZ16+BM16+CD16+I16 | CH16: =CF16-CG16
A17: Даркстор Чоко | B17: Приход | H17: =C17+D17+E17+F17+G17 | I17: =#REF!+#REF!+#REF!+#REF!+#REF! | J17: =I17-H17 | AD17: 600000 | AL17: =K17+AD17+AF17+AH17+AJ17 | AM17: =AB17+AE17+AG17+AI17+AK17 | AN17: =AM17-AL17 | AO17: 210000 | AS17: 440000 | AY17: =AO17+AQ17+AS17+AU17+AW17 | AZ17: =AP17+AR17+AT17+AV17+AX17 | BA17: =AZ17-AY17 | BH17: 650000 | BL17: =BB17+BD17+BF17+BH17+BJ17 | BM17: =BC17+BE17+BG17+BI17+BK17 | BN17: =BM17-BL17 | BO17: 150000 | BS17: 150000 | CC17: =BO17+BQ17+BS17+BU17+BW17+BY17+CA17 | CD17: =BP17+BR17+BT17+BV17+BX17+BZ17+CB17 | CE17: =CD17-CC17 | CF17: =AL17+AY17+BL17+CC17+H17 | CG17: =AM17+AZ17+BM17+CD17+I17 | CH17: =CF17-CG17
A18: Глово, Вольт | B18: Приход | H18: =C18+D18+E18+F18+G18 | I18: =#REF!+#REF!+#REF!+#REF!+#REF! | J18: =I18-H18 | AD18: 1000000 | AE18: 157556 | AH18: 1000000 | AL18: =K18+AD18+AF18+AH18+AJ18 | AM18: =AB18+AE18+AG18+AI18+AK18 | AN18: =AM18-AL18 | AQ18: 1000000 | AY18: =AO18+AQ18+AS18+AU18+AW18 | AZ18: =AP18+AR18+AT18+AV18+AX18 | BA18: =AZ18-AY18 | BD18: 500000 | BJ18: 1000000 | BL18: =BB18+BD18+BF18+BH18+BJ18 | BM18: =BC18+BE18+BG18+BI18+BK18 | BN18: =BM18-BL18 | BQ18: 1000000 | BU18: 600000 | CC18: =BO18+BQ18+BS18+BU18+BW18+BY18+CA18 | CD18: =BP18+BR18+BT18+BV18+BX18+BZ18+CB18 | CE18: =CD18-CC18 | CF18: =AL18+AY18+BL18+CC18+H18 | CG18: =AM18+AZ18+BM18+CD18+I18 | CH18: =CF18-CG18
A19: Торты | B19: Приход | H19: =C19+D19+E19+F19+G19 | I19: =#REF!+#REF!+#REF!+#REF!+#REF! | J19: =I19-H19 | AH19: 500000 | AL19: =K19+AD19+AF19+AH19+AJ19 | AM19: =AB19+AE19+AG19+AI19+AK19 | AN19: =AM19-AL19 | AY19: =AO19+AQ19+AS19+AU19+AW19 | AZ19: =AP19+AR19+AT19+AV19+AX19 | BA19: =AZ19-AY19 | BH19: 300000 | BL19: =BB19+BD19+BF19+BH19+BJ19 | BM19: =BC19+BE19+BG19+BI19+BK19 | BN19: =BM19-BL19 | BU19: 300000 | CC19: =BO19+BQ19+BS19+BU19+BW19+BY19+CA19 | CD19: =BP19+BR19+BT19+BV19+BX19+BZ19+CB19 | CE19: =CD19-CC19 | CF19: =AL19+AY19+BL19+CC19+H19 | CG19: =AM19+AZ19+BM19+CD19+I19 | CH19: =CF19-CG19
A20: Итого по банку | B20: Приход | C20: 0 | D20: =SUM(D6:D19) | E20: =SUM(E6:E19) | F20: =SUM(F6:F19) | G20: =SUM(G6:G19) | H20: =SUM(H6:H19) | I20: =SUM(I6:I19) | J20: =I20-H20 | K20: =SUM(K6:K19) | AB20: =SUM(AB6:AB19) | AD20: =SUM(AD6:AD19) | AE20: =SUM(AE6:AE19) | AF20: =SUM(AF6:AF19) | AG20: =SUM(AG6:AG19) | AH20: =SUM(AH6:AH19) | AI20: =SUM(AI6:AI19) | AJ20: =SUM(AJ6:AJ19) | AK20: =SUM(AK6:AK19) | ... AM20: =SUM(AM6:AM19) | AN20: =AM20-AL20 | AO20: =SUM(AO6:AO19) | AP20: =SUM(AP6:AP19) | AQ20: =SUM(AQ6:AQ19) | AR20: =SUM(AR6:AR19) | AS20: =SUM(AS6:AS19) | AT20: =SUM(AT6:AT19) | AU20: =SUM(AU6:AU19) | AV20: =SUM(AV6:AV19) | ... BM20: =SUM(BM6:BM19) | BN20: =BM20-BL20 | BO20: =SUM(BO6:BO19) | BP20: =SUM(BP6:BP19) | BQ20: =SUM(BQ6:BQ19) | BR20: =SUM(BR6:BR19) | BS20: =SUM(BS6:BS19) | BT20: =SUM(BT6:BT19) | BU20: =SUM(BU6:BU19) | BV20: =SUM(BV6:BV19) | ... CD20: =SUM(CD6:CD19) | CE20: =CD20-CC20 | CF20: =SUM(CF6:CF19) | CG20: =SUM(CG6:CG19) | CH20: =CF20-CG20
A21: 97- Кейтеринг гость | B21: Приход | H21: =C21+D21+E21+F21+G21 | I21: =#REF!+#REF!+#REF!+#REF!+#REF! | J21: =I21-H21 | AH21: 450000 | AL21: =K21+AD21+AF21+AH21+AJ21 | AM21: =AB21+AE21+AG21+AI21+AK21 | AN21: =AM21-AL21 | AU21: 250000 | AY21: =AO21+AQ21+AS21+AU21+AW21 | AZ21: =AP21+AR21+AT21+AV21+AX21 | BA21: =AZ21-AY21 | BD21: 300000 | BL21: =BB21+BD21+BF21+BH21+BJ21 | BM21: =BC21+BE21+BG21+BI21+BK21 | BN21: =BM21-BL21 | BQ21: 500000 | CC21: =BO21+BQ21+BS21+BU21+BW21+BY21+CA21 | CD21: =BP21+BR21+BT21+BV21+BX21+BZ21+CB21 | CE21: =CD21-CC21 | CF21: =AL21+AY21+BL21+CC21+H21 | CG21: =AM21+AZ21+BM21+CD21+I21 | CH21: =CF21-CG21
A22: Возврат с подотчета, Кредит | B22: Приход | H22: =C22+D22+E22+F22+G22 | I22: =#REF!+#REF!+#REF!+#REF!+#REF! | J22: =I22-H22 | AL22: =K22+AD22+AF22+AH22+AJ22 | AM22: =AB22+AE22+AG22+AI22+AK22 | AN22: =AM22-AL22 | AY22: =AO22+AQ22+AS22+AU22+AW22 | AZ22: =AP22+AR22+AT22+AV22+AX22 | BA22: =AZ22-AY22 | BL22: =BB22+BD22+BF22+BH22+BJ22 | BM22: =BC22+BE22+BG22+BI22+BK22 | BN22: =BM22-BL22 | CC22: =BO22+BQ22+BS22+BU22+BW22+BY22+CA22 | CD22: =BP22+BR22+BT22+BV22+BX22+BZ22+CB22 | CE22: =CD22-CC22 | CF22: =AL22+AY22+BL22+CC22+H22 | CG22: =AM22+AZ22+BM22+CD22+I22 | CH22: =CF22-CG22
A23: Crave | B23: Приход | H23: =C23+D23+E23+F23+G23 | I23: =#REF!+#REF!+#REF!+#REF!+#REF! | J23: =I23-H23 | AB23: 600000 | AL23: =K23+AD23+AF23+AH23+AJ23 | AM23: =AB23+AE23+AG23+AI23+AK23 | AN23: =AM23-AL23 | AY23: =AO23+AQ23+AS23+AU23+AW23 | AZ23: =AP23+AR23+AT23+AV23+AX23 | BA23: =AZ23-AY23 | BL23: =BB23+BD23+BF23+BH23+BJ23 | BM23: =BC23+BE23+BG23+BI23+BK23 | BN23: =BM23-BL23 | CC23: =BO23+BQ23+BS23+BU23+BW23+BY23+CA23 | CD23: =BP23+BR23+BT23+BV23+BX23+BZ23+CB23 | CE23: =CD23-CC23 | CF23: =AL23+AY23+BL23+CC23+H23 | CG23: =AM23+AZ23+BM23+CD23+I23 | CH23: =CF23-CG23
A24: 7-Kaspi Банк (нал) | B24: Приход | H24: =C24+D24+E24+F24+G24 | I24: =#REF!+#REF!+#REF!+#REF!+#REF! | J24: =I24-H24 | AF24: 1000000 | AH24: 1000000 | AL24: =K24+AD24+AF24+AH24+AJ24 | AM24: =AB24+AE24+AG24+AI24+AK24 | AN24: =AM24-AL24 | AY24: =AO24+AQ24+AS24+AU24+AW24 | AZ24: =AP24+AR24+AT24+AV24+AX24 | BA24: =AZ24-AY24 | BL24: =BB24+BD24+BF24+BH24+BJ24 | BM24: =BC24+BE24+BG24+BI24+BK24 | BN24: =BM24-BL24 | CC24: =BO24+BQ24+BS24+BU24+BW24+BY24+CA24 | CD24: =BP24+BR24+BT24+BV24+BX24+BZ24+CB24 | CE24: =CD24-CC24 | CF24: =AL24+AY24+BL24+CC24+H24 | CG24: =AM24+AZ24+BM24+CD24+I24 | CH24: =CF24-CG24
A25: 9-БАЗИЛИК 5 (АКСАЙ) | B25: Приход | H25: =C25+D25+E25+F25+G25 | I25: =#REF!+#REF!+#REF!+#REF!+#REF! | J25: =I25-H25 | AL25: =K25+AD25+AF25+AH25+AJ25 | AM25: =AB25+AE25+AG25+AI25+AK25 | AN25: =AM25-AL25 | AY25: =AO25+AQ25+AS25+AU25+AW25 | AZ25: =AP25+AR25+AT25+AV25+AX25 | BA25: =AZ25-AY25 | BL25: =BB25+BD25+BF25+BH25+BJ25 | BM25: =BC25+BE25+BG25+BI25+BK25 | BN25: =BM25-BL25 | CC25: =BO25+BQ25+BS25+BU25+BW25+BY25+CA25 | CD25: =BP25+BR25+BT25+BV25+BX25+BZ25+CB25 | CE25: =CD25-CC25 | CF25: =AL25+AY25+BL25+CC25+H25 | CG25: =AM25+AZ25+BM25+CD25+I25 | CH25: =CF25-CG25
A26: 2-Алматушка (нал) | B26: Приход | H26: =C26+D26+E26+F26+G26 | I26: =#REF!+#REF!+#REF!+#REF!+#REF! | J26: =I26-H26 | AL26: =K26+AD26+AF26+AH26+AJ26 | AM26: =AB26+AE26+AG26+AI26+AK26 | AN26: =AM26-AL26 | AY26: =AO26+AQ26+AS26+AU26+AW26 | AZ26: =AP26+AR26+AT26+AV26+AX26 | BA26: =AZ26-AY26 | BL26: =BB26+BD26+BF26+BH26+BJ26 | BM26: =BC26+BE26+BG26+BI26+BK26 | BN26: =BM26-BL26 | CC26: =BO26+BQ26+BS26+BU26+BW26+BY26+CA26 | CD26: =BP26+BR26+BT26+BV26+BX26+BZ26+CB26 | CE26: =CD26-CC26 | CF26: =AL26+AY26+BL26+CC26+H26 | CG26: =AM26+AZ26+BM26+CD26+I26 | CH26: =CF26-CG26
A27: 1-Basilic номер1 (нал) | B27: Приход | H27: =C27+D27+E27+F27+G27 | I27: =#REF!+#REF!+#REF!+#REF!+#REF! | J27: =I27-H27 | AL27: =K27+AD27+AF27+AH27+AJ27 | AM27: =AB27+AE27+AG27+AI27+AK27 | AN27: =AM27-AL27 | AY27: =AO27+AQ27+AS27+AU27+AW27 | AZ27: =AP27+AR27+AT27+AV27+AX27 | BA27: =AZ27-AY27 | BL27: =BB27+BD27+BF27+BH27+BJ27 | BM27: =BC27+BE27+BG27+BI27+BK27 | BN27: =BM27-BL27 | BQ27: 1000000 | CC27: =BO27+BQ27+BS27+BU27+BW27+BY27+CA27 | CD27: =BP27+BR27+BT27+BV27+BX27+BZ27+CB27 | CE27: =CD27-CC27 | CF27: =AL27+AY27+BL27+CC27+H27 | CG27: =AM27+AZ27+BM27+CD27+I27 | CH27: =CF27-CG27
A28: Частное лицо (Покупатель) | B28: Приход | H28: =C28+D28+E28+F28+G28 | I28: =#REF!+#REF!+#REF!+#REF!+#REF! | J28: =I28-H28 | AG28: 228846 | AH28: 200000 | AL28: =K28+AD28+AF28+AH28+AJ28 | AM28: =AB28+AE28+AG28+AI28+AK28 | AN28: =AM28-AL28 | AU28: 400000 | AY28: =AO28+AQ28+AS28+AU28+AW28 | AZ28: =AP28+AR28+AT28+AV28+AX28 | BA28: =AZ28-AY28 | BH28: 200000 | BL28: =BB28+BD28+BF28+BH28+BJ28 | BM28: =BC28+BE28+BG28+BI28+BK28 | BN28: =BM28-BL28 | BQ28: 200000 | CC28: =BO28+BQ28+BS28+BU28+BW28+BY28+CA28 | CD28: =BP28+BR28+BT28+BV28+BX28+BZ28+CB28 | CE28: =CD28-CC28 | CF28: =AL28+AY28+BL28+CC28+H28 | CG28: =AM28+AZ28+BM28+CD28+I28 | CH28: =CF28-CG28
A29: 98-FOOD vending : СКЛАД АППАРАТ №1 (ФЗ Ермагамбет) | B29: Приход | H29: =C29+D29+E29+F29+G29 | I29: =#REF!+#REF!+#REF!+#REF!+#REF! | J29: =I29-H29 | AE29: 1500000 | AL29: =K29+AD29+AF29+AH29+AJ29 | AM29: =AB29+AE29+AG29+AI29+AK29 | AN29: =AM29-AL29 | AY29: =AO29+AQ29+AS29+AU29+AW29 | AZ29: =AP29+AR29+AT29+AV29+AX29 | BA29: =AZ29-AY29 | BL29: =BB29+BD29+BF29+BH29+BJ29 | BM29: =BC29+BE29+BG29+BI29+BK29 | BN29: =BM29-BL29 | CC29: =BO29+BQ29+BS29+BU29+BW29+BY29+CA29 | CD29: =BP29+BR29+BT29+BV29+BX29+BZ29+CB29 | CE29: =CD29-CC29 | CF29: =AL29+AY29+BL29+CC29+H29 | CG29: =AM29+AZ29+BM29+CD29+I29 | CH29: =CF29-CG29
A30: Итого по кассе | B30: Приход | C30: 0 | D30: =SUM(D21:D29) | E30: =SUM(E21:E29) | F30: =SUM(F21:F29) | G30: =SUM(G21:G29) | H30: =SUM(H21:H29) | I30: =SUM(I21:I29) | J30: =I30-H30 | K30: =SUM(K21:K29) | AB30: =SUM(AB21:AB29) | AD30: =SUM(AD21:AD29) | AE30: =SUM(AE21:AE29) | AF30: =SUM(AF21:AF29) | AG30: =SUM(AG21:AG29) | AH30: =SUM(AH21:AH29) | AI30: =SUM(AI21:AI29) | AJ30: =SUM(AJ21:AJ29) | AK30: =SUM(AK21:AK29) | ... AM30: =SUM(AM21:AM29) | AN30: =AM30-AL30 | AO30: =SUM(AO21:AO29) | AP30: =SUM(AP21:AP29) | AQ30: =SUM(AQ21:AQ29) | AR30: =SUM(AR21:AR29) | AS30: =SUM(AS21:AS29) | AT30: =SUM(AT21:AT29) | AU30: =SUM(AU21:AU29) | AV30: =SUM(AV21:AV29) | ... BM30: =SUM(BM21:BM29) | BN30: =BM30-BL30 | BO30: =SUM(BO21:BO29) | BP30: =SUM(BP21:BP29) | BQ30: =SUM(BQ21:BQ29) | BR30: =SUM(BR21:BR29) | BS30: =SUM(BS21:BS29) | BT30: =SUM(BT21:BT29) | BU30: =SUM(BU21:BU29) | BV30: =SUM(BV21:BV29) | ... CD30: =SUM(CD21:CD29) | CE30: =CD30-CC30 | CF30: =SUM(CF21:CF29) | CG30: =SUM(CG21:CG29) | CH30: =CF30-CG30
A31: 1.Выручка | B31: Приход | C31: 0 | D31: =D20+D30 | E31: =E20+E30 | F31: =F20+F30 | G31: =G20+G30 | H31: =H30+H20 | I31: =I30+I20 | J31: =I31-H31 | K31: =K20+K30 | AB31: =AB20+AB30 | AD31: =AD20+AD30 | AE31: =AE20+AE30 | AF31: =AF20+AF30 | AG31: =AG20+AG30 | AH31: =AH20+AH30 | AI31: =AI20+AI30 | AJ31: =AJ20+AJ30 | AK31: =AK20+AK30 | AL31: =AL30+AL20 | AM31: =AM30+AM20 | AN31: =AM31-AL31 | AO31: =AO20+AO30 | AP31: =AP20+AP30 | AQ31: =AQ20+AQ30 | AR31: =AR20+AR30 | AS31: =AS20+AS30 | AT31: =AT20+AT30 | AU31: =AU20+AU30 | AV31: =AV20+AV30 | ... AZ31: =AZ20+AZ30 | BA31: =AZ31-AY31 | BB31: =BB20+BB30 | BC31: =BC20+BC30 | BD31: =BD20+BD30 | BE31: =BE20+BE30 | BF31: =BF20+BF30 | BG31: =BG20+BG30 | BH31: =BH20+BH30 | BI31: =BI20+BI30 | ... BM31: =BM20+BM30 | BN31: =BM31-BL31 | BO31: =BO20+BO30 | BP31: =BP20+BP30 | BQ31: =BQ20+BQ30 | BR31: =BR20+BR30 | BS31: =BS20+BS30 | BT31: =BT20+BT30 | BU31: =BU20+BU30 | BV31: =BV20+BV30 | ... CD31: =CD20+CD30 | CE31: =CD31-CC31 | CF31: =CF20+CF30 | CG31: =CG20+CG30 | CH31: =CF31-CG31
A32: IT-обслуживание,телефония,интернет | B32: Расход | E32: -82240 | F32: -220400 | G32: -80000 | H32: =C32+D32+E32+F32+G32 | I32: =#REF!+#REF!+#REF!+#REF!+#REF! | J32: =I32-H32 | AD32: -120000 | AL32: =K32+AF32+AD32+AH32+AJ32 | AM32: =AB32+AE32+AG32+AI32+AK32 | AN32: =AM32-AL32 | AY32: =AO32+AQ32+AS32+AU32+AW32 | AZ32: =AP32+AR32+AT32+AV32+AX32 | BA32: =AZ32-AY32 | BL32: =BB32+BD32+BF32+BH32+BJ32 | BM32: =BC32+BE32+BG32+BI32+BK32 | BN32: =BM32-BL32 | BO32: -40472 | BQ32: -90000 | CC32: =BO32+BQ32+BS32+BU32+BW32+BY32+CA32 | CD32: =BP32+BR32+BT32+BV32+BX32+BZ32+CB32 | CE32: =CD32-CC32 | CF32: =AL32+AY32+BL32+CC32+H32 | CG32: =AM32+AZ32+BM32+CD32+I32 | CH32: =CF32-CG32
A33: Авансы поставщикам | B33: Расход | H33: =C33+D33+E33+F33+G33 | I33: =#REF!+#REF!+#REF!+#REF!+#REF! | J33: =I33-H33 | AL33: =K33+AF33+AD33+AH33+AJ33 | AM33: =AB33+AE33+AG33+AI33+AK33 | AN33: =AM33-AL33 | AY33: =AO33+AQ33+AS33+AU33+AW33 | AZ33: =AP33+AR33+AT33+AV33+AX33 | BA33: =AZ33-AY33 | BL33: =BB33+BD33+BF33+BH33+BJ33 | BM33: =BC33+BE33+BG33+BI33+BK33 | BN33: =BM33-BL33 | CC33: =BO33+BQ33+BS33+BU33+BW33+BY33+CA33 | CD33: =BP33+BR33+BT33+BV33+BX33+BZ33+CB33 | CE33: =CD33-CC33 | CF33: =AL33+AY33+BL33+CC33+H33 | CG33: =AM33+AZ33+BM33+CD33+I33 | CH33: =CF33-CG33
A34: Административные расходы | B34: Расход | F34: -3000 | G34: -3000 | H34: =C34+D34+E34+F34+G34 | I34: =#REF!+#REF!+#REF!+#REF!+#REF! | J34: =I34-H34 | K34: -3000 | AB34: =-950000-220400-1300 | AD34: =-3000-400000 | AE34: =-400000-1300 | AF34: -3000 | AG34: =-24300-4000 | AH34: -3000 | AJ34: -3000 | AL34: =K34+AF34+AD34+AH34+AJ34 | AM34: =AB34+AE34+AG34+AI34+AK34 | AN34: =AM34-AL34 | AO34: -3000 | AQ34: -30000 | AS34: -32400 | AU34: -30000 | AY34: =AO34+AQ34+AS34+AU34+AW34 | AZ34: =AP34+AR34+AT34+AV34+AX34 | BA34: =AZ34-AY34 | BB34: -3000 | BD34: -3000 | BF34: -3000 | BH34: -30000 | BJ34: -3000 | BL34: =BB34+BD34+BF34+BH34+BJ34 | BM34: =BC34+BE34+BG34+BI34+BK34 | BN34: =BM34-BL34 | BO34: -3000 | BQ34: -3000 | BS34: -3000 | BU34: -3000 | CC34: =BO34+BQ34+BS34+BU34+BW34+BY34+CA34 | CD34: =BP34+BR34+BT34+BV34+BX34+BZ34+CB34 | CE34: =CD34-CC34 | CF34: =AL34+AY34+BL34+CC34+H34 | CG34: =AM34+AZ34+BM34+CD34+I34 | CH34: =CF34-CG34
A35: Возврат ВФП | B35: Расход | H35: =C35+D35+E35+F35+G35 | I35: =#REF!+#REF!+#REF!+#REF!+#REF! | J35: =I35-H35 | AL35: =K35+AF35+AD35+AH35+AJ35 | AM35: =AB35+AE35+AG35+AI35+AK35 | AN35: =AM35-AL35 | AY35: =AO35+AQ35+AS35+AU35+AW35 | AZ35: =AP35+AR35+AT35+AV35+AX35 | BA35: =AZ35-AY35 | BL35: =BB35+BD35+BF35+BH35+BJ35 | BM35: =BC35+BE35+BG35+BI35+BK35 | BN35: =BM35-BL35 | CC35: =BO35+BQ35+BS35+BU35+BW35+BY35+CA35 | CD35: =BP35+BR35+BT35+BV35+BX35+BZ35+CB35 | CE35: =CD35-CC35 | CF35: =AL35+AY35+BL35+CC35+H35 | CG35: =AM35+AZ35+BM35+CD35+I35 | CH35: =CF35-CG35
A36: Представительские расходы | B36: Расход | H36: =C36+D36+E36+F36+G36 | I36: =#REF!+#REF!+#REF!+#REF!+#REF! | J36: =I36-H36 | AL36: =K36+AF36+AD36+AH36+AJ36 | AM36: =AB36+AE36+AG36+AI36+AK36 | AN36: =AM36-AL36 | AY36: =AO36+AQ36+AS36+AU36+AW36 | AZ36: =AP36+AR36+AT36+AV36+AX36 | BA36: =AZ36-AY36 | BL36: =BB36+BD36+BF36+BH36+BJ36 | BM36: =BC36+BE36+BG36+BI36+BK36 | BN36: =BM36-BL36 | CC36: =BO36+BQ36+BS36+BU36+BW36+BY36+CA36 | CD36: =BP36+BR36+BT36+BV36+BX36+BZ36+CB36 | CE36: =CD36-CC36 | CF36: =AL36+AY36+BL36+CC36+H36 | CG36: =AM36+AZ36+BM36+CD36+I36 | CH36: =CF36-CG36
A37: Аренда помещений | B37: Расход | H37: =C37+D37+E37+F37+G37 | I37: =#REF!+#REF!+#REF!+#REF!+#REF! | J37: =I37-H37 | AL37: =K37+AF37+AD37+AH37+AJ37 | AM37: =AB37+AE37+AG37+AI37+AK37 | AN37: =AM37-AL37 | AQ37: -6655000 | AY37: =AO37+AQ37+AS37+AU37+AW37 | AZ37: =AP37+AR37+AT37+AV37+AX37 | BA37: =AZ37-AY37 | BL37: =BB37+BD37+BF37+BH37+BJ37 | BM37: =BC37+BE37+BG37+BI37+BK37 | BN37: =BM37-BL37 | CC37: =BO37+BQ37+BS37+BU37+BW37+BY37+CA37 | CD37: =BP37+BR37+BT37+BV37+BX37+BZ37+CB37 | CE37: =CD37-CC37 | CF37: =AL37+AY37+BL37+CC37+H37 | CG37: =AM37+AZ37+BM37+CD37+I37 | CH37: =CF37-CG37
A38: Газ | B38: Расход | H38: =C38+D38+E38+F38+G38 | I38: =#REF!+#REF!+#REF!+#REF!+#REF! | J38: =I38-H38 | AL38: =K38+AF38+AD38+AH38+AJ38 | AM38: =AB38+AE38+AG38+AI38+AK38 | AN38: =AM38-AL38 | AY38: =AO38+AQ38+AS38+AU38+AW38 | AZ38: =AP38+AR38+AT38+AV38+AX38 | BA38: =AZ38-AY38 | BL38: =BB38+BD38+BF38+BH38+BJ38 | BM38: =BC38+BE38+BG38+BI38+BK38 | BN38: =BM38-BL38 | BO38: -630000 | CC38: =BO38+BQ38+BS38+BU38+BW38+BY38+CA38 | CD38: =BP38+BR38+BT38+BV38+BX38+BZ38+CB38 | CE38: =CD38-CC38 | CF38: =AL38+AY38+BL38+CC38+H38 | CG38: =AM38+AZ38+BM38+CD38+I38 | CH38: =CF38-CG38
A39: Маркетинг | B39: Расход | H39: =C39+D39+E39+F39+G39 | I39: =#REF!+#REF!+#REF!+#REF!+#REF! | J39: =I39-H39 | AG39: -1000000 | AL39: =K39+AF39+AD39+AH39+AJ39 | AM39: =AB39+AE39+AG39+AI39+AK39 | AN39: =AM39-AL39 | AY39: =AO39+AQ39+AS39+AU39+AW39 | AZ39: =AP39+AR39+AT39+AV39+AX39 | BA39: =AZ39-AY39 | BL39: =BB39+BD39+BF39+BH39+BJ39 | BM39: =BC39+BE39+BG39+BI39+BK39 | BN39: =BM39-BL39 | CC39: =BO39+BQ39+BS39+BU39+BW39+BY39+CA39 | CD39: =BP39+BR39+BT39+BV39+BX39+BZ39+CB39 | CE39: =CD39-CC39 | CF39: =AL39+AY39+BL39+CC39+H39 | CG39: =AM39+AZ39+BM39+CD39+I39 | CH39: =CF39-CG39
A40: Мусор | B40: Расход | H40: =C40+D40+E40+F40+G40 | I40: =#REF!+#REF!+#REF!+#REF!+#REF! | J40: =I40-H40 | AG40: -7000 | AL40: =K40+AF40+AD40+AH40+AJ40 | AM40: =AB40+AE40+AG40+AI40+AK40 | AN40: =AM40-AL40 | AW40: -100000 | AY40: =AO40+AQ40+AS40+AU40+AW40 | AZ40: =AP40+AR40+AT40+AV40+AX40 | BA40: =AZ40-AY40 | BJ40: -100000 | BL40: =BB40+BD40+BF40+BH40+BJ40 | BM40: =BC40+BE40+BG40+BI40+BK40 | BN40: =BM40-BL40 | BO40: -850000 | CC40: =BO40+BQ40+BS40+BU40+BW40+BY40+CA40 | CD40: =BP40+BR40+BT40+BV40+BX40+BZ40+CB40 | CE40: =CD40-CC40 | CF40: =AL40+AY40+BL40+CC40+H40 | CG40: =AM40+AZ40+BM40+CD40+I40 | CH40: =CF40-CG40
A41: Налоги и другие платежи в бюджет | B41: Расход | H41: =C41+D41+E41+F41+G41 | I41: =#REF!+#REF!+#REF!+#REF!+#REF! | J41: =I41-H41 | AB41: -2000000 | AE41: -7000000 | AL41: =K41+AF41+AD41+AH41+AJ41 | AM41: =AB41+AE41+AG41+AI41+AK41 | AN41: =AM41-AL41 | AW41: -8000000 | AY41: =AO41+AQ41+AS41+AU41+AW41 | AZ41: =AP41+AR41+AT41+AV41+AX41 | BA41: =AZ41-AY41 | BH41: -14104937 | BJ41: -427718 | BL41: =BB41+BD41+BF41+BH41+BJ41 | BM41: =BC41+BE41+BG41+BI41+BK41 | BN41: =BM41-BL41 | BQ41: -12000000 | CC41: =BO41+BQ41+BS41+BU41+BW41+BY41+CA41 | CD41: =BP41+BR41+BT41+BV41+BX41+BZ41+CB41 | CE41: =CD41-CC41 | CF41: =AL41+AY41+BL41+CC41+H41 | CG41: =AM41+AZ41+BM41+CD41+I41 | CH41: =CF41-CG41
A42: Оплата труда | B42: Расход | H42: =C42+D42+E42+F42+G42 | I42: =#REF!+#REF!+#REF!+#REF!+#REF! | J42: =I42-H42 | AD42: -14340000 | AL42: =K42+AF42+AD42+AH42+AJ42 | AM42: =AB42+AE42+AG42+AI42+AK42 | AN42: =AM42-AL42 | AY42: =AO42+AQ42+AS42+AU42+AW42 | AZ42: =AP42+AR42+AT42+AV42+AX42 | BA42: =AZ42-AY42 | BH42: -1700000 | BL42: =BB42+BD42+BF42+BH42+BJ42 | BM42: =BC42+BE42+BG42+BI42+BK42 | BN42: =BM42-BL42 | CC42: =BO42+BQ42+BS42+BU42+BW42+BY42+CA42 | CD42: =BP42+BR42+BT42+BV42+BX42+BZ42+CB42 | CE42: =CD42-CC42 | CF42: =AL42+AY42+BL42+CC42+H42 | CG42: =AM42+AZ42+BM42+CD42+I42 | CH42: =CF42-CG42
A43: Охрана | B43: Расход | H43: =C43+D43+E43+F43+G43 | I43: =#REF!+#REF!+#REF!+#REF!+#REF! | J43: =I43-H43 | AL43: =K43+AF43+AD43+AH43+AJ43 | AM43: =AB43+AE43+AG43+AI43+AK43 | AN43: =AM43-AL43 | AQ43: -1000000 | AY43: =AO43+AQ43+AS43+AU43+AW43 | AZ43: =AP43+AR43+AT43+AV43+AX43 | BA43: =AZ43-AY43 | BL43: =BB43+BD43+BF43+BH43+BJ43 | BM43: =BC43+BE43+BG43+BI43+BK43 | BN43: =BM43-BL43 | CC43: =BO43+BQ43+BS43+BU43+BW43+BY43+CA43 | CD43: =BP43+BR43+BT43+BV43+BX43+BZ43+CB43 | CE43: =CD43-CC43 | CF43: =AL43+AY43+BL43+CC43+H43 | CG43: =AM43+AZ43+BM43+CD43+I43 | CH43: =CF43-CG43
A44: Платежи поставщикам Прочее | B44: Расход | E44: -180000 | H44: =C44+D44+E44+F44+G44 | I44: =#REF!+#REF!+#REF!+#REF!+#REF! | J44: =I44-H44 | AL44: =K44+AF44+AD44+AH44+AJ44 | AM44: =AB44+AE44+AG44+AI44+AK44 | AN44: =AM44-AL44 | AY44: =AO44+AQ44+AS44+AU44+AW44 | AZ44: =AP44+AR44+AT44+AV44+AX44 | BA44: =AZ44-AY44 | BL44: =BB44+BD44+BF44+BH44+BJ44 | BM44: =BC44+BE44+BG44+BI44+BK44 | BN44: =BM44-BL44 | CC44: =BO44+BQ44+BS44+BU44+BW44+BY44+CA44 | CD44: =BP44+BR44+BT44+BV44+BX44+BZ44+CB44 | CE44: =CD44-CC44 | CF44: =AL44+AY44+BL44+CC44+H44 | CG44: =AM44+AZ44+BM44+CD44+I44 | CH44: =CF44-CG44
A45: Производственные расходы | B45: Расход | H45: =C45+D45+E45+F45+G45 | I45: =#REF!+#REF!+#REF!+#REF!+#REF! | J45: =I45-H45 | AB45: =-335000 | AE45: -300000 | AL45: =K45+AF45+AD45+AH45+AJ45 | AM45: =AB45+AE45+AG45+AI45+AK45 | AN45: =AM45-AL45 | AS45: -88300 | AY45: =AO45+AQ45+AS45+AU45+AW45 | AZ45: =AP45+AR45+AT45+AV45+AX45 | BA45: =AZ45-AY45 | BD45: -150000 | BL45: =BB45+BD45+BF45+BH45+BJ45 | BM45: =BC45+BE45+BG45+BI45+BK45 | BN45: =BM45-BL45 | CC45: =BO45+BQ45+BS45+BU45+BW45+BY45+CA45 | CD45: =BP45+BR45+BT45+BV45+BX45+BZ45+CB45 | CE45: =CD45-CC45 | CF45: =AL45+AY45+BL45+CC45+H45 | CG45: =AM45+AZ45+BM45+CD45+I45 | CH45: =CF45-CG45
A46: Инвентарь | B46: Расход | H46: =C46+D46+E46+F46+G46 | I46: =#REF!+#REF!+#REF!+#REF!+#REF! | J46: =I46-H46 | AL46: =K46+AF46+AD46+AH46+AJ46 | AM46: =AB46+AE46+AG46+AI46+AK46 | AN46: =AM46-AL46 | AY46: =AO46+AQ46+AS46+AU46+AW46 | AZ46: =AP46+AR46+AT46+AV46+AX46 | BA46: =AZ46-AY46 | BL46: =BB46+BD46+BF46+BH46+BJ46 | BM46: =BC46+BE46+BG46+BI46+BK46 | BN46: =BM46-BL46 | CC46: =BO46+BQ46+BS46+BU46+BW46+BY46+CA46 | CD46: =BP46+BR46+BT46+BV46+BX46+BZ46+CB46 | CE46: =CD46-CC46 | CF46: =AL46+AY46+BL46+CC46+H46 | CG46: =AM46+AZ46+BM46+CD46+I46 | CH46: =CF46-CG46
A47: Униформа | B47: Расход | G47: -150000 | H47: =C47+D47+E47+F47+G47 | I47: =#REF!+#REF!+#REF!+#REF!+#REF! | J47: =I47-H47 | AB47: -39900 | AL47: =K47+AF47+AD47+AH47+AJ47 | AM47: =AB47+AE47+AG47+AI47+AK47 | AN47: =AM47-AL47 | AY47: =AO47+AQ47+AS47+AU47+AW47 | AZ47: =AP47+AR47+AT47+AV47+AX47 | BA47: =AZ47-AY47 | BL47: =BB47+BD47+BF47+BH47+BJ47 | BM47: =BC47+BE47+BG47+BI47+BK47 | BN47: =BM47-BL47 | CC47: =BO47+BQ47+BS47+BU47+BW47+BY47+CA47 | CD47: =BP47+BR47+BT47+BV47+BX47+BZ47+CB47 | CE47: =CD47-CC47 | CF47: =AL47+AY47+BL47+CC47+H47 | CG47: =AM47+AZ47+BM47+CD47+I47 | CH47: =CF47-CG47
A48: Упаковка | B48: Расход | G48: -2000000 | H48: =C48+D48+E48+F48+G48 | I48: =#REF!+#REF!+#REF!+#REF!+#REF! | J48: =I48-H48 | AB48: -132000 | AD48: -2500000 | AE48: -569817 | AJ48: -2000000 | AL48: =K48+AF48+AD48+AH48+AJ48 | AM48: =AB48+AE48+AG48+AI48+AK48 | AN48: =AM48-AL48 | AS48: -1500000 | AU48: -900000 | AW48: -600000 | AY48: =AO48+AQ48+AS48+AU48+AW48 | AZ48: =AP48+AR48+AT48+AV48+AX48 | BA48: =AZ48-AY48 | BD48: -1000000 | BH48: -1000000 | BJ48: -2000000 | BL48: =BB48+BD48+BF48+BH48+BJ48 | BM48: =BC48+BE48+BG48+BI48+BK48 | BN48: =BM48-BL48 | BQ48: -2000000 | CC48: =BO48+BQ48+BS48+BU48+BW48+BY48+CA48 | CD48: =BP48+BR48+BT48+BV48+BX48+BZ48+CB48 | CE48: =CD48-CC48 | CF48: =AL48+AY48+BL48+CC48+H48 | CG48: =AM48+AZ48+BM48+CD48+I48 | CH48: =CF48-CG48
A49: Хоз.товара | B49: Расход | H49: =C49+D49+E49+F49+G49 | I49: =#REF!+#REF!+#REF!+#REF!+#REF! | J49: =I49-H49 | AE49: -340760 | AL49: =K49+AF49+AD49+AH49+AJ49 | AM49: =AB49+AE49+AG49+AI49+AK49 | AN49: =AM49-AL49 | AW49: -300000 | AY49: =AO49+AQ49+AS49+AU49+AW49 | AZ49: =AP49+AR49+AT49+AV49+AX49 | BA49: =AZ49-AY49 | BL49: =BB49+BD49+BF49+BH49+BJ49 | BM49: =BC49+BE49+BG49+BI49+BK49 | BN49: =BM49-BL49 | CC49: =BO49+BQ49+BS49+BU49+BW49+BY49+CA49 | CD49: =BP49+BR49+BT49+BV49+BX49+BZ49+CB49 | CE49: =CD49-CC49 | CF49: =AL49+AY49+BL49+CC49+H49 | CG49: =AM49+AZ49+BM49+CD49+I49 | CH49: =CF49-CG49
A50: Погашение кредита и %% | B50: Расход | H50: =C50+D50+E50+F50+G50 | I50: =#REF!+#REF!+#REF!+#REF!+#REF! | J50: =I50-H50 | AL50: =K50+AF50+AD50+AH50+AJ50 | AM50: =AB50+AE50+AG50+AI50+AK50 | AN50: =AM50-AL50 | AY50: =AO50+AQ50+AS50+AU50+AW50 | AZ50: =AP50+AR50+AT50+AV50+AX50 | BA50: =AZ50-AY50 | BL50: =BB50+BD50+BF50+BH50+BJ50 | BM50: =BC50+BE50+BG50+BI50+BK50 | BN50: =BM50-BL50 | BO50: -1198352 | BU50: =-915358-1770150 | CC50: =BO50+BQ50+BS50+BU50+BW50+BY50+CA50 | CD50: =BP50+BR50+BT50+BV50+BX50+BZ50+CB50 | CE50: =CD50-CC50 | CF50: =AL50+AY50+BL50+CC50+H50 | CG50: =AM50+AZ50+BM50+CD50+I50 | CH50: =CF50-CG50
A51: Расходы по реализации Разные(Логистика) | B51: Расход | F51: -2000000 | H51: =C51+D51+E51+F51+G51 | I51: =#REF!+#REF!+#REF!+#REF!+#REF! | J51: =I51-H51 | AJ51: -2725000 | AL51: =K51+AF51+AD51+AH51+AJ51 | AM51: =AB51+AE51+AG51+AI51+AK51 | AN51: =AM51-AL51 | AW51: -1500000 | AY51: =AO51+AQ51+AS51+AU51+AW51 | AZ51: =AP51+AR51+AT51+AV51+AX51 | BA51: =AZ51-AY51 | BJ51: -2000000 | BL51: =BB51+BD51+BF51+BH51+BJ51 | BM51: =BC51+BE51+BG51+BI51+BK51 | BN51: =BM51-BL51 | CC51: =BO51+BQ51+BS51+BU51+BW51+BY51+CA51 | CD51: =BP51+BR51+BT51+BV51+BX51+BZ51+CB51 | CE51: =CD51-CC51 | CF51: =AL51+AY51+BL51+CC51+H51 | CG51: =AM51+AZ51+BM51+CD51+I51 | CH51: =CF51-CG51
A52: Ремонт помещений | B52: Расход | H52: =C52+D52+E52+F52+G52 | I52: =#REF!+#REF!+#REF!+#REF!+#REF! | J52: =I52-H52 | AL52: =K52+AF52+AD52+AH52+AJ52 | AM52: =AB52+AE52+AG52+AI52+AK52 | AN52: =AM52-AL52 | AY52: =AO52+AQ52+AS52+AU52+AW52 | AZ52: =AP52+AR52+AT52+AV52+AX52 | BA52: =AZ52-AY52 | BL52: =BB52+BD52+BF52+BH52+BJ52 | BM52: =BC52+BE52+BG52+BI52+BK52 | BN52: =BM52-BL52 | CC52: =BO52+BQ52+BS52+BU52+BW52+BY52+CA52 | CD52: =BP52+BR52+BT52+BV52+BX52+BZ52+CB52 | CE52: =CD52-CC52 | CF52: =AL52+AY52+BL52+CC52+H52 | CG52: =AM52+AZ52+BM52+CD52+I52 | CH52: =CF52-CG52
A53: Ремонт оборудования | B53: Расход | H53: =C53+D53+E53+F53+G53 | I53: =#REF!+#REF!+#REF!+#REF!+#REF! | J53: =I53-H53 | AL53: =K53+AF53+AD53+AH53+AJ53 | AM53: =AB53+AE53+AG53+AI53+AK53 | AN53: =AM53-AL53 | AY53: =AO53+AQ53+AS53+AU53+AW53 | AZ53: =AP53+AR53+AT53+AV53+AX53 | BA53: =AZ53-AY53 | BL53: =BB53+BD53+BF53+BH53+BJ53 | BM53: =BC53+BE53+BG53+BI53+BK53 | BN53: =BM53-BL53 | CC53: =BO53+BQ53+BS53+BU53+BW53+BY53+CA53 | CD53: =BP53+BR53+BT53+BV53+BX53+BZ53+CB53 | CE53: =CD53-CC53 | CF53: =AL53+AY53+BL53+CC53+H53 | CG53: =AM53+AZ53+BM53+CD53+I53 | CH53: =CF53-CG53
A54: Приобретение основных средств | B54: Расход | H54: =C54+D54+E54+F54+G54 | I54: =#REF!+#REF!+#REF!+#REF!+#REF! | J54: =I54-H54 | AL54: =K54+AF54+AD54+AH54+AJ54 | AM54: =AB54+AE54+AG54+AI54+AK54 | AN54: =AM54-AL54 | AY54: =AO54+AQ54+AS54+AU54+AW54 | AZ54: =AP54+AR54+AT54+AV54+AX54 | BA54: =AZ54-AY54 | BL54: =BB54+BD54+BF54+BH54+BJ54 | BM54: =BC54+BE54+BG54+BI54+BK54 | BN54: =BM54-BL54 | CC54: =BO54+BQ54+BS54+BU54+BW54+BY54+CA54 | CD54: =BP54+BR54+BT54+BV54+BX54+BZ54+CB54 | CE54: =CD54-CC54 | CF54: =AL54+AY54+BL54+CC54+H54 | CG54: =AM54+AZ54+BM54+CD54+I54 | CH54: =CF54-CG54
A55: Сырье Платежи поставщикам | B55: Расход | G55: -14000000 | H55: =C55+D55+E55+F55+G55 | I55: =#REF!+#REF!+#REF!+#REF!+#REF! | J55: =I55-H55 | AB55: -4844150 | AD55: -2000000 | AE55: -4111835 | AF55: -14000000 | AG55: =-699700-6755898 | AJ55: -14000000 | AL55: =K55+AF55+AD55+AH55+AJ55 | AM55: =AB55+AE55+AG55+AI55+AK55 | AN55: =AM55-AL55 | AQ55: -6000000 | AS55: -10000000 | AW55: -13000000 | AY55: =AO55+AQ55+AS55+AU55+AW55 | AZ55: =AP55+AR55+AT55+AV55+AX55 | BA55: =AZ55-AY55 | BD55: -12000000 | BJ55: -12000000 | BL55: =BB55+BD55+BF55+BH55+BJ55 | BM55: =BC55+BE55+BG55+BI55+BK55 | BN55: =BM55-BL55 | BO55: -30000000 | BQ55: -10000000 | CC55: =BO55+BQ55+BS55+BU55+BW55+BY55+CA55 | CD55: =BP55+BR55+BT55+BV55+BX55+BZ55+CB55 | CE55: =CD55-CC55 | CF55: =AL55+AY55+BL55+CC55+H55 | CG55: =AM55+AZ55+BM55+CD55+I55 | CH55: =CF55-CG55
A56: Электроэнергия | B56: Расход | H56: =C56+D56+E56+F56+G56 | I56: =#REF!+#REF!+#REF!+#REF!+#REF! | J56: =I56-H56 | AL56: =K56+AF56+AD56+AH56+AJ56 | AM56: =AB56+AE56+AG56+AI56+AK56 | AN56: =AM56-AL56 | AY56: =AO56+AQ56+AS56+AU56+AW56 | AZ56: =AP56+AR56+AT56+AV56+AX56 | BA56: =AZ56-AY56 | BL56: =BB56+BD56+BF56+BH56+BJ56 | BM56: =BC56+BE56+BG56+BI56+BK56 | BN56: =BM56-BL56 | BO56: -6100000 | CC56: =BO56+BQ56+BS56+BU56+BW56+BY56+CA56 | CD56: =BP56+BR56+BT56+BV56+BX56+BZ56+CB56 | CE56: =CD56-CC56 | CF56: =AL56+AY56+BL56+CC56+H56 | CG56: =AM56+AZ56+BM56+CD56+I56 | CH56: =CF56-CG56
A57: Итого по банку | B57: Расход | C57: 0 | D57: =SUM(D32:D56) | E57: =SUM(E32:E56) | F57: =SUM(F32:F56) | G57: =SUM(G32:G56) | H57: =SUM(H32:H56) | I57: =SUM(I32:I56) | J57: =I57-H57 | K57: =SUM(K32:K56) | AB57: =SUM(AB32:AB56) | AD57: =SUM(AD32:AD56) | AE57: =SUM(AE32:AE56) | AF57: =SUM(AF32:AF56) | AG57: =SUM(AG32:AG56) | AH57: =SUM(AH32:AH56) | AI57: =SUM(AI32:AI56) | AJ57: =SUM(AJ32:AJ56) | AK57: =SUM(AK32:AK56) | ... AM57: =SUM(AM32:AM56) | AN57: =AM57-AL57 | AO57: =SUM(AO32:AO56) | AP57: =SUM(AP32:AP56) | AQ57: =SUM(AQ32:AQ56) | AR57: =SUM(AR32:AR56) | AS57: =SUM(AS32:AS56) | AT57: =SUM(AT32:AT56) | AU57: =SUM(AU32:AU56) | AV57: =SUM(AV32:AV56) | ... AZ57: =SUM(AZ32:AZ56) | BA57: =AZ57-AY57 | BB57: =SUM(BB32:BB56) | BC57: =SUM(BC32:BC56) | BD57: =SUM(BD32:BD56) | BE57: =SUM(BE32:BE56) | BF57: =SUM(BF32:BF56) | BG57: =SUM(BG32:BG56) | BH57: =SUM(BH32:BH56) | BI57: =SUM(BI32:BI56) | ... BM57: =SUM(BM32:BM56) | BN57: =BM57-BL57 | BO57: =SUM(BO32:BO56) | BP57: =SUM(BP32:BP56) | BQ57: =SUM(BQ32:BQ56) | BR57: =SUM(BR32:BR56) | BS57: =SUM(BS32:BS56) | BT57: =SUM(BT32:BT56) | BU57: =SUM(BU32:BU56) | BV57: =SUM(BV32:BV56) | ... CD57: =SUM(CD32:CD56) | CE57: =CD57-CC57 | CF57: =SUM(CF32:CF56) | CG57: =SUM(CG32:CG56) | CH57: =CF57-CG57
A58: Подотчет (Рынок сырье, Рынок ТМЦ) | B58: Расход | F58: -500000 | G58: -500000 | H58: =C58+D58+E58+F58+G58 | I58: =#REF!+#REF!+#REF!+#REF!+#REF! | J58: =I58-H58 | K58: -300000 | AD58: -500000 | AF58: -600000 | AG58: -500000 | AH58: -500000 | AJ58: -500000 | AL58: =K58+AF58+AD58+AH58+AJ58 | AM58: =AB58+AE58+AG58+AI58+AK58 | AN58: =AM58-AL58 | AO58: -500000 | AQ58: -100000 | AS58: -600000 | AU58: -600000 | AW58: -500000 | AY58: =AO58+AQ58+AS58+AU58+AW58 | AZ58: =AP58+AR58+AT58+AV58+AX58 | BA58: =AZ58-AY58 | BD58: -600000 | BF58: -600000 | BH58: -1000000 | BL58: =BB58+BD58+BF58+BH58+BJ58 | BM58: =BC58+BE58+BG58+BI58+BK58 | BN58: =BM58-BL58 | BO58: -600000 | BQ58: -600000 | BS58: -500000 | CC58: =BO58+BQ58+BS58+BU58+BW58+BY58+CA58 | CD58: =BP58+BR58+BT58+BV79+BX58+BZ58+CB58 | CE58: =CD58-CC58 | CF58: =AL58+AY58+BL58+CC58+H58 | CG58: =AM58+AZ58+BM58+CD58+I58 | CH58: =CF58-CG58
A59: Административные расходы | B59: Расход | F59: -109000 | G59: -15000 | H59: =C59+D59+E59+F59+G59 | I59: =#REF!+#REF!+#REF!+#REF!+#REF! | J59: =I59-H59 | AB59: -70000 | AE59: =-28500-3530 | AJ59: -15000 | AL59: =K59+AF59+AD59+AH59+AJ59 | AM59: =AB59+AE59+AG59+AI59+AK59 | AN59: =AM59-AL59 | AW59: -15000 | AY59: =AO59+AQ59+AS59+AU59+AW59 | AZ59: =AP59+AR59+AT59+AV59+AX59 | BA59: =AZ59-AY59 | BB59: -3000 | BH59: -38000 | BJ59: -15000 | BL59: =BB59+BD59+BF59+BH59+BJ59 | BM59: =BC59+BE59+BG59+BI59+BK59 | BN59: =BM59-BL59 | CC59: =BO59+BQ59+BS59+BU59+BW59+BY59+CA59 | CD59: =BP59+BR59+BT59+BV59+BX59+BZ59+CB59 | CE59: =CD59-CC59 | CF59: =AL59+AY59+BL59+CC59+H59 | CG59: =AM59+AZ59+BM59+CD59+I59 | CH59: =CF59-CG59
A60: Представительские расходы | B60: Расход | G60: -60329 | H60: =C60+D60+E60+F60+G60 | I60: =#REF!+#REF!+#REF!+#REF!+#REF! | J60: =I60-H60 | AL60: =K60+AF60+AD60+AH60+AJ60 | AM60: =AB60+AE60+AG60+AI60+AK60 | AN60: =AM60-AL60 | AY60: =AO60+AQ60+AS60+AU60+AW60 | AZ60: =AP60+AR60+AT60+AV60+AX60 | BA60: =AZ60-AY60 | BL60: =BB60+BD60+BF60+BH60+BJ60 | BM60: =BC60+BE60+BG60+BI60+BK60 | BN60: =BM60-BL60 | CC60: =BO60+BQ60+BS60+BU60+BW60+BY60+CA60 | CD60: =BP60+BR60+BT60+BV60+BX60+BZ60+CB60 | CE60: =CD60-CC60 | CF60: =AL60+AY60+BL60+CC60+H60 | CG60: =AM60+AZ60+BM60+CD60+I60 | CH60: =CF60-CG60
A61: Аренда квартир | B61: Расход | H61: =C61+D61+E61+F61+G61 | I61: =#REF!+#REF!+#REF!+#REF!+#REF! | J61: =I61-H61 | AL61: =K61+AF61+AD61+AH61+AJ61 | AM61: =AB61+AE61+AG61+AI61+AK61 | AN61: =AM61-AL61 | AO61: =-175000-300000 | AY61: =AO61+AQ61+AS61+AU61+AW61 | AZ61: =AP61+AR61+AT61+AV61+AX61 | BA61: =AZ61-AY61 | BH61: -350149 | BL61: =BB61+BD61+BF61+BH61+BJ61 | BM61: =BC61+BE61+BG61+BI61+BK61 | BN61: =BM61-BL61 | CC61: =BO61+BQ61+BS61+BU61+BW61+BY61+CA61 | CD61: =BP61+BR61+BT61+BV61+BX61+BZ61+CB61 | CE61: =CD61-CC61 | CF61: =AL61+AY61+BL61+CC61+H61 | CG61: =AM61+AZ61+BM61+CD61+I61 | CH61: =CF61-CG61
A62: Налоги и другие платежи в бюджет | B62: Расход | H62: =C62+D62+E62+F62+G62 | I62: =#REF!+#REF!+#REF!+#REF!+#REF! | J62: =I62-H62 | AL62: =K62+AF62+AD62+AH62+AJ62 | AM62: =AB62+AE62+AG62+AI62+AK62 | AN62: =AM62-AL62 | AY62: =AO62+AQ62+AS62+AU62+AW62 | AZ62: =AP62+AR62+AT62+AV62+AX62 | BA62: =AZ62-AY62 | BL62: =BB62+BD62+BF62+BH62+BJ62 | BM62: =BC62+BE62+BG62+BI62+BK62 | BN62: =BM62-BL62 | CC62: =BO62+BQ62+BS62+BU62+BW62+BY62+CA62 | CD62: =BP62+BR62+BT62+BV62+BX62+BZ62+CB62 | CE62: =CD62-CC62 | CF62: =AL62+AY62+BL62+CC62+H62 | CG62: =AM62+AZ62+BM62+CD62+I62 | CH62: =CF62-CG62
A63: Маркетинг | B63: Расход | H63: =C63+D63+E63+F63+G63 | I63: =#REF!+#REF!+#REF!+#REF!+#REF! | J63: =I63-H63 | AH63: -450000 | AL63: =K63+AF63+AD63+AH63+AJ63 | AM63: =AB63+AE63+AG63+AI63+AK63 | AN63: =AM63-AL63 | AY63: =AO63+AQ63+AS63+AU63+AW63 | AZ63: =AP63+AR63+AT63+AV63+AX63 | BA63: =AZ63-AY63 | BL63: =BB63+BD63+BF63+BH63+BJ63 | BM63: =BC63+BE63+BG63+BI63+BK63 | BN63: =BM63-BL63 | CC63: =BO63+BQ63+BS63+BU63+BW63+BY63+CA63 | CD63: =BP63+BR63+BT63+BV63+BX63+BZ63+CB63 | CE63: =CD63-CC63 | CF63: =AL63+AY63+BL63+CC63+H63 | CG63: =AM63+AZ63+BM63+CD63+I63 | CH63: =CF63-CG63
A64: Оплата труда | B64: Расход | G64: -2500000 | H64: =C64+D64+E64+F64+G64 | I64: =#REF!+#REF!+#REF!+#REF!+#REF! | J64: =I64-H64 | AD64: -1000000 | AE64: -2481189 | AF64: -2000000 | AG64: -2346182 | AH64: -2000000 | AJ64: -1500000 | AL64: =K64+AF64+AD64+AH64+AJ64 | AM64: =AB64+AE64+AG64+AI64+AK64 | AN64: =AM64-AL64 | AO64: -650000 | AS64: -12500000 | AU64: -8000000 | AW64: -7000000 | AY64: =AO64+AQ64+AS64+AU64+AW64 | AZ64: =AP64+AR64+AT64+AV64+AX64 | BA64: =AZ64-AY64 | BH64: =-6000000 | BJ64: -7000000 | BL64: =BB64+BD64+BF64+BH64+BJ64 | BM64: =BC64+BE64+BG64+BI64+BK64 | BN64: =BM64-BL64 | BO64: -5000000 | BQ64: -2000000 | BU64: -2000000 | CC64: =BO64+BQ64+BS64+BU64+BW64+BY64+CA64 | CD64: =BP64+BR64+BT64+BV64+BX64+BZ64+CB64 | CE64: =CD64-CC64 | CF64: =AL64+AY64+BL64+CC64+H64 | CG64: =AM64+AZ64+BM64+CD64+I64 | CH64: =CF64-CG64
A65: Платежи поставщикам Прочее | B65: Расход | H65: =C65+D65+E65+F65+G65 | I65: =#REF!+#REF!+#REF!+#REF!+#REF! | J65: =I65-H65 | AL65: =K65+AF65+AD65+AH65+AJ65 | AM65: =AB65+AE65+AG65+AI65+AK65 | AN65: =AM65-AL65 | AY65: =AO65+AQ65+AS65+AU65+AW65 | AZ65: =AP65+AR65+AT65+AV65+AX65 | BA65: =AZ65-AY65 | BL65: =BB65+BD65+BF65+BH65+BJ65 | BM65: =BC65+BE65+BG65+BI65+BK65 | BN65: =BM65-BL65 | CC65: =BO65+BQ65+BS65+BU65+BW65+BY65+CA65 | CD65: =BP65+BR65+BT65+BV65+BX65+BZ65+CB65 | CE65: =CD65-CC65 | CF65: =AL65+AY65+BL65+CC65+H65 | CG65: =AM65+AZ65+BM65+CD65+I65 | CH65: =CF65-CG65
A66: Производственные расходы | B66: Расход | F66: -48000 | H66: =C66+D66+E66+F66+G66 | I66: =#REF!+#REF!+#REF!+#REF!+#REF! | J66: =I66-H66 | K66: -48000 | AB66: -48000 | AE66: =-30000 | AH66: -48000 | AL66: =K66+AF66+AD66+AH66+AJ66 | AM66: =AB66+AE66+AG66+AI66+AK66 | AN66: =AM66-AL66 | AO66: -42000 | AQ66: -42000 | AY66: =AO66+AQ66+AS66+AU66+AW66 | AZ66: =AP66+AR66+AT66+AV66+AX66 | BA66: =AZ66-AY66 | BD66: -48000 | BH66: -48000 | BL66: =BB66+BD66+BF66+BH66+BJ66 | BM66: =BC66+BE66+BG66+BI66+BK66 | BN66: =BM66-BL66 | BQ66: -48000 | CC66: =BO66+BQ66+BS66+BU66+BW66+BY66+CA66 | CD66: =BP66+BR66+BT66+BV66+BX66+BZ66+CB66 | CE66: =CD66-CC66 | CF66: =AL66+AY66+BL66+CC66+H66 | CG66: =AM66+AZ66+BM66+CD66+I66 | CH66: =CF66-CG66
A67: Инвентарь | B67: Расход | F67: =-15000-69000 | G67: -144600 | H67: =C67+D67+E67+F67+G67 | I67: =#REF!+#REF!+#REF!+#REF!+#REF! | J67: =I67-H67 | K67: =-15000-27000 | AD67: -40000 | AL67: =K67+AF67+AD67+AH67+AJ67 | AM67: =AB67+AE67+AG67+AI67+AK67 | AN67: =AM67-AL67 | AQ67: =-116000-19100 | AY67: =AO67+AQ67+AS67+AU67+AW67 | AZ67: =AP67+AR67+AT67+AV67+AX67 | BA67: =AZ67-AY67 | BD67: -32000 | BF67: -35000 | BL67: =BB67+BD67+BF67+BH67+BJ67 | BM67: =BC67+BE67+BG67+BI67+BK67 | BN67: =BM67-BL67 | CC67: =BO67+BQ67+BS67+BU67+BW67+BY67+CA67 | CD67: =BP67+BR67+BT67+BV67+BX67+BZ67+CB67 | CE67: =CD67-CC67 | CF67: =AL67+AY67+BL67+CC67+H67 | CG67: =AM67+AZ67+BM67+CD67+I67 | CH67: =CF67-CG67
A68: Погашение кредита и %% | B68: Расход | H68: =C68+D68+E68+F68+G68 | I68: =#REF!+#REF!+#REF!+#REF!+#REF! | J68: =I68-H68 | AL68: =K68+AF68+AD68+AH68+AJ68 | AM68: =AB68+AE68+AG68+AI68+AK68 | AN68: =AM68-AL68 | AY68: =AO68+AQ68+AS68+AU68+AW68 | AZ68: =AP68+AR68+AT68+AV68+AX68 | BA68: =AZ68-AY68 | BL68: =BB68+BD68+BF68+BH68+BJ68 | BM68: =BC68+BE68+BG68+BI68+BK68 | BN68: =BM68-BL68 | CC68: =BO68+BQ68+BS68+BU68+BW68+BY68+CA68 | CD68: =BP68+BR68+BT68+BV68+BX68+BZ68+CB68 | CE68: =CD68-CC68 | CF68: =AL68+AY68+BL68+CC68+H68 | CG68: =AM68+AZ68+BM68+CD68+I68 | CH68: =CF68-CG68
A69: Хоз.товара | B69: Расход | H69: =C69+D69+E69+F69+G69 | I69: =#REF!+#REF!+#REF!+#REF!+#REF! | J69: =I69-H69 | AL69: =K69+AF69+AD69+AH69+AJ69 | AM69: =AB69+AE69+AG69+AI69+AK69 | AN69: =AM69-AL69 | AY69: =AO69+AQ69+AS69+AU69+AW69 | AZ69: =AP69+AR69+AT69+AV69+AX69 | BA69: =AZ69-AY69 | BL69: =BB69+BD69+BF69+BH69+BJ69 | BM69: =BC69+BE69+BG69+BI69+BK69 | BN69: =BM69-BL69 | CC69: =BO69+BQ69+BS69+BU69+BW69+BY69+CA69 | CD69: =BP69+BR69+BT69+BV69+BX69+BZ69+CB69 | CE69: =CD69-CC69 | CF69: =AL69+AY69+BL69+CC69+H69 | CG69: =AM69+AZ69+BM69+CD69+I69 | CH69: =CF69-CG69
A70: Канц.товары | B70: Расход | H70: =C70+D70+E70+F70+G70 | I70: =#REF!+#REF!+#REF!+#REF!+#REF! | J70: =I70-H70 | AL70: =K70+AF70+AD70+AH70+AJ70 | AM70: =AB70+AE70+AG70+AI70+AK70 | AN70: =AM70-AL70 | AY70: =AO70+AQ70+AS70+AU70+AW70 | AZ70: =AP70+AR70+AT70+AV70+AX70 | BA70: =AZ70-AY70 | BL70: =BB70+BD70+BF70+BH70+BJ70 | BM70: =BC70+BE70+BG70+BI70+BK70 | BN70: =BM70-BL70 | CC70: =BO70+BQ70+BS70+BU70+BW70+BY70+CA70 | CD70: =BP70+BR70+BT70+BV70+BX70+BZ70+CB70 | CE70: =CD70-CC70 | CF70: =AL70+AY70+BL70+CC70+H70 | CG70: =AM70+AZ70+BM70+CD70+I70 | CH70: =CF70-CG70
A71: Расходы по реализации Разные | B71: Расход | H71: =C71+D71+E71+F71+G71 | I71: =#REF!+#REF!+#REF!+#REF!+#REF! | J71: =I71-H71 | AL71: =K71+AF71+AD71+AH71+AJ71 | AM71: =AB71+AE71+AG71+AI71+AK71 | AN71: =AM71-AL71 | AY71: =AO71+AQ71+AS71+AU71+AW71 | AZ71: =AP71+AR71+AT71+AV71+AX71 | BA71: =AZ71-AY71 | BL71: =BB71+BD71+BF71+BH71+BJ71 | BM71: =BC71+BE71+BG71+BI71+BK71 | BN71: =BM71-BL71 | CC71: =BO71+BQ71+BS71+BU71+BW71+BY71+CA71 | CD71: =BP71+BR71+BT71+BV71+BX71+BZ71+CB71 | CE71: =CD71-CC71 | CF71: =AL71+AY71+BL71+CC71+H71 | CG71: =AM71+AZ71+BM71+CD71+I71 | CH71: =CF71-CG71
A72: Ремонт помещений | B72: Расход | H72: =C72+D72+E72+F72+G72 | I72: =#REF!+#REF!+#REF!+#REF!+#REF! | J72: =I72-H72 | AL72: =K72+AF72+AD72+AH72+AJ72 | AM72: =AB72+AE72+AG72+AI72+AK72 | AN72: =AM72-AL72 | AY72: =AO72+AQ72+AS72+AU72+AW72 | AZ72: =AP72+AR72+AT72+AV72+AX72 | BA72: =AZ72-AY72 | BL72: =BB72+BD72+BF72+BH72+BJ72 | BM72: =BC72+BE72+BG72+BI72+BK72 | BN72: =BM72-BL72 | CC72: =BO72+BQ72+BS72+BU72+BW72+BY72+CA72 | CD72: =BP72+BR72+BT72+BV72+BX72+BZ72+CB72 | CE72: =CD72-CC72 | CF72: =AL72+AY72+BL72+CC72+H72 | CG72: =AM72+AZ72+BM72+CD72+I72 | CH72: =CF72-CG72
A73: Ремонт оборудования | B73: Расход | F73: -171500 | H73: =C73+D73+E73+F73+G73 | I73: =#REF!+#REF!+#REF!+#REF!+#REF! | J73: =I73-H73 | AD73: -212000 | AL73: =K73+AF73+AD73+AH73+AJ73 | AM73: =AB73+AE73+AG73+AI73+AK73 | AN73: =AM73-AL73 | AQ73: -148000 | AY73: =AO73+AQ73+AS73+AU73+AW73 | AZ73: =AP73+AR73+AT73+AV73+AX73 | BA73: =AZ73-AY73 | BF73: -187500 | BL73: =BB73+BD73+BF73+BH73+BJ73 | BM73: =BC73+BE73+BG73+BI73+BK73 | BN73: =BM73-BL73 | CC73: =BO73+BQ73+BS73+BU73+BW73+BY73+CA73 | CD73: =BP73+BR73+BT73+BV73+BX73+BZ73+CB73 | CE73: =CD73-CC73 | CF73: =AL73+AY73+BL73+CC73+H73 | CG73: =AM73+AZ73+BM73+CD73+I73 | CH73: =CF73-CG73
A74: Приобретение основных средств | B74: Расход | H74: =C74+D74+E74+F74+G74 | I74: =#REF!+#REF!+#REF!+#REF!+#REF! | J74: =I74-H74 | AL74: =K74+AF74+AD74+AH74+AJ74 | AM74: =AB74+AE74+AG74+AI74+AK74 | AN74: =AM74-AL74 | AY74: =AO74+AQ74+AS74+AU74+AW74 | AZ74: =AP74+AR74+AT74+AV74+AX74 | BA74: =AZ74-AY74 | BL74: =BB74+BD74+BF74+BH74+BJ74 | BM74: =BC74+BE74+BG74+BI74+BK74 | BN74: =BM74-BL74 | CC74: =BO74+BQ74+BS74+BU74+BW74+BY74+CA74 | CD74: =BP74+BR74+BT74+BV74+BX74+BZ74+CB74 | CE74: =CD74-CC74 | CF74: =AL74+AY74+BL74+CC74+H74 | CG74: =AM74+AZ74+BM74+CD74+I74 | CH74: =CF74-CG74
